Workbook

Sheet Batch1 calculation
D2: Unit KRW
A3: Phase 1 | C3: Paid amount for each site | D3: Total Paid amount
A4: 김한용 | B4: 드림1 | C4: 303473480 | D4: =SUM(C4:C7) -> 1210404780
B5: 드림2 | C5: 302270100
B6: 제일테크1 | C6: 302330600
B7: 제일테크2 | C7: 302330600
A8: 이홍연 | B8: 가시솔라1 (오은주) | C8: 302379000 | D8: =SUM(C8:C11) -> 1209503900
B9: 가시솔라2 (오은주) | C9: 302379000
B10: 행원햇빛 | C10: 302372950
B11: 와이제이 수산 | C11: 302372950
F13: Unit KRW
A14: Phase 2 | C14: Paid amount for each site | D14: Total Paid amount | E14: Divide for Phase 1 | F14: Amount of Divided into 5
A15: 김한용 | B15: 빛나리2 | C15: 54945000 | D15: =SUM(C15:C19) -> 211365000 | E15: 4 | F15: =D15/E15 -> 52841250
B16: 빛나리3 | C16: 11000000
B17: 빛나리4 | C17: 35530000
B18: 빛나리7 | C18: 54945000
B19: 흥산2 (김명현) | C19: 54945000
A20: 이홍연 | B20: 가시솔라1 (오은주) | C20: 54945000 | D20: =SUM(C20:C24) -> 207790000 | E20: 4 | F20: =D20/E20 -> 51947500
B21: 가시솔라2 (오은주) | C21: 7040000
B22: 행원햇빛 | C22: 54945000
B23: 와이제이 덕천 | C23: 54945000
B24: 와이제이 수산 | C24: 35915000

Sheet Week news
A1: Korea Weekly Update
A3: SN | B3: Subject | C3: Discription
A4: 1 | B4: Political Environment Update | C4: a. The Prime Minister is in power, the President is being slowly removed from his functions and the former Minister of Defense jailed. The country is likely to be preparing for elections in 2025 and few is expected from the government side in terms of new policies. This is basically a frozen environment. However, in the beginning of next year 2 major things are expected on REN side: grid release schedule and PPA price adjustment for DG.
A5: 2 | B5: KEPCO / Grid availability | C5: a. Grid release tips this week shows 1.3GW of grid release in Honam and Jeju regions announcement in January 2025. Originated plans to look after a few more ground PV from the pipeline that had secured GIA to add 3 to 5 MW to Batch 1 and 2 and completed a 21MW+ GM PV batch overall.
C6: b. More GW are expected to be released in 2026 as MoTIE extended the period of construction to frozen projects having received connection to YE 2025. Meaning many projects with limited capital may be on sale in 2025.
A7: 3 | B7: 4MWp PPA at 180won/KRW | C7: a. RWE Energy Trading reached out to Originated to get an urgent 4MWp RtB available for cPPA for one of their coal power producer clients. The expected price per MWh is said to be 180,000KRW (EUR120)
C8: b. Detailed meeting about contracting planned on Dec. 30th.
A11: Outstanding by year end
A13: SN | B13: Project | C13: What to do next
A14: 1 | B14: Ground mounted Batch 1: 8MW | C14: a. EPC contract b. pre-PPA binding contract c. KEPCO grid release date
A15: 2 | B15: Ground mounted Batch 2: 6.8MW | C15: a. APA x 6 / SPA x 4 b. LDD and taxation DD final c. 4MWp PPA with RWE @ 180KRW/kWh d. Transfer of c. 2m EUR
A16: 3 | B16: DG organic 3.633MW (+8MW tender) | C16: a. SPA completed b. Approval of 3.2MW c. Sign lease d. Transfer of 20% DEVEX to Solar City e. (Tender 8MW DG Port Kukyang Logitek)
A17: 4 | B17: Wind 37.2MW | C17: a. NBO b. LDD, Technical DD, Texation DD c. SPA/SHA/DSA d. Site extension + 37.2MW
B18: Conclusion Korea on the map with 55.7 locked in pipeline for construction in 2025 18.5MW and development 37.2MW. Next lock in campaign: + 13.8MW of DG in pipeline to be locked in by end of January 2025.

Sheet ref.Phase 1 (2)
B2: Phase 1 | L2: [단위 : 원]
B3: 구분 | C3: 지급일자 | D3: YJ NANSAN1 | E3: YJ NANSAN2 | F3: YJ GASI1 | G3: YJ GASI2 | H3: Dream1 | I3: Dream2 | J3: Jeil Tech1 | K3: Jeil Tech2 | L3: 합계 | O3: 0.1
B4: 발전용량(kw) | D4: 999.58 | E4: 999.58 | F4: 999.6 | G4: 999.6 | H4: 999.24 | I4: 999.24 | J4: 999.44 | K4: 999.44 | L4: =+SUM(E4:K4) -> 6996.14
B5: 입금액(EUR) | D5: 210448.88 | E5: 210448.88 | F5: 210453.09 | G5: 210453.09 | H5: 211354.04 | I5: 210377.3 | J5: 210419.4 | K5: 210419.4 | L5: =+SUM(E5:K5) -> 1473925.2
B6: 전체금액 | D6: =+D7/$B$7 -> 549769000 | E6: =+E7/$B$7 -> 549769000 | F6: =+F7/$B$7 -> 549780000 | G6: =+G7/$B$7 -> 549780000 | H6: =+H4*550000000/1000 -> 549582000 | I6: =+I7/$B$7 -> 549582000 | J6: =+J7/$B$7 -> 549692000 | K6: =+K7/$B$7 -> 549692000 | L6: =+L7/$B$7 -> 3.8504286e+09
B7: 0.55 | D7: 302372950 | E7: 302372950 | F7: 302379000 | G7: 302379000 | H7: 303673480 | I7: 302270100 | J7: 302330600 | K7: 302330600 | L7: =+SUM(E7:K7) -> 2117735730
B8: 추가입금액 (10%) | D8: =+D20*$O$3 -> 54976900 | E8: =+E20*$O$3 -> 54976900 | F8: =+F20*$O$3 -> 54978000 | G8: =+G20*$O$3 -> 54978000 | H8: =+H20*$O$3 -> 55213360 | I8: =+I20*$O$3 -> 54958200 | J8: =+J20*$O$3 -> 54969200 | K8: =+K20*$O$3 -> 54969200 | L8: =+SUM(E8:K8) -> 385042860
B9: 입금 금액 | D9: =+$C$18/4 -> 51947500 | E9: =+$C$18/4 -> 51947500 | F9: =+$C$18/4 -> 51947500 | G9: =+$C$18/4 -> 51947500 | H9: =+$C$17/4 -> 52841250 | I9: =+$C$17/4 -> 52841250 | J9: =+$C$17/4 -> 52841250 | K9: =+$C$17/4 -> 52841250 | L9: =+SUM(E9:K9) -> 367207500
B10: 잔금 | D10: =+D6-D7-D9 -> 195448550 | E10: =+E6-E7-E9 -> 195448550 | F10: =+F6-F7-F9 -> 195453500 | G10: =+G6-G7-G9 -> 195453500 | H10: =+H6-H7-H9 -> 193067270 | I10: =+I6-I7-I9 -> 194470650 | J10: =+J6-J7-J9 -> 194520150 | K10: =+K6-K7-K9 -> 194520150 | L10: =+L6-L7-L9 -> 1.3654854e+09
B11: 입금처 | D11: YJ SOLAR CO.LTD | E11: YJ SOLAR CO.LTD | F11: YJ SOLAR CO.LTD | G11: YJ SOLAR CO.LTD | H11: KIM HAN YONG | I11: LEE SU KYUNG | J11: KIM JUNG HEE | K11: JEIL TECH CO.LTD | L11: YJ SOLAR CO.LTD
D12: =+D9+D7 -> 354320450 | E12: =+E9+E7 -> 354320450 | F12: =+F9+F7 -> 354326500 | G12: =+G9+G7 -> 354326500 | H12: =+H9+H7 -> 356514730 | I12: =+I9+I7 -> 355111350 | J12: =+J9+J7 -> 355171850 | K12: =+K9+K7 -> 355171850
D13: 이홍연 | E13: 이홍연 | F13: 이홍연 | G13: 이홍연 | H13: 김한용 | I13: 김한용 | J13: 김한용 | K13: 김한용
B14: 0.05 | D14: =+D6*$B$14 -> 27488450 | E14: =+E6*$B$14 -> 27488450 | F14: =+F6*$B$14 -> 27489000 | G14: =+G6*$B$14 -> 27489000 | H14: =+H6*$B$14 -> 27479100 | I14: =+I6*$B$14 -> 27479100 | J14: =+J6*$B$14 -> 27484600 | K14: =+K6*$B$14 -> 27484600
B15: 0.3 | D15: =+D6*$B$15 -> 164930700 | E15: =+E6*$B$15 -> 164930700 | F15: =+F6*$B$15 -> 164934000 | G15: =+G6*$B$15 -> 164934000 | H15: =+H6*$B$15 -> 164874600 | I15: =+I6*$B$15 -> 164874600 | J15: =+J6*$B$15 -> 164907600 | K15: =+K6*$B$15 -> 164907600
D16: =+D4*550000000/1000-D6 -> 0 | E16: =+E4*550000000/1000-E6 -> 0 | F16: =+F4*550000000/1000-F6 -> 0 | G16: =+G4*550000000/1000-G6 -> 0 | H16: =+H4*550000000/1000-H6 -> 0 | I16: =+I4*550000000/1000-I6 -> 0 | J16: =+J4*550000000/1000-J6 -> 0 | K16: =+K4*550000000/1000-K6 -> 0
B17: 김한용 | C17: =+'ref.Phase 1 (2)'!C33 -> 211365000
B18: 이홍연 | C18: =+'ref.Phase 1 (2)'!C34 -> 207790000 | E18: =+C18/4 -> 51947500
B20: 전체금액 | D20: =+D7/$B$7 -> 549769000 | E20: =+E7/$B$7 -> 549769000 | F20: =+F7/$B$7 -> 549780000 | G20: =+G7/$B$7 -> 549780000 | H20: =+H7/$B$7 -> 552133600 | I20: =+I7/$B$7 -> 549582000 | J20: =+J7/$B$7 -> 549692000 | K20: =+K7/$B$7 -> 549692000
B21: 0.55 | D21: =+D20*$B$21=D7 -> TRUE | E21: =+E20*$B$21=E7 -> TRUE | F21: =+F20*$B$21=F7 -> TRUE | G21: =+G20*$B$21=G7 -> TRUE | H21: =+H20*$B$21=H7 -> TRUE | I21: =+I20*$B$21=I7 -> TRUE | J21: =+J20*$B$21=J7 -> TRUE | K21: =+K20*$B$21=K7 -> TRUE
D22: =+D7/D6 -> 0.55 | E22: =+E7/E6 -> 0.55 | F22: =+F7/F6 -> 0.55 | G22: =+G7/G6 -> 0.55 | H22: =+H7/H6 -> 0.55255354 | I22: =+I7/I6 -> 0.55 | J22: =+J7/J6 -> 0.55 | K22: =+K7/K6 -> 0.55
B25: Phase 2 | M25: [단위 : 원]
B26: 구분 | C26: 지급일자 | D26: Hangwon Hatbit PV | E26: YJ SUSAN PV | F26: Gasi Solar 1PV | G26: Gasi Solar 2PV | H26: Bitnari 2 | I26: Bitnari 3 | J26: Bitnari 4 | K26: Bitnari 7 | L26: Heungsan 2 PV | M26: YJ DUCKHUN | O26: 0.1
B27: 발전용량(kw)
B28: 입금액(EUR) | D28: 38418.78 | E28: 25112.57 | F28: 38418.78 | G28: 4922.53 | H28: 38418.78 | I28: 7691.45 | J28: 24843.37 | K28: 38418.78 | L28: 38418.78 | M28: 38418.78
B29: 0.1 | D29: 54945000 | E29: 35915000 | F29: 54945000 | G29: 7040000 | H29: 54945000 | I29: 11000000 | J29: 35530000 | K29: 54945000 | L29: 54945000 | M29: 54945000 | N29: =SUM(E29:M29) -> 364210000
B31: 입금처 | D31: YJ SOLAR CO.LTD | E31: YJ SOLAR CO.LTD | F31: OH EUN JU | G31: OH EUN JU | H31: KIM HAN YONG | I31: KIM HAN YONG | J31: KIM HAN YONG | K31: KIM HAN YONG | L31: KIM MYUNG HYUN | M31: YJ SOLAR CO.LTD
D32: 이홍연 | E32: 이홍연 | F32: 이홍연 | G32: 이홍연 | H32: 김한용 | I32: 김한용 | J32: 김한용 | K32: 김한용 | L32: 김한용 | M32: 이홍연
B33: 김한용 | C33: =+H29+I29+J29+K29+L29 -> 211365000
B34: 이홍연 | C34: =+E29+F29+G29+D29+M29 -> 207790000
C35: =+C33+C34=N29 -> FALSE

Sheet 관련 현황
B3: ▶ 작성 내용
B4: 1. Pipeline에 있는 각 Project 별 내용을 SPV별로 나눠 관리를 하기 위해 SPV별로 정리
B5: 2. 승인 받은 DG (Liquidity projection for April & May 2025) 관련 내용을 근거로 작성(지급일자)
B6: - 지급일자 4월로 승인받았으나 자금 지급이 늦어짐으로 4월을 5월로 지급하는 일정으로 작성 됨
B8: ▶ 지급일자 확인
B9: 1. 지급일자는 DEVEX 추가 지급 일정이 확정 됐을때 자료 보완 필요(계속적인 업데이트 필요)
B10: - SPV 별 자금 현황 확인 및 Broker(솔라시티, 에너지플랜 등)과 협의 후 일정 업데이트
B12: ▶Project 추가 여부
B13: 1. 그린볼트 승인 및 자금 투여 시 해당 SPV에 추가 업데이트 진행
B14: 2. 현 추가 사업자등록 완료 된 4,5,8,9,10호의 사업자도 추가 진행 가능

Sheet Summary
B2: Balance by SPV
I3: [Dated : 2025.10.04]
B4: SPV | C4: Currency | D4: =+[1]자금현황!E5 -> Balance | E4: KRW | F4: to be Paid in Oct. | G4: Requested Amount (KRW) | H4: Requested Amount (EUR) | I4: Details
B5: Bolt Taeyanggwang 1HO | C5: KRW | D5: 115042926 | E5: =+D5 -> 115042926 | I5: Please check the following.
C6: EUR | D6: 299993.87 | E6: =+D6*$E$15 -> 4.4099099e+08
C7: KRW Total | E7: =SUM(E5:E6) -> 5.5603391e+08 | F7: =+'Amount to be paid in 2025(1004)'!P52 -> 2497132990 | G7: =+F7-E7 -> 1.9410991e+09 | H7: =+G7/$E$15 -> 1320475.6
B8: POSN2HO | C8: KRW | D8: 5130070 | E8: =+D8 -> 5130070 | I8: Please check the following.
C9: EUR | D9: 0 | E9: =+D9*$E$15 -> 0
C10: KRW Total | E10: =SUM(E8:E9) -> 5130070 | F10: =+D21+D22+D23 -> 1242149643 | G10: =+F10-E10 -> 1237019573 | H10: =+G10/$E$15 -> 841509.91
B11: Total | C11: KRW | D11: =+D5 -> 115042926 | E11: =+E5 -> 115042926
C12: EUR | D12: =+D6 -> 299993.87 | E12: =+D12*$E$15 -> 4.4099099e+08
C13: KRW Total | E13: =SUM(E11:E12) -> 5.5603391e+08
D15: Exchange | E15: 1470
B18: SPV | C18: Category | D18: Requested Amount (KRW) | E18: Requested Amount (EUR) | F18: Details
B19: Bolt Taeyanggwang 1HO | C19: CAPEX | D19: =+'Amount to be paid in 2025(1004)'!P30 -> 2430003290 | E19: =+D19/$E$15 -> 1653063.5 | F19: 50% of GM_Batch1 4MWp payment is required. Scheduled payment date: 13 Oct.
C20: DEVEX | D20: =+'Amount to be paid in 2025(1004)'!P50 -> 67129700 | E20: =+D20/$E$15 -> 45666.463 | F20: Payment of the outstanding amount for GM_Batch1 4MWp is scheduled.
B21: POSN2HO | C21: CAPEX | D21: =+'Amount to be paid_POSN2HO'!D28+'Amount to be paid_POSN2HO'!D29+'Amount to be paid_POSN2HO'!D30 -> 9.3134947e+08 | E21: =+D21/$E$15 -> 633571.07 | F21: Excluding the previously paid Grid Connection Fee and considering the additional requested amount, \931,349,470 (EUR 633,571.07) is requested.
C22: DEVEX | D22: =+'Amount to be paid_POSN2HO'!O22 -> 123494400 | E22: =+D22/$E$15 -> 84009.796 | F22: Funds are requested for the payment of 20% of the acquisition amount.
C23: OPEX | D23: =+'Amount to be paid_POSN2HO'!D31+'Amount to be paid_POSN2HO'!D32 -> 187305773 | E23: =+D23/$E$15 -> 127418.89 | F23: Payment of \187,305,773 (EUR 127,418.89) is requested for the Prepaid Lease Fee and OE Fee.

Sheet DEVEX Payment Status
B2: DEVEX Payment Status
B4: SPV | C4: NO | D4: Name of Project | E4: Capacity (kWp) | F4: DEVEX/MWp | G4: DEVEX Total Amount | H4: Payment ratio | I4: Total | J4: 2024 Total | K4: 2025 Total | L4: 45688 | M4: 45716 | N4: 45747 | O4: 45777 | P4: 45808 | Q4: 45838 | R4: 45869 | S4: 45900 | T4: 45930 | U4: 45961 | V4: 45991 | W4: 46022 | X4: 2026 Total | Y4: 46053 | Z4: 46081 | AA4: 46112 | AB4: 46142 | AC4: 46173 | AD4: 46203 | AE4: 46234 | AF4: 46265 | AG4: 46295 | AH4: 46326 | AI4: 46356 | AJ4: 46387
B6: Total | C6: =+C7+C8+C9+C10+C11+C12 -> 22 | E6: =+SUM(E13:E34) -> 15912.58 | G6: =+SUM(G13:G34) -> 7955636000 | H6: =+I6/G6 -> 0.61739671 | I6: =+J6+K6+X6 -> 4911783500 | J6: =+SUM(J13:J34) -> 2837860300 | K6: =+SUM(K13:K34) -> 2073923200 | L6: =+SUM(L13:L34) -> 0 | M6: =+SUM(M13:M34) -> 0 | N6: =+SUM(N13:N34) -> 0 | O6: =+SUM(O13:O34) -> 0 | P6: =+SUM(P13:P34) -> 740251200 | Q6: =+SUM(Q13:Q34) -> 0 | ... AJ6: =+SUM(AJ13:AJ34) -> 0
B7: Bolt T 1HO Total | C7: =+C26 -> 14 | E7: =+SUM(E13:E26) -> 10394.64 | G7: =+SUM(G13:G26) -> 6436728000 | H7: =+I7/G7 -> 0.55588981 | I7: =+SUM(I13:I26) -> 3578111500 | J7: =+SUM(J13:J26) -> 2837860300 | K7: =+SUM(K13:K26) -> 740251200 | L7: =+SUM(L13:L26) -> 0 | M7: =+SUM(M13:M26) -> 0 | N7: =+SUM(N13:N26) -> 0 | O7: =+SUM(O13:O26) -> 0 | P7: =+SUM(P13:P26) -> 740251200 | ... AJ7: =+SUM(AJ13:AJ26) -> 0
B8: Galsan Solar Total | C8: =+C27 -> 1 | E8: =+E27 -> 993.6 | G8: =+G27 -> 223820970 | H8: =+I8/G8 -> 1 | I8: =+I27 -> 223820970 | J8: =+J27 -> 0 | K8: =+K27 -> 223820970 | L8: =+L27 -> 0 | M8: =+M27 -> 0 | N8: =+N27 -> 0 | O8: =+O27 -> 0 | P8: =+P27 -> 0 | ... AJ8: =+AJ27 -> 0
B9: Mineuri Solar Total | C9: =+C28 -> 1 | E9: =+E28 -> 993.6 | G9: =+G28 -> 110418040 | H9: =+I9/G9 -> 1 | I9: =+I28 -> 110418040 | J9: =+J28 -> 0 | K9: =+K28 -> 110418040 | L9: =+L28 -> 0 | M9: =+M28 -> 0 | N9: =+N28 -> 0 | O9: =+O28 -> 0 | P9: =+P28 -> 0 | ... AJ9: =+AJ28 -> 0
B10: SeagolSolar Total | C10: =+C29 -> 1 | E10: =+E29 -> 993.6 | G10: =+G29 -> 108773270 | H10: =+I10/G10 -> 1 | I10: =+I29 -> 108773270 | J10: =+J29 -> 0 | K10: =+K29 -> 108773270 | L10: =+L29 -> 0 | M10: =+M29 -> 0 | N10: =+N29 -> 0 | O10: =+O29 -> 0 | P10: =+P29 -> 0 | ... AJ10: =+AJ29 -> 0
B11: Jaesan Solar Total | C11: =+C30 -> 1 | E11: =+E30 -> 993.6 | G11: =+G30 -> 458479720 | H11: =+I11/G11 -> 1 | I11: =+I30 -> 458479720 | J11: =+J30 -> 0 | K11: =+K30 -> 458479720 | L11: =+L30 -> 0 | M11: =+M30 -> 0 | N11: =+N30 -> 0 | O11: =+O30 -> 0 | P11: =+P30 -> 0 | ... AJ11: =+AJ30 -> 0
B12: POSN2HO Total | C12: 4 | E12: =+SUM(E31:E34) -> 1543.54 | G12: =+SUM(G31:G34) -> 617416000 | H12: =+I12/G12 -> 0.69998186 | I12: =+SUM(I31:I34) -> 432180000 | J12: =+SUM(J31:J34) -> 0 | K12: =+SUM(K31:K34) -> 432180000 | L12: =+SUM(L31:L34) -> 0 | M12: =+SUM(M31:M34) -> 0 | N12: =+SUM(N31:N34) -> 0 | O12: =+SUM(O31:O34) -> 0 | P12: =+SUM(P31:P34) -> 0 | ... AJ12: =+SUM(AJ31:AJ34) -> 0
B13: Bolt Taeyanggwang 1HO | C13: 1 | D13: =+'GM Batch1'!C11 -> YJ NANSAN 1 | E13: =+'GM Batch1'!D11 -> 999.58 | F13: 550000000 | G13: =+E13*F13/1000 -> 549769000 | H13: =+I13/G13 -> 0.66947518 | I13: =+J13+K13+X13 -> 368056700 | J13: =+'GM Batch1'!Q12+'GM Batch1'!X12 -> 368056700 | K13: =+SUM(L13:W13) -> 0 | X13: =+SUM(Y13:AJ13) -> 0
C14: =+C13+1 -> 2 | D14: =+'GM Batch1'!C17 -> YJ NANSAN 2 | E14: =+'GM Batch1'!D17 -> 999.58 | F14: 550000000 | G14: =+E14*F14/1000 -> 549769000 | H14: =+I14/G14 -> 0.66947518 | I14: =+J14+K14+X14 -> 368056700 | J14: =+'GM Batch1'!Q18+'GM Batch1'!X18 -> 368056700 | K14: =+SUM(L14:W14) -> 0 | X14: =+SUM(Y14:AJ14) -> 0
C15: =+C14+1 -> 3 | D15: =+'GM Batch1'!C23 -> YJ GASI 1 | E15: =+'GM Batch1'!D23 -> 999.6 | F15: 550000000 | G15: =+E15*F15/1000 -> 549780000 | H15: =+I15/G15 -> 0.66947279 | I15: =+J15+K15+X15 -> 368062750 | J15: =+'GM Batch1'!Q24+'GM Batch1'!X24 -> 368062750 | K15: =+SUM(L15:W15) -> 0 | X15: =+SUM(Y15:AJ15) -> 0
C16: =+C15+1 -> 4 | D16: =+'GM Batch1'!C29 -> YJ GASI 2 | E16: =+'GM Batch1'!D29 -> 999.6 | F16: 550000000 | G16: =+E16*F16/1000 -> 549780000 | H16: =+I16/G16 -> 0.66947279 | I16: =+J16+K16+X16 -> 368062750 | J16: =+'GM Batch1'!Q30+'GM Batch1'!X30 -> 368062750 | K16: =+SUM(L16:W16) -> 0 | X16: =+SUM(Y16:AJ16) -> 0
C17: =+C16+1 -> 5 | D17: =+'GM Batch1'!C35 -> Dream 1 | E17: =+'GM Batch1'!D35 -> 999.24 | F17: 550000000 | G17: =+E17*F17/1000 -> 549582000 | H17: =+I17/G17 -> 0.62115408 | I17: =+J17+K17+X17 -> 341375100 | J17: =+'GM Batch1'!Q36+'GM Batch1'!X36 -> 341375100 | K17: =+SUM(L17:W17) -> 0 | X17: =+SUM(Y17:AJ17) -> 0
C18: =+C17+1 -> 6 | D18: =+'GM Batch1'!C41 -> Dream 2 | E18: =+'GM Batch1'!D41 -> 999.24 | F18: 550000000 | G18: =+E18*F18/1000 -> 549582000 | H18: =+I18/G18 -> 0.62115408 | I18: =+J18+K18+X18 -> 341375100 | J18: =+'GM Batch1'!Q42+'GM Batch1'!X42 -> 341375100 | K18: =+SUM(L18:W18) -> 0 | X18: =+SUM(Y18:AJ18) -> 0
C19: =+C18+1 -> 7 | D19: =+'GM Batch1'!C47 -> JEIL TECH 1 | E19: =+'GM Batch1'!D47 -> 999.44 | F19: 550000000 | G19: =+E19*F19/1000 -> 549692000 | H19: =+I19/G19 -> 0.62113984 | I19: =+J19+K19+X19 -> 341435600 | J19: =+'GM Batch1'!Q48+'GM Batch1'!X48 -> 341435600 | K19: =+SUM(L19:W19) -> 0 | X19: =+SUM(Y19:AJ19) -> 0
C20: =+C19+1 -> 8 | D20: =+'GM Batch1'!C53 -> JEIL TECH 2 | E20: =+'GM Batch1'!D53 -> 999.44 | F20: 550000000 | G20: =+E20*F20/1000 -> 549692000 | H20: =+I20/G20 -> 0.62113984 | I20: =+J20+K20+X20 -> 341435600 | J20: =+'GM Batch1'!Q54+'GM Batch1'!X54 -> 341435600 | K20: =+SUM(L20:W20) -> 0 | X20: =+SUM(Y20:AJ20) -> 0
C21: =+C20+1 -> 9 | D21: =+'GM Batch2-APA'!C11 -> Jangchon 1 (APA) | E21: =+'GM Batch2-APA'!D11 -> 551.04 | F21: 850000000 | G21: =+E21*F21/1000 -> 4.68384e+08 | H21: =+I21/G21 -> 0.55467821 | I21: =+J21+K21+X21 -> 259802400 | K21: =+SUM(L21:W21) -> 259802400 | P21: =+'GM Batch2-APA'!Q12+'GM Batch2-APA'!Q13+'GM Batch2-APA'!Q14 -> 259802400 | X21: =+SUM(Y21:AJ21) -> 0
C22: =+C21+1 -> 10 | D22: =+'GM Batch2-APA'!C17 -> Soltop Masan 1 (APA) | E22: =+'GM Batch2-APA'!D17 -> 399.04 | F22: 850000000 | G22: =+E22*F22/1000 -> 339184000 | H22: =+I22/G22 -> 0.30588235 | I22: =+J22+K22+X22 -> 103750400 | K22: =+SUM(L22:W22) -> 103750400 | P22: =+'GM Batch2-APA'!Q18+'GM Batch2-APA'!Q19+'GM Batch2-APA'!Q20 -> 103750400 | X22: =+SUM(Y22:AJ22) -> 0
C23: =+C22+1 -> 11 | D23: =+'GM Batch2-APA'!C23 -> Hanil Mugok 15 (APA) | E23: =+'GM Batch2-APA'!D23 -> 499.96 | F23: 850000000 | G23: =+E23*F23/1000 -> 424966000 | H23: =+I23/G23 -> 0.30588235 | I23: =+J23+K23+X23 -> 129989600 | K23: =+SUM(L23:W23) -> 129989600 | P23: =+'GM Batch2-APA'!Q24+'GM Batch2-APA'!Q25+'GM Batch2-APA'!Q26 -> 129989600 | X23: =+SUM(Y23:AJ23) -> 0
C24: =+C23+1 -> 12 | D24: =+'GM Batch2-APA'!C29 -> Hanil Jigyeong 1 (APA) | E24: =+'GM Batch2-APA'!D29 -> 499.96 | F24: 850000000 | G24: =+E24*F24/1000 -> 424966000 | H24: =+I24/G24 -> 0.30588235 | I24: =+J24+K24+X24 -> 129989600 | K24: =+SUM(L24:W24) -> 129989600 | P24: =+'GM Batch2-APA'!Q30+'GM Batch2-APA'!Q31+'GM Batch2-APA'!Q32 -> 129989600 | X24: =+SUM(Y24:AJ24) -> 0
C25: =+C24+1 -> 13 | D25: =+'GM Batch2-APA'!C35 -> Hanil Jigyeong 2 (APA) | E25: =+'GM Batch2-APA'!D35 -> 149.64 | F25: 850000000 | G25: =+E25*F25/1000 -> 1.27194e+08 | H25: =+I25/G25 -> 0.30588235 | I25: =+J25+K25+X25 -> 38906400 | K25: =+SUM(L25:W25) -> 38906400 | P25: =+'GM Batch2-APA'!Q36+'GM Batch2-APA'!Q37+'GM Batch2-APA'!Q38 -> 38906400 | X25: =+SUM(Y25:AJ25) -> 0
C26: =+C25+1 -> 14 | D26: =+'GM Batch2-APA'!C41 -> Ho Duck4 (APA) | E26: =+'GM Batch2-APA'!D41 -> 299.28 | F26: 850000000 | G26: =+E26*F26/1000 -> 2.54388e+08 | H26: =+I26/G26 -> 0.30588235 | I26: =+J26+K26+X26 -> 77812800 | K26: =+SUM(L26:W26) -> 77812800 | P26: =+'GM Batch2-APA'!Q42+'GM Batch2-APA'!Q43+'GM Batch2-APA'!Q44 -> 77812800 | X26: =+SUM(Y26:AJ26) -> 0
B27: Galsan Solar | C27: 1 | D27: =+'GM Batch2-SPA'!C11 -> Galsan (SPA) | E27: =+'GM Batch2-SPA'!D11 -> 993.6 | F27: =+G27/E27*1000 -> 2.2526265e+08 | G27: 223820970 | H27: =+I27/G27 -> 1 | I27: =+J27+K27+X27 -> 223820970 | K27: =+SUM(L27:W27) -> 223820970 | R27: =+'GM Batch2-SPA'!Q12 -> 223820970 | X27: =+SUM(Y27:AJ27) -> 0
B28: Mineuri Solar | C28: 1 | D28: =+'GM Batch2-SPA'!C17 -> Mineuri (SPA) | E28: =+'GM Batch2-SPA'!D17 -> 993.6 | F28: =+G28/E28*1000 -> 1.1112927e+08 | G28: 110418040 | H28: =+I28/G28 -> 1 | I28: =+J28+K28+X28 -> 110418040 | K28: =+SUM(L28:W28) -> 110418040 | R28: =+'GM Batch2-SPA'!Q18 -> 110418040 | X28: =+SUM(Y28:AJ28) -> 0
B29: SeagolSolar | C29: 1 | D29: =+'GM Batch2-SPA'!C23 -> Seagol(SPA) | E29: =+'GM Batch2-SPA'!D23 -> 993.6 | F29: =+G29/E29*1000 -> 1.094739e+08 | G29: 108773270 | H29: =+I29/G29 -> 1 | I29: =+J29+K29+X29 -> 108773270 | K29: =+SUM(L29:W29) -> 108773270 | R29: =+'GM Batch2-SPA'!Q24 -> 108773270 | X29: =+SUM(Y29:AJ29) -> 0
B30: Jaesan Solar | C30: 1 | D30: =+'GM Batch2-SPA'!C29 -> Jaesan (SPA) | E30: =+'GM Batch2-SPA'!D29 -> 993.6 | F30: =+G30/E30*1000 -> 4.6143289e+08 | G30: 458479720 | H30: =+I30/G30 -> 1 | I30: =+J30+K30+X30 -> 458479720 | K30: =+SUM(L30:W30) -> 458479720 | R30: =+'GM Batch2-SPA'!Q30 -> 458479720 | X30: =+SUM(Y30:AJ30) -> 0
B31: POSN2HO | C31: 1 | D31: =+'DG M&A-SPA_POSN'!C11 -> POS-1 | E31: =+'DG M&A-SPA_POSN'!D11 -> 340.8 | F31: 400000000 | G31: =+E31*F31/1000 -> 136320000 | H31: =+I31/G31 -> 0.74535211 | I31: =+J31+K31+X31 -> 101606400 | K31: =+SUM(L31:W31) -> 101606400 | R31: =+'DG M&A-SPA_POSN'!Q12 -> 101606400 | X31: =+SUM(Y31:AJ31) -> 0
C32: =+C31+1 -> 2 | D32: =+'DG M&A-SPA_POSN'!C17 -> POS-3 | E32: =+'DG M&A-SPA_POSN'!D17 -> 144.84 | F32: 400000000 | G32: =+E32*F32/1000 -> 57936000 | H32: =+I32/G32 -> 0.68202154 | I32: =+J32+K32+X32 -> 39513600 | K32: =+SUM(L32:W32) -> 39513600 | R32: =+'DG M&A-SPA_POSN'!Q18 -> 39513600 | X32: =+SUM(Y32:AJ32) -> 0
C33: =+C32+1 -> 3 | D33: =+'DG M&A-SPA_POSN'!C23 -> POS-4 | E33: =+'DG M&A-SPA_POSN'!D23 -> 807.98 | F33: 400000000 | G33: =+E33*F33/1000 -> 323192000 | H33: =+I33/G33 -> 0.68498601 | I33: =+J33+K33+X33 -> 221382000 | K33: =+SUM(L33:W33) -> 221382000 | R33: =+'DG M&A-SPA_POSN'!Q24 -> 221382000 | X33: =+SUM(Y33:AJ33) -> 0
C34: =+C33+1 -> 4 | D34: =+'DG M&A-SPA_POSN'!C29 -> POS-8 | E34: =+'DG M&A-SPA_POSN'!D29 -> 249.92 | F34: 400000000 | G34: =+E34*F34/1000 -> 99968000 | H34: =+I34/G34 -> 0.69700304 | I34: =+J34+K34+X34 -> 69678000 | K34: =+SUM(L34:W34) -> 69678000 | R34: =+'DG M&A-SPA_POSN'!Q30 -> 69678000 | X34: =+SUM(Y34:AJ34) -> 0

Sheet Amount to be paid in 2025(1004)
B2: SPV Name | D2: Bolt Taeyanggwang 1HO
B3: Business License Number | D3: 388-86-03459
B4: Corporate Registry Number | D4: 110111-9077515
B5: SPV Address | D5: #214, 42, Eonju-ro 147-gil, Gangnam-gu, Seoul, Korea | P5: =+P11+P12 -> 1214989490
B6: Project Tech. | D6: GM_Batch1,2, DG_M&A | P6: =+P5/1470 -> 826523.46
B7: Bank & Bank account Number | D7: KB Bank : 096368-11-010020
Y8: [Unit : KRW, EUR]
B9: SPV | C9: Name of Project | D9: CAPEX per kWp | E9: DEVEX per kWp | F9: Capacity (kWp) | G9: Total amount to be settled | H9: Amount scheduled to be paid in Jul. to Sep. | I9: 전체 지급예정 | J9: Total | K9: Paid (By Sep. 30, 2025) | L9: Balance on Sep. 30, 2025 | M9: Required funds for Oct. | N9: Amount scheduled to be paid in Oct. | O9: Oct. | Q9: Amount scheduled to be paid in Nov. | R9: Nov. | T9: Dec. | V9: Jan. 2026 | X9: After Jan.2026 | AA9: Review
O10: Date | P10: Payment | R10: Date | S10: Payment | T10: Date | U10: Payment | V10: Date | W10: Payment
B11: Bolt Taeyanggwang 1HO | C11: YJ NANSAN 1 | D11: =1050000+$D$64/1000 -> 1077500 | F11: 999.58 | G11: =D11*F11*1.1/1470 -> 805953.87 | H11: =+P11+S11 -> 896123470 | I11: =+F11*D11*1.1 -> 1184752195 | J11: =+K11+P11+S11+U11+Y11+W11 -> 1184752195 | K11: =+'GM Batch1'!AE11 -> 231000000 | N11: =+P11 -> 607494745 | O11: =+'GM Batch1'!AO11 -> 45950 | P11: =+'GM Batch1'!AR11 -> 607494745 | Q11: =+S11 -> 288628725 | R11: =+'GM Batch1'!BC11 -> 45991 | S11: =+'GM Batch1'!BF11 -> 288628725 | T11: =+'GM Batch1'!BJ11 -> 46022 | U11: =+'GM Batch1'!BM11+'GM Batch1'!AF11 -> 57628725 | AA11: =+I11=J11 -> TRUE
C12: YJ NANSAN 2 | D12: =1050000+$D$64/1000 -> 1077500 | F12: 999.58 | G12: =D12*F12*1.1/1470 -> 805953.87 | H12: =+P12+S12 -> 896123470 | I12: =+F12*D12*1.1 -> 1184752195 | J12: =+K12+P12+S12+U12+Y12+W12 -> 1184752195 | K12: =+'GM Batch1'!AE17 -> 231000000 | N12: =+P12 -> 607494745 | O12: =+'GM Batch1'!AO17 -> 45950 | P12: =+'GM Batch1'!AR17 -> 607494745 | Q12: =+S12 -> 288628725 | R12: =+'GM Batch1'!BC17 -> 45991 | S12: =+'GM Batch1'!BF17 -> 288628725 | T12: =+'GM Batch1'!BJ17 -> 46022 | U12: =+'GM Batch1'!BM17+'GM Batch1'!AF17 -> 57628725 | AA12: =+I12=J12 -> TRUE
C13: YJ GASI 1 | D13: =1050000+$D$64/1000 -> 1077500 | F13: 999.6 | G13: =D13*F13*1.1/1470 -> 805970 | H13: =+P13+S13 -> 896141400 | I13: =+F13*D13*1.1 -> 1184775900 | J13: =+K13+P13+S13+U13+Y13+W13 -> 1184775900 | K13: =+'GM Batch1'!AE23 -> 231000000 | N13: =+P13 -> 607506900 | O13: =+'GM Batch1'!AO23 -> 45950 | P13: =+'GM Batch1'!AR23 -> 607506900 | Q13: =+S13 -> 288634500 | R13: =+'GM Batch1'!BC23 -> 45991 | S13: =+'GM Batch1'!BF23 -> 288634500 | T13: =+'GM Batch1'!BJ23 -> 46022 | U13: =+'GM Batch1'!BM23+'GM Batch1'!AF23 -> 57634500 | AA13: =+I13=J13 -> TRUE
C14: YJ GASI 2 | D14: =1050000+$D$64/1000 -> 1077500 | F14: 999.6 | G14: =D14*F14*1.1/1470 -> 805970 | H14: =+P14+S14 -> 896141400 | I14: =+F14*D14*1.1 -> 1184775900 | J14: =+K14+P14+S14+U14+Y14+W14 -> 1184775900 | K14: =+'GM Batch1'!AE29 -> 231000000 | N14: =+P14 -> 607506900 | O14: =+'GM Batch1'!AO29 -> 45950 | P14: =+'GM Batch1'!AR29 -> 607506900 | Q14: =+S14 -> 288634500 | R14: =+'GM Batch1'!BC29 -> 45991 | S14: =+'GM Batch1'!BF29 -> 288634500 | T14: =+'GM Batch1'!BJ29 -> 46022 | U14: =+'GM Batch1'!BM29+'GM Batch1'!AF29 -> 57634500 | AA14: =+I14=J14 -> TRUE
C15: Dream 1 | D15: =1050000+$D$64/1000 -> 1077500 | F15: 999.24 | G15: =D15*F15*1.1/1470 -> 805679.73 | H15: =+P15+S15 -> 0 | I15: =+F15*D15*1.1 -> 1184349210 | J15: =+K15+P15+S15+U15+Y15+W15 -> 1184349210 | K15: 0 | N15: =+P15 -> 0 | Q15: =+S15 -> 0 | V15: =+'GM Batch1'!AA35 -> 46052 | W15: =+'GM Batch1'!AD35 -> 2.3082444e+08 | Y15: =+'GM Batch1'!I35-'GM Batch1'!AD35 -> 953524770 | AA15: =+I15=J15 -> TRUE
C16: Dream 2 | D16: =1050000+$D$64/1000 -> 1077500 | F16: 999.24 | G16: =D16*F16*1.1/1470 -> 805679.73 | H16: =+P16+S16 -> 0 | I16: =+F16*D16*1.1 -> 1184349210 | J16: =+K16+P16+S16+U16+Y16+W16 -> 1184349210 | K16: 0 | N16: =+P16 -> 0 | Q16: =+S16 -> 0 | V16: =+'GM Batch1'!AA41 -> 46052 | W16: =+'GM Batch1'!AD41 -> 2.3082444e+08 | Y16: =+'GM Batch1'!I41-'GM Batch1'!AD41 -> 953524770 | AA16: =+I16=J16 -> TRUE
C17: JEIL TECH 1 | D17: =1050000+$D$64/1000 -> 1077500 | F17: 999.44 | G17: =D17*F17*1.1/1470 -> 805840.99 | H17: =+P17+S17 -> 0 | I17: =+F17*D17*1.1 -> 1184586260 | J17: =+K17+P17+S17+U17+Y17+W17 -> 1184586260 | K17: 0 | N17: =+P17 -> 0 | Q17: =+S17 -> 0 | V17: =+'GM Batch1'!AA47 -> 46052 | W17: =+'GM Batch1'!AD47 -> 2.3087064e+08 | Y17: =+'GM Batch1'!I47-'GM Batch1'!AD47 -> 953715620 | AA17: =+I17=J17 -> TRUE
C18: JEIL TECH 2 | D18: =1050000+$D$64/1000 -> 1077500 | F18: 999.44 | G18: =D18*F18*1.1/1470 -> 805840.99 | H18: =+P18+S18 -> 0 | I18: =+F18*D18*1.1 -> 1184586260 | J18: =+K18+P18+S18+U18+Y18+W18 -> 1184586260 | K18: 0 | N18: =+P18 -> 0 | Q18: =+S18 -> 0 | V18: =+'GM Batch1'!AA53 -> 46052 | W18: =+'GM Batch1'!AD53 -> 2.3087064e+08 | Y18: =+'GM Batch1'!I53-'GM Batch1'!AD53 -> 953715620 | AA18: =+I18=J18 -> TRUE
C19: Jangchon 1 (APA) | D19: =1050000+$D$64/1000 -> 1077500 | F19: 999.24 | G19: =D19*F19*1.1/1470 -> 805679.73 | H19: =+P19+S19 -> 0 | I19: =+F19*D19*1.1 -> 1184349210 | J19: =+K19+P19+S19+U19+Y19+W19 -> 0 | N19: =+P19 -> 0 | Q19: =+S19 -> 0 | AA19: =+I19=J19 -> FALSE
C20: Soltop Masan 1 (APA) | D20: =1050000+$D$64/1000 -> 1077500 | F20: 399.04 | G20: =D20*F20*1.1/1470 -> 321742.97 | H20: =+P20+S20 -> 0 | I20: =+F20*D20*1.1 -> 4.7296216e+08 | J20: =+K20+P20+S20+U20+Y20+W20 -> 0 | N20: =+P20 -> 0 | Q20: =+S20 -> 0 | AA20: =+I20=J20 -> FALSE
C21: Hanil Mugok 15 (APA) | D21: =1050000+$D$64/1000 -> 1077500 | F21: 499.96 | G21: =D21*F21*1.1/1470 -> 403114.01 | H21: =+P21+S21 -> 0 | I21: =+F21*D21*1.1 -> 592577590 | J21: =+K21+P21+S21+U21+Y21+W21 -> 0 | N21: =+P21 -> 0 | Q21: =+S21 -> 0 | AA21: =+I21=J21 -> FALSE
C22: Hanil Jigyeong 1 (APA) | D22: =1050000+$D$64/1000 -> 1077500 | F22: 499.96 | G22: =D22*F22*1.1/1470 -> 403114.01 | H22: =+P22+S22 -> 0 | I22: =+F22*D22*1.1 -> 592577590 | J22: =+K22+P22+S22+U22+Y22+W22 -> 0 | N22: =+P22 -> 0 | Q22: =+S22 -> 0
C23: Hanil Jigyeong 2 (APA) | D23: =1050000+$D$64/1000 -> 1077500 | F23: 149.64 | G23: =D23*F23*1.1/1470 -> 120653.61 | H23: =+P23+S23 -> 0 | I23: =+F23*D23*1.1 -> 177360810 | J23: =+K23+P23+S23+U23+Y23+W23 -> 0 | N23: =+P23 -> 0 | Q23: =+S23 -> 0
C24: Ho Duck4 (APA) | D24: =1050000+$D$64/1000 -> 1077500 | F24: 299.28 | G24: =D24*F24*1.1/1470 -> 241307.22 | H24: =+P24+S24 -> 0 | I24: =+F24*D24*1.1 -> 354721620 | J24: =+K24+P24+S24+U24+Y24+W24 -> 0 | N24: =+P24 -> 0 | Q24: =+S24 -> 0
C25: Galsan (SPA) | D25: =1050000+$D$64/1000 -> 1077500 | F25: 993.6 | G25: =D25*F25*1.1/1470 -> 801132.24 | H25: =+P25+S25 -> 0 | I25: =+F25*D25*1.1 -> 1177664400 | J25: =+K25+P25+S25+U25+Y25+W25 -> 0 | N25: =+P25 -> 0 | Q25: =+S25 -> 0
C26: Mineuri (SPA) | D26: =1050000+$D$64/1000 -> 1077500 | F26: 993.6 | G26: =D26*F26*1.1/1470 -> 801132.24 | H26: =+P26+S26 -> 0 | I26: =+F26*D26*1.1 -> 1177664400 | J26: =+K26+P26+S26+U26+Y26+W26 -> 0 | N26: =+P26 -> 0 | Q26: =+S26 -> 0
C27: Saegol (SPA) | D27: =1050000+$D$64/1000 -> 1077500 | F27: 993.6 | G27: =D27*F27*1.1/1470 -> 801132.24 | H27: =+P27+S27 -> 0 | I27: =+F27*D27*1.1 -> 1177664400 | J27: =+K27+P27+S27+U27+Y27+W27 -> 0 | N27: =+P27 -> 0 | Q27: =+S27 -> 0
C28: Jaesan (SPA) | D28: =1050000+$D$64/1000 -> 1077500 | F28: 993.6 | G28: =D28*F28*1.1/1470 -> 801132.24 | H28: =+P28+S28 -> 0 | I28: =+F28*D28*1.1 -> 1177664400 | J28: =+K28+P28+S28+U28+Y28+W28 -> 0 | N28: =+P28 -> 0 | Q28: =+S28 -> 0 | AA28: =+I28=J28 -> FALSE
C29: CAPEX Total | F29: =+SUM(F11:F28) -> 14817.24 | G29: =SUM(G11:G28) -> 11947030 | H29: =H30/1470 -> 2438455.6 | I29: =I30/1470 -> 6446889.2 | J29: =J30/1470 -> 6446889.2 | K29: =K30/1470 -> 628571.43 | N29: =N30/1470 -> 1653063.5 | P29: =P30/1470 -> 1653063.5 | Q29: =Q30/1470 -> 785392.14 | S29: =S30/1470 -> 785392.14 | U29: =U30/1470 -> 156820.71 | W29: =W30/1470 -> 628156.57 | Y29: =Y30/1470 -> 2594884.9
H30: =+SUM(H11:H18) -> 3584529740 | I30: =+SUM(I11:I18) -> 9476927130 | J30: =+SUM(J11:J18) -> 9476927130 | K30: =+SUM(K11:K18) -> 924000000 | N30: =+SUM(N11:N18) -> 2430003290 | O30: =+SUM(O11:O18) -> 183800 | P30: =+SUM(P11:P18) -> 2430003290 | Q30: =+SUM(Q11:Q18) -> 1154526450 | R30: =+SUM(R11:R18) -> 183964 | S30: =+SUM(S11:S18) -> 1154526450 | T30: =+SUM(T11:T18) -> 184088 | U30: =+SUM(U11:U18) -> 2.3052645e+08 | ... Y30: =+SUM(Y11:Y18) -> 3814480780
C31: YJ NANSAN 1 | E31: 550000 | F31: 999.58 | G31: =E31*F31*1.1/1470 -> 411391.77 | H31: =+P31+S31 -> 16781600 | I31: =+E31*F31 -> 549769000 | J31: =+K31+P31+S31+U31+Y31+W31 -> 549769000 | K31: =+'GM Batch1'!K12 -> 368056700 | N31: =+P31 -> 16781600 | O31: =+'GM Batch1'!AA12 -> 45950 | P31: =+'GM Batch1'!AD12 -> 16781600 | Q31: =+S31 -> 0 | T31: =+'GM Batch1'!BJ12 -> 46022 | U31: =+'GM Batch1'!BM12 -> 164930700 | AA31: =+I31=J31 -> TRUE
C32: YJ NANSAN 2 | E32: 550000 | F32: 999.58 | G32: =E32*F32*1.1/1470 -> 411391.77 | H32: =+P32+S32 -> 16781600 | I32: =+E32*F32 -> 549769000 | J32: =+K32+P32+S32+U32+Y32+W32 -> 549769000 | K32: =+'GM Batch1'!K18 -> 368056700 | N32: =+P32 -> 16781600 | O32: =+'GM Batch1'!AA18 -> 45950 | P32: =+'GM Batch1'!AD18 -> 16781600 | Q32: =+S32 -> 0 | T32: =+'GM Batch1'!BJ18 -> 46022 | U32: =+'GM Batch1'!BM18 -> 164930700 | AA32: =+I32=J32 -> TRUE
C33: YJ GASI 1 | E33: 550000 | F33: 999.6 | G33: =E33*F33*1.1/1470 -> 411400 | H33: =+P33+S33 -> 16783250 | I33: =+E33*F33 -> 549780000 | J33: =+K33+P33+S33+U33+Y33+W33 -> 549780000 | K33: =+'GM Batch1'!K24 -> 368062750 | N33: =+P33 -> 16783250 | O33: =+'GM Batch1'!AA24 -> 45950 | P33: =+'GM Batch1'!AD24 -> 16783250 | Q33: =+S33 -> 0 | T33: =+'GM Batch1'!BJ24 -> 46022 | U33: =+'GM Batch1'!BM24 -> 164934000 | AA33: =+I33=J33 -> TRUE
C34: YJ GASI 2 | E34: 550000 | F34: 999.6 | G34: =E34*F34*1.1/1470 -> 411400 | H34: =+P34+S34 -> 16783250 | I34: =+E34*F34 -> 549780000 | J34: =+K34+P34+S34+U34+Y34+W34 -> 549780000 | K34: =+'GM Batch1'!K30 -> 368062750 | N34: =+P34 -> 16783250 | O34: =+'GM Batch1'!AA30 -> 45950 | P34: =+'GM Batch1'!AD30 -> 16783250 | Q34: =+S34 -> 0 | T34: =+'GM Batch1'!BJ30 -> 46022 | U34: =+'GM Batch1'!BM30 -> 164934000 | AA34: =+I34=J34 -> TRUE
C35: Dream 1 | E35: 550000 | F35: 999.24 | G35: =E35*F35*1.1/1470 -> 411251.84 | H35: =+P35+S35 -> 0 | I35: =+E35*F35 -> 549582000 | J35: =+K35+P35+S35+U35+Y35+W35 -> 549582000 | K35: =+'GM Batch1'!K36 -> 341375100 | N35: =+P35 -> 0 | Q35: =+S35 -> 0 | T35: =+'GM Batch1'!AA36 -> 46022 | U35: =+'GM Batch1'!AD36 -> 43332300 | Y35: =+'GM Batch1'!BM36 -> 164874600 | AA35: =+I35=J35 -> TRUE
C36: Dream 2 | E36: 550000 | F36: 999.24 | G36: =E36*F36*1.1/1470 -> 411251.84 | H36: =+P36+S36 -> 0 | I36: =+E36*F36 -> 549582000 | J36: =+K36+P36+S36+U36+Y36+W36 -> 549582000 | K36: =+'GM Batch1'!K42 -> 341375100 | N36: =+P36 -> 0 | Q36: =+S36 -> 0 | T36: =+'GM Batch1'!AA42 -> 46022 | U36: =+'GM Batch1'!AD42 -> 43332300 | Y36: =+'GM Batch1'!BM42 -> 164874600 | AA36: =+I36=J36 -> TRUE
C37: JEIL TECH 1 | E37: 550000 | F37: 999.44 | G37: =E37*F37*1.1/1470 -> 411334.15 | H37: =+P37+S37 -> 0 | I37: =+E37*F37 -> 549692000 | J37: =+K37+P37+S37+U37+Y37+W37 -> 549692000 | K37: =+'GM Batch1'!K48 -> 341435600 | N37: =+P37 -> 0 | Q37: =+S37 -> 0 | T37: =+'GM Batch1'!AA48 -> 46022 | U37: =+'GM Batch1'!AD48 -> 43348800 | Y37: =+'GM Batch1'!BM48 -> 164907600 | AA37: =+I37=J37 -> TRUE
C38: JEIL TECH 2 | E38: 550000 | F38: 999.44 | G38: =E38*F38*1.1/1470 -> 411334.15 | H38: =+P38+S38 -> 0 | I38: =+E38*F38 -> 549692000 | J38: =+K38+P38+S38+U38+Y38+W38 -> 549692000 | K38: =+'GM Batch1'!K54 -> 341435600 | N38: =+P38 -> 0 | Q38: =+S38 -> 0 | T38: =+'GM Batch1'!AA54 -> 46022 | U38: =+'GM Batch1'!AD54 -> 43348800 | Y38: =+'GM Batch1'!BM54 -> 164907600 | AA38: =+I38=J38 -> TRUE
C39: Jangchon 1 (APA) | E39: 850000 | F39: 999.24 | G39: =E39*F39*1.1/1470 -> 635571.02 | H39: =+P39+S39 -> 0 | I39: =+E39*F39 -> 849354000 | J39: =+K39+P39+S39+U39+Y39+W39 -> 0 | N39: =+P39 -> 0 | Q39: =+S39 -> 0 | AA39: =+I39=J39 -> FALSE
C40: Soltop Masan 1 (APA) | E40: 850000 | F40: 399.04 | G40: =E40*F40*1.1/1470 -> 253811.16 | H40: =+P40+S40 -> 0 | I40: =+E40*F40 -> 339184000 | J40: =+K40+P40+S40+U40+Y40+W40 -> 0 | N40: =+P40 -> 0 | Q40: =+S40 -> 0 | AA40: =+I40=J40 -> FALSE
C41: Hanil Mugok 15 (APA) | E41: 850000 | F41: 499.96 | G41: =E41*F41*1.1/1470 -> 318001.77 | H41: =+P41+S41 -> 0 | I41: =+E41*F41 -> 424966000 | J41: =+K41+P41+S41+U41+Y41+W41 -> 0 | N41: =+P41 -> 0 | Q41: =+S41 -> 0 | AA41: =+I41=J41 -> FALSE
C42: Hanil Jigyeong 1 (APA) | E42: 850000 | F42: 499.96 | G42: =E42*F42*1.1/1470 -> 318001.77 | H42: =+P42+S42 -> 0 | I42: =+E42*F42 -> 424966000 | J42: =+K42+P42+S42+U42+Y42+W42 -> 0 | N42: =+P42 -> 0 | Q42: =+S42 -> 0
C43: Hanil Jigyeong 2 (APA) | E43: 850000 | F43: 149.64 | G43: =E43*F43*1.1/1470 -> 95179.184 | H43: =+P43+S43 -> 0 | I43: =+E43*F43 -> 1.27194e+08 | J43: =+K43+P43+S43+U43+Y43+W43 -> 0 | N43: =+P43 -> 0 | Q43: =+S43 -> 0
C44: Ho Duck4 (APA) | E44: 850000 | F44: 299.28 | G44: =E44*F44*1.1/1470 -> 190358.37 | H44: =+P44+S44 -> 0 | I44: =+E44*F44 -> 2.54388e+08 | J44: =+K44+P44+S44+U44+Y44+W44 -> 0 | N44: =+P44 -> 0 | Q44: =+S44 -> 0
C45: Galsan (SPA) | E45: 650000 | F45: 993.6 | G45: =E45*F45*1.1/1470 -> 483281.63 | H45: =+P45+S45 -> 0 | I45: =+E45*F45 -> 645840000 | J45: =+K45+P45+S45+U45+Y45+W45 -> 0 | N45: =+P45 -> 0 | Q45: =+S45 -> 0
C46: Mineuri (SPA) | E46: 650000 | F46: 993.6 | G46: =E46*F46*1.1/1470 -> 483281.63 | H46: =+P46+S46 -> 0 | I46: =+E46*F46 -> 645840000 | J46: =+K46+P46+S46+U46+Y46+W46 -> 0 | N46: =+P46 -> 0 | Q46: =+S46 -> 0
C47: Saegol (SPA) | E47: 650000 | F47: 993.6 | G47: =E47*F47*1.1/1470 -> 483281.63 | H47: =+P47+S47 -> 0 | I47: =+E47*F47 -> 645840000 | J47: =+K47+P47+S47+U47+Y47+W47 -> 0 | N47: =+P47 -> 0 | Q47: =+S47 -> 0
C48: Jaesan (SPA) | E48: 650000 | F48: 993.6 | G48: =E48*F48*1.1/1470 -> 483281.63 | H48: =+P48+S48 -> 0 | I48: =+E48*F48 -> 645840000 | J48: =+K48+P48+S48+U48+Y48+W48 -> 0 | N48: =+P48 -> 0 | Q48: =+S48 -> 0 | AA48: =+I48=J48 -> FALSE
C49: DEVEX Total | F49: =SUM(F31:F48) -> 14817.24 | G49: =SUM(G31:G48) -> 7034805.3 | H49: =H50/1470 -> 45666.463 | J49: =J50/1470 -> 2991595.9 | K49: =K50/1470 -> 1930517.2 | L49: =L50/1470 -> 378254.36 | N49: =N50/1470 -> 45666.463 | P49: =P50/1470 -> 45666.463 | Q49: =Q50/1470 -> 0 | S49: =S50/1470 -> 0 | U49: =U50/1470 -> 566728.98 | W49: =W50/1470 -> 0 | Y49: =Y50/1470 -> 448683.27
H50: =+SUM(H31:H38) -> 67129700 | I50: =+SUM(I31:I38) -> 4397646000 | J50: =+SUM(J31:J38) -> 4397646000 | K50: =+SUM(K31:K38) -> 2837860300 | L50: =+[2]Bolt1ho!$M$8 -> 556033915 | N50: =+SUM(N31:N38) -> 67129700 | O50: =+SUM(O31:O38) -> 183800 | P50: =+SUM(P31:P38) -> 67129700 | Q50: =+SUM(Q31:Q38) -> 0 | R50: =+SUM(R31:R38) -> 0 | S50: =+SUM(S31:S38) -> 0 | T50: =+SUM(T31:T38) -> 368176 | U50: =+SUM(U31:U38) -> 833091600 | ... Y50: =+SUM(Y31:Y38) -> 659564400
B51: Total | F51: =+F49 -> 14817.24 | G51: =+G49+G29 -> 18981835 | H51: =+H43+H49 -> 45666.463 | I51: =I52/1470 -> 3164649 | J51: =J52/1470 -> 9438485.1 | K51: =K52/1470 -> 2559088.6 | L51: =L52/1470 -> 378254.36 | M51: =M52/1470 -> 1320475.6 | N51: =N52/1470 -> 1698729.9 | P51: =P52/1470 -> 1698729.9 | Q51: =Q52/1470 -> 785392.14 | R51: =R52/1470 -> 0 | S51: =S52/1470 -> 785392.14 | T51: =T52/1470 -> 0 | U51: =U52/1470 -> 723549.69 | V51: =V52/1470 -> 0 | W51: =W52/1470 -> 628156.57 | ... Y51: =Y52/1470 -> 3043568.1
I52: =+I44+I50 -> 4652034000 | J52: =+J50+J30 -> 13874573130 | K52: =+K50+K30 -> 3761860300 | L52: =+L50+L30 -> 556033915 | M52: =+N52-L52 -> 1941099075 | N52: =+N50+N30 -> 2497132990 | P52: =+P50+P30 -> 2497132990 | Q52: =+Q50+Q30 -> 1154526450 | R52: =+R44 -> 0 | S52: =+S50+S30 -> 1154526450 | T52: =+T44 -> 0 | U52: =+U50+U30 -> 1.0636181e+09 | V52: =+V44 -> 0 | W52: =+W50+W30 -> 9.2339016e+08 | X52: =+X44 -> 0 | Y52: =+Y50+Y30 -> 4474045180
B54: ※CAPEX payment schedule for Oct. | J54: =+J29-K29 -> 5818317.8 | K54: 942471
B55: SPV | C55: Name of Project | D55: DEVEX per kWp | E55: DEVEX per kWp | F55: Capacity (kWp) | G55: Total amount to be settled | H55: Amount scheduled to be paid in Jul. to Aug. | I55: 전체 지급예정 | J55: Total | K55: Paid | L55: Balance on Jul. 21, 2025 | N55: Amount scheduled to be paid in Aug. to Sep. (2nd Drawdown Amount) | O55: Jul. | Q55: Amount scheduled to be paid in Aug. to Sep. (2nd Drawdown Amount) | R55: Aug. | T55: Sep. | V55: Oct. | X55: After Oct. | AA55: Review
O56: Date | P56: Payment | R56: Date | S56: Payment | T56: Date | U56: Payment | V56: Date | W56: Payment
C57: POS-1 | D57: 400000 | E57: 400000 | F57: =+'DG M&A-SPA_POSN'!D11 -> 340.8 | G57: =E57*F57*1.1/1470 -> 102008.16 | H57: =+P57+S57 -> 0 | I57: =+F57*550000000/1000 -> 187440000 | J57: =+K57+P57+S57+U57+Y57+W57 -> 0 | N57: =S57+U57 -> 0 | Q57: =V57+X57 -> 0 | AA57: =+I57=J57 -> FALSE
C58: POS-3 | D58: 400000 | E58: 400000 | F58: =+'DG M&A-SPA_POSN'!D17 -> 144.84 | G58: =E58*F58*1.1/1470 -> 43353.469 | H58: =+P58+S58 -> 0 | I58: =+F58*550000000/1000 -> 79662000 | J58: =+K58+P58+S58+U58+Y58+W58 -> 0 | N58: =S58+U58 -> 0 | Q58: =V58+X58 -> 0 | AA58: =+I58=J58 -> FALSE
C59: POS-4 | D59: 400000 | E59: 400000 | F59: =+'DG M&A-SPA_POSN'!D23 -> 807.98 | G59: =E59*F59*1.1/1470 -> 241844.35 | H59: =+P59+S59 -> 0 | I59: =+F59*550000000/1000 -> 444389000 | J59: =+K59+P59+S59+U59+Y59+W59 -> 0 | N59: =S59+U59 -> 0 | Q59: =V59+X59 -> 0 | AA59: =+I59=J59 -> FALSE
C60: POS-8 | D60: 400000 | E60: 400000 | F60: =+'DG M&A-SPA_POSN'!D29 -> 249.92 | G60: =E60*F60*1.1/1470 -> 74805.986 | H60: =+P60+S60 -> 0 | I60: =+F60*550000000/1000 -> 137456000 | J60: =+K60+P60+S60+U60+Y60+W60 -> 0 | N60: =S60+U60 -> 0 | Q60: =V60+X60 -> 0 | AA60: =+I60=J60 -> FALSE
C61: Total | F61: =SUM(F57:F60) -> 1543.54 | G61: =SUM(G57:G60) -> 462011.97 | H61: =H62/1470 -> 0 | K61: =K62/1470 -> 0 | L61: =L62/1470 -> 0 | N61: =N62/1470 -> 0 | P61: =P62/1470 -> 0 | Q61: =Q62/1470 -> 0 | S61: =S62/1470 -> 0 | U61: =U62/1470 -> 0 | W61: =W62/1470 -> 0 | Y61: =Y62/1470 -> 0
H62: =+SUM(H57:H60) -> 0 | I62: =+SUM(I57:I60) -> 848947000 | J62: =+SUM(J57:J60) -> 0 | K62: =+SUM(K57:K60) -> 0 | N62: =+SUM(N57:N60) -> 0 | P62: =+SUM(P57:P60) -> 0 | Q62: =+SUM(Q57:Q60) -> 0 | S62: =+SUM(S57:S60) -> 0 | U62: =+SUM(U57:U60) -> 0 | W62: =+SUM(W57:W60) -> 0 | Y62: =+SUM(Y57:Y60) -> 0 | AA62: =+I62=J62 -> FALSE
B63: - The supervision fee of 27,500,000 KRW per MWp must be paid in Oct. | K63: 1630.78
C64: CAPEX 추가 금액 -감리 | D64: 27500000 | K64: =+K54*K63 -> 1.5369629e+09

Sheet Amount to be paid_POSN2HO
B2: SPV Name | D2: POSN2HO
B3: Business License Number | D3: 609-87-03315
B4: Corporate Registry Number | D4: 110111-8843256
B5: SPV Address | D5: #228, 42, Eonju-ro 147-gil, Gangnam-gu, Seoul, Korea
B6: Project Tech. | D6: DG_M&A
B7: Bank & Bank account Number | D7: KB Bank : 096301-04-106357
V8: [Unit : KRW, EUR / 1EUR=1,470KRW]
B9: SPV | C9: Batch | D9: Name of Project | E9: CAPEX per kWp | F9: DEVEX per kWp | G9: Capacity (kWp) | H9: Total amount to be settled | I9: Total | J9: Paid (By Sep. 30, 2025) | K9: Balance on Sep. 30, 2025 | L9: Required funds for Oct. | M9: Amount scheduled to be paid in Oct. | N9: Oct. | P9: Amount scheduled to be paid in Oct. to After Oct. | Q9: Nov. | S9: Dec. | U9: Jan. 2026 | X9: Review
N10: Date | O10: Payment | Q10: Date | R10: Payment | S10: Date | T10: Payment
B11: POSN2HO | C11: DG_M&A | D11: POS-1 | E11: 1100000 | G11: =+'DG M&A-SPA_POSN'!D11 -> 340.8 | H11: =+E11*G11*1.1/1470 -> 280522.45 | I11: =+J11+M11+P11 -> 206184000 | M11: =+O11 -> 206184000 | N11: =+'DG M&A-SPA_POSN'!AA11 -> 45960 | O11: =+'DG M&A-SPA_POSN'!AD11 -> 206184000 | P11: =+R11 -> 0 | V11: =+'DG M&A-SPA_POSN'!BM11 -> 206184000 | X11: =+J11+M11+P11+V11=G11*E11*1.1 -> TRUE
D12: POS-3 | E12: 1100000 | G12: =+'DG M&A-SPA_POSN'!D17 -> 144.84 | H12: =+E12*G12*1.1/1470 -> 119222.04 | I12: =+J12+M12+P12 -> 87628200 | M12: =+O12 -> 87628200 | N12: =+'DG M&A-SPA_POSN'!AA17 -> 45960 | O12: =+'DG M&A-SPA_POSN'!AD17 -> 87628200 | P12: =+R12 -> 0 | V12: =+'DG M&A-SPA_POSN'!BM17 -> 87628200 | X12: =+J12+M12+P12+V12=G12*E12*1.1 -> TRUE
D13: POS-4 | E13: 1100000 | G13: =+'DG M&A-SPA_POSN'!D23 -> 807.98 | H13: =+E13*G13*1.1/1470 -> 665071.97 | I13: =+J13+M13+P13 -> 488827900 | M13: =+O13 -> 488827900 | N13: =+'DG M&A-SPA_POSN'!AA23 -> 45960 | O13: =+'DG M&A-SPA_POSN'!AD23 -> 488827900 | P13: =+R13 -> 0 | V13: =+'DG M&A-SPA_POSN'!BM23 -> 488827900 | X13: =+J13+M13+P13+V13=G13*E13*1.1 -> TRUE
D14: POS-8 | E14: 1100000 | G14: =+'DG M&A-SPA_POSN'!D29 -> 249.92 | H14: =+E14*G14*1.1/1470 -> 205716.46 | I14: =+J14+M14+P14 -> 151201600 | M14: =+O14 -> 151201600 | N14: =+'DG M&A-SPA_POSN'!AA29 -> 45960 | O14: =+'DG M&A-SPA_POSN'!AD29 -> 151201600 | P14: =+R14 -> 0 | V14: =+'DG M&A-SPA_POSN'!BM29 -> 151201600 | X14: =+J14+M14+P14+V14=G14*E14*1.1 -> TRUE
D15: Total | G15: =SUM(G11:G14) -> 1543.54 | H15: =SUM(H11:H14) -> 1270532.9 | I15: =I16/1470 -> 635266.46 | J15: =J16/1470 -> 0 | M15: =M16/1470 -> 635266.46 | O15: =O16/1470 -> 635266.46 | P15: =P16/1470 -> 0 | R15: =R16/1470 -> 0 | T15: =T16/1470 -> 0 | V15: =V16/1470 -> 635266.46
I16: =+SUM(I11:I14) -> 933841700 | J16: =+SUM(J11:J14) -> 0 | M16: =+SUM(M11:M14) -> 933841700 | O16: =+SUM(O11:O14) -> 933841700 | P16: =+SUM(P11:P14) -> 0 | R16: =+SUM(R11:R14) -> 0 | T16: =+SUM(T11:T14) -> 0 | V16: =+SUM(V11:V14) -> 933841700
C17: DG_M&A | D17: POS-1 | F17: 400000 | G17: =+'DG M&A-SPA_POSN'!D11 -> 340.8 | H17: =+F17*G17/1470 -> 92734.694 | I17: =+J17+M17+P17 -> 122688000 | J17: =+'DG M&A-SPA_POSN'!Q12 -> 101606400 | M17: =+O17 -> 21081600 | N17: =+'DG M&A-SPA_POSN'!AA17 -> 45960 | O17: =+'DG M&A-SPA_POSN'!W12+'DG M&A-SPA_POSN'!R12 -> 21081600 | P17: =+R17 -> 0 | V17: =+'DG M&A-SPA_POSN'!BM12 -> 13632000 | X17: =+J17+M17+P17+V17=G17*F17 -> TRUE
D18: POS-3 | F18: 400000 | G18: =+'DG M&A-SPA_POSN'!D17 -> 144.84 | H18: =+F18*G18/1470 -> 39412.245 | I18: =+J18+M18+P18 -> 52142400 | J18: =+'DG M&A-SPA_POSN'!Q18 -> 39513600 | M18: =+O18 -> 12628800 | N18: =+'DG M&A-SPA_POSN'!AA23 -> 45960 | O18: =+'DG M&A-SPA_POSN'!W18+'DG M&A-SPA_POSN'!R18 -> 12628800 | P18: =+R18 -> 0 | V18: =+'DG M&A-SPA_POSN'!BM18 -> 5793600 | X18: =+J18+M18+P18+V18=G18*F18 -> TRUE
D19: POS-4 | F19: 400000 | G19: =+'DG M&A-SPA_POSN'!D23 -> 807.98 | H19: =+F19*G19/1470 -> 219858.5 | I19: =+J19+M19+P19 -> 290872800 | J19: =+'DG M&A-SPA_POSN'!Q24 -> 221382000 | M19: =+O19 -> 69490800 | N19: =+'DG M&A-SPA_POSN'!AA29 -> 45960 | O19: =+'DG M&A-SPA_POSN'!W24+'DG M&A-SPA_POSN'!R24 -> 69490800 | P19: =+R19 -> 0 | V19: =+'DG M&A-SPA_POSN'!BM24 -> 32319200 | X19: =+J19+M19+P19+V19=G19*F19 -> TRUE
D20: POS-8 | F20: 400000 | G20: =+'DG M&A-SPA_POSN'!D29 -> 249.92 | H20: =+F20*G20/1470 -> 68005.442 | I20: =+J20+M20+P20 -> 89971200 | J20: =+'DG M&A-SPA_POSN'!Q30 -> 69678000 | M20: =+O20 -> 20293200 | N20: =+'DG M&A-SPA_POSN'!AA35 -> 45950 | O20: =+'DG M&A-SPA_POSN'!W30+'DG M&A-SPA_POSN'!R30 -> 20293200 | P20: =+R20 -> 0 | V20: =+'DG M&A-SPA_POSN'!BM30 -> 9996800 | X20: =+J20+M20+P20+V20=G20*F20 -> TRUE
D21: Total | G21: =SUM(G17:G20) -> 1543.54 | H21: =SUM(H17:H20) -> 420010.88 | I21: =I22/1470 -> 378009.8 | J21: =J22/1470 -> 294000 | M21: =M22/1470 -> 84009.796 | O21: =O22/1470 -> 84009.796 | P21: =P22/1470 -> 0 | R21: =R22/1470 -> 0 | T21: =T22/1470 -> 0 | V21: =V22/1470 -> 42001.088
I22: =+SUM(I17:I20) -> 555674400 | J22: =+SUM(J17:J20) -> 432180000 | M22: =+SUM(M17:M20) -> 123494400 | O22: =+SUM(O17:O20) -> 123494400 | P22: =+SUM(P17:P20) -> 0 | R22: =+SUM(R17:R20) -> 0 | T22: =+SUM(T17:T20) -> 0 | V22: =+SUM(V17:V20) -> 61741600
B23: Total | G23: =+G15 -> 1543.54 | H23: =+H15+H21 -> 1690543.8 | I23: =I24/1470 -> 1013276.3 | J23: =J24/1470 -> 294000 | K23: =K24/1470 -> 3489.8435 | L23: =L24/1470 -> 841509.91 | M23: =M24/1470 -> 719276.26 | O23: =O24/1470 -> 719276.26 | P23: =P24/1470 -> 0 | R23: =R24/1470 -> 0 | T23: =T24/1470 -> 0 | V23: =V24/1470 -> 677267.55
I24: =+I16+I22 -> 1489516100 | J24: =+J16+J22 -> 432180000 | K24: 5130070 | L24: =+D33+M22-K24 -> 1237019573 | M24: =+M16+M22 -> 1057336100 | O24: =+O16+O22 -> 1057336100 | P24: =+P16 -> 0 | R24: =+R16 -> 0 | T24: =+T16 -> 0 | V24: =+V16+V22 -> 995583300
B26: ※ CAPEX amount to be paid on 15 Oct. | P26: =+G19 -> 807.98
B27: Category | C27: Amount | D27: 45931 | F27: 46022 | H27: Remark | K27: 818246865
B28: CAPEX | C28: =+H15*1470 -> 1.8676834e+09 | D28: =+C28*50% -> 9.338417e+08 | E28: =+D28/1470 -> 635266.46 | F28: =+C28*50% -> 9.338417e+08 | G28: =+F28/1470 -> 635266.46 | J28: =+G11/$G$15 -> 0.22079117 | K28: =+J28*$K$27 -> 1.8066168e+08 | L28: 내일
B29: Grid Connection Fee | C29: -46492230 | D29: =+C29*100% -> -46492230 | E29: =+D29/1470 -> -31627.367 | G29: =+F29/1470 -> 0 | H29: Paid in advance on 12 Sep. | J29: =+G12/$G$15 -> 0.093836247 | K29: =+J29*$K$27 -> 76781215 | L29: 포스엔 하고 2호 돈이 얼마가 들어왔고
B30: Additional CAPEX Cost | C30: 44000000 | D30: =+C30 -> 44000000 | E30: =+D30/1470 -> 29931.973 | G30: =+F30/1470 -> 0 | H30: Reflected in the Oct. billing amount | J30: =+G13/$G$15 -> 0.52345906 | K30: =+J30*$K$27 -> 4.2831874e+08 | L30: 나가야 되는 돈 | M30: 나가야 되는 돈
B31: Prepaid Lease Fee | C31: 182895773 | D31: =+C31 -> 182895773 | E31: =+D31/1470 -> 124418.89 | G31: =+F31/1470 -> 0 | H31: Remaining lease fees for 5 years prepaid for POS_1, 3, 4, and 8 | J31: =+G14/$G$15 -> 0.16191352 | K31: =+J31*$K$27 -> 1.3248523e+08 | L31: 임대료 | M31: 2에서 나가야 되는 돈
B32: OE Fee | C32: 4410000 | D32: =+C32 -> 4410000 | E32: =+D32/1470 -> 3000 | G32: =+F32/1470 -> 0 | L32: CAPEX | M32: 이렇게 이렇게 나갈거다…. 도영이사가 마테오 한테 메일 보내라…. 익일.
B33: Total | C33: =+SUM(C28:C32) -> 2.0524969e+09 | D33: =+SUM(D28:D32) -> 1118655243 | E33: =+SUM(E28:E32) -> 760989.96 | F33: =+SUM(F28:F32) -> 9.338417e+08 | G33: =+SUM(G28:G32) -> 635266.46
D34: Total | E34: =+E33+G33 -> 1396256.4 | F34: =1300464.9+124418.89+3000 -> 1427883.8 | G34: =1300464.9+124418.89 -> 1424883.8
I35: =+F35/H35 -> #DIV/0!
B36: 지급현황 | E36: =+E37/F37 -> 0.73113249 | F36: =+E37+220000000 -> 818246865
B37: 45975 | C37: 공사비 50% | E37: 598246865 | F37: 818246865
B38: 지급 내역
B39: 효성에너지팜 지급금액
B40: CAPEX 50%
B41: 계통연계비1
B42: 계통연계비2
B43: 합계
B44: 실 지급액
B46: OR 반환 금액
B47: 계통연계비2
B48: 추가비용
B49: 합계
B51: NEXT_S 반환 금액
... B54: 합계
C61: NEXT S 추가선납임차료 | E61: 8382528
C62: 잔여 선납임차료 | D62: POS1 | E62: =+E66 -> 40344480
C63: =+C62 -> 잔여 선납임차료 | D63: POS4 | E63: =+E68 -> 96502725
D66: POS1 | E66: 40344480
D67: POS3 | E67: 552420
D68: POS4 | E68: 96502725
D69: POS8 | E69: 37113120
E70: =SUM(E66:E69) -> 174512745
E71: =+E70+E61 -> 182895273 | F71: =+E71-C31 -> -500
E74: =+E62-30080160 -> 10264320
E75: =+E74*2 -> 20528640
E76: 10264320
E77: 20956320
E78: 23482305
E79: =SUM(E76:E78) -> 54702945

Sheet Amount to be paid in 2025(Total
B2: SPV Name | D2: Bolt Taeyanggwang 1HO
B3: Business License Number | D3: 388-86-03459
B4: Corporate Registry Number | D4: 110111-9077515
B5: SPV Address | D5: #214, 42, Eonju-ro 147-gil, Gangnam-gu, Seoul, Korea
B6: Project Tech. | D6: GM_Batch1,2, DG_M&A
B7: Bank & Bank account Number | D7: KB Bank : 096301-04-103314
T8: [Unit : KRW, EUR / 1EUR=1,470KRW]
B9: SPV | C9: Batch | D9: Name of Project | E9: CAPEX per kWp | F9: Capacity (kWp) | G9: Total amount to be settled | H9: Total | I9: Paid (By Aug. 31, 2025) | J9: Balance on Aug. 20, 2025 | K9: Amount scheduled to be paid in Aug. to Sep. (2nd Drawdown Amount) | L9: Sep. | N9: Oct. | P9: Amount scheduled to be paid in Oct. to After Oct. (3rd Drawdown Amount) | Q9: Nov. | S9: After Nov. | V9: Review
L10: Date | M10: Payment | N10: Date | O10: Payment | Q10: Date | R10: Payment
B11: Bolt Taeyanggwang 1HO | C11: GM_Batch1 | D11: =+'GM Batch1'!C11 -> YJ NANSAN 1 | E11: 1050000 | F11: =+'GM Batch1'!D11 -> 999.58 | G11: =E11*F11*1.1/1470 -> 785384.29 | H11: =+I11+K11+P11 -> 0 | K11: =+M11+O11 -> 0 | P11: =+R11+T11 -> 0
D12: =+'GM Batch1'!C17 -> YJ NANSAN 2 | E12: 1050000 | F12: =+'GM Batch1'!D17 -> 999.58 | G12: =E12*F12*1.1/1470 -> 785384.29 | H12: =+I12+K12+P12 -> 0 | K12: =+M12+O12 -> 0 | P12: =+R12+T12 -> 0 | V12: =+I12+K12+P12=E12*F12*1.1 -> FALSE | W12: =+E12*F12*1.1=I12+M12+O12+R12+T12 -> FALSE
D13: =+'GM Batch1'!C23 -> YJ GASI 1 | E13: 1050000 | F13: =+'GM Batch1'!D23 -> 999.6 | G13: =E13*F13*1.1/1470 -> 785400 | H13: =+I13+K13+P13 -> 0 | K13: =+M13+O13 -> 0 | P13: =+R13+T13 -> 0 | V13: =+I13+K13+P13=E13*F13*1.1 -> FALSE | W13: =+E13*F13*1.1=I13+M13+O13+R13+T13 -> FALSE
D14: =+'GM Batch1'!C29 -> YJ GASI 2 | E14: 1050000 | F14: =+'GM Batch1'!D29 -> 999.6 | G14: =E14*F14*1.1/1470 -> 785400 | H14: =+I14+K14+P14 -> 0 | K14: =+M14+O14 -> 0 | P14: =+R14+T14 -> 0 | V14: =+I14+K14+P14=E14*F14*1.1 -> FALSE | W14: =+E14*F14*1.1=I14+M14+O14+R14+T14 -> FALSE
D15: =+'GM Batch1'!C35 -> Dream 1 | E15: 1050000 | F15: =+'GM Batch1'!D35 -> 999.24 | G15: =E15*F15*1.1/1470 -> 785117.14 | H15: =+I15+K15+P15 -> 0 | K15: =+M15+O15 -> 0 | P15: =+R15+T15 -> 0 | V15: =+I15+K15+P15=E15*F15*1.1 -> FALSE | W15: =+E15*F15*1.1=I15+M15+O15+R15+T15 -> FALSE
D16: =+'GM Batch1'!C41 -> Dream 2 | E16: 1050000 | F16: =+'GM Batch1'!D41 -> 999.24 | G16: =E16*F16*1.1/1470 -> 785117.14 | H16: =+I16+K16+P16 -> 0 | K16: =+M16+O16 -> 0 | P16: =+R16+T16 -> 0 | V16: =+I16+K16+P16=E16*F16*1.1 -> FALSE | W16: =+E16*F16*1.1=I16+M16+O16+R16+T16 -> FALSE
D17: =+'GM Batch1'!C47 -> JEIL TECH 1 | E17: 1050000 | F17: =+'GM Batch1'!D47 -> 999.44 | G17: =E17*F17*1.1/1470 -> 785274.29 | H17: =+I17+K17+P17 -> 0 | K17: =+M17+O17 -> 0 | P17: =+R17+T17 -> 0 | V17: =+I17+K17+P17=E17*F17*1.1 -> FALSE | W17: =+E17*F17*1.1=I17+M17+O17+R17+T17 -> FALSE
D18: =+'GM Batch1'!C53 -> JEIL TECH 2 | E18: 1050000 | F18: =+'GM Batch1'!D53 -> 999.44 | G18: =E18*F18*1.1/1470 -> 785274.29 | H18: =+I18+K18+P18 -> 0 | K18: =+M18+O18 -> 0 | P18: =+R18+T18 -> 0 | V18: =+I18+K18+P18=E18*F18*1.1 -> FALSE | W18: =+E18*F18*1.1=I18+M18+O18+R18+T18 -> FALSE
D19: Total | F19: =SUM(F11:F18) -> 7995.72 | G19: =SUM(G11:G18) -> 6282351.4 | I19: =I20/1470 -> 0 | K19: =K20/1470 -> 0 | M19: =M20/1470 -> 0 | O19: =O20/1470 -> 0 | P19: =P20/1470 -> 0 | R19: =R20/1470 -> 0 | T19: =T20/1470 -> 0
H20: =+SUM(H11:H18) -> 0 | I20: =+SUM(I11:I18) -> 0 | K20: =+SUM(K11:K18) -> 0 | M20: =+SUM(M11:M18) -> 0 | O20: =+SUM(O11:O18) -> 0 | P20: =+SUM(P11:P18) -> 0 | R20: =+SUM(R11:R18) -> 0 | T20: =+SUM(T11:T18) -> 0
C21: GM_Batch2 APA | D21: =+'GM Batch2-APA'!C11 -> Jangchon 1 (APA) | E21: 1050000 | F21: =+'GM Batch2-APA'!D11 -> 551.04 | G21: =E21*F21*1.1/1470 -> 432960 | H21: =+I21+K21+P21 -> 0 | K21: =+M21+O21 -> 0 | P21: =+R21+T21 -> 0 | V21: =+I21+K21+P21=E21*F21*1.1 -> FALSE | W21: =+E21*F21*1.1=I21+M21+O21+R21+T21 -> FALSE
D22: =+'GM Batch2-APA'!C17 -> Soltop Masan 1 (APA) | E22: 1050000 | F22: =+'GM Batch2-APA'!D17 -> 399.04 | G22: =E22*F22*1.1/1470 -> 313531.43 | H22: =+I22+K22+P22 -> 0 | K22: =+M22+O22 -> 0 | P22: =+R22+T22 -> 0 | V22: =+I22+K22+P22=E22*F22*1.1 -> FALSE | W22: =+E22*F22*1.1=I22+M22+O22+R22+T22 -> FALSE
D23: =+'GM Batch2-APA'!C23 -> Hanil Mugok 15 (APA) | E23: 1050000 | F23: =+'GM Batch2-APA'!D23 -> 499.96 | G23: =E23*F23*1.1/1470 -> 392825.71 | H23: =+I23+K23+P23 -> 0 | K23: =+M23+O23 -> 0 | P23: =+R23+T23 -> 0 | V23: =+I23+K23+P23=E23*F23*1.1 -> FALSE | W23: =+E23*F23*1.1=I23+M23+O23+R23+T23 -> FALSE
D24: =+'GM Batch2-APA'!C29 -> Hanil Jigyeong 1 (APA) | E24: 1050000 | F24: =+'GM Batch2-APA'!D29 -> 499.96 | G24: =E24*F24*1.1/1470 -> 392825.71 | H24: =+I24+K24+P24 -> 0 | K24: =+M24+O24 -> 0 | P24: =+R24+T24 -> 0 | V24: =+I24+K24+P24=E24*F24*1.1 -> FALSE | W24: =+E24*F24*1.1=I24+M24+O24+R24+T24 -> FALSE
D25: =+'GM Batch2-APA'!C35 -> Hanil Jigyeong 2 (APA) | E25: 1050000 | F25: =+'GM Batch2-APA'!D35 -> 149.64 | G25: =E25*F25*1.1/1470 -> 117574.29 | H25: =+I25+K25+P25 -> 0 | K25: =+M25+O25 -> 0 | P25: =+R25+T25 -> 0 | V25: =+I25+K25+P25=E25*F25*1.1 -> FALSE | W25: =+E25*F25*1.1=I25+M25+O25+R25+T25 -> FALSE
D26: =+'GM Batch2-APA'!C41 -> Ho Duck4 (APA) | E26: 1050000 | F26: =+'GM Batch2-APA'!D41 -> 299.28 | G26: =E26*F26*1.1/1470 -> 235148.57 | H26: =+I26+K26+P26 -> 0 | K26: =+M26+O26 -> 0 | P26: =+R26+T26 -> 0 | V26: =+I26+K26+P26=E26*F26*1.1 -> FALSE | W26: =+E26*F26*1.1=I26+M26+O26+R26+T26 -> FALSE
D27: Total | F27: =SUM(F21:F26) -> 2398.92 | G27: =SUM(G21:G26) -> 1884865.7 | I27: =I28/1470 -> 0 | K27: =K28/1470 -> 0 | M27: =M28/1470 -> 0 | O27: =O28/1470 -> 0 | P27: =P28/1470 -> 0 | R27: =R28/1470 -> 0 | T27: =T28/1470 -> 0
H28: =+SUM(H21:H26) -> 0 | I28: =+SUM(I21:I26) -> 0 | K28: =+SUM(K21:K26) -> 0 | M28: =+SUM(M21:M26) -> 0 | O28: =+SUM(O21:O26) -> 0 | P28: =+SUM(P21:P26) -> 0 | R28: =+SUM(R21:R26) -> 0 | T28: =+SUM(T21:T26) -> 0 | V28: =+#REF!=H28 -> #REF!
C29: GM_Batch2 SPA | D29: =+'GM Batch2-SPA'!C11 -> Galsan (SPA) | E29: 1050000 | F29: =+'GM Batch2-SPA'!D11 -> 993.6 | G29: =E29*F29*1.1/1470 -> 780685.71 | H29: =+I29+K29+P29 -> 0 | K29: =+M29+O29 -> 0 | P29: =+R29+T29 -> 0 | V29: =+I29+K29+P29=E29*F29*1.1 -> FALSE | W29: =+E29*F29*1.1=I29+M29+O29+R29+T29 -> FALSE
D30: =+'GM Batch2-SPA'!C17 -> Mineuri (SPA) | E30: 1050000 | F30: =+'GM Batch2-SPA'!D17 -> 993.6 | G30: =E30*F30*1.1/1470 -> 780685.71 | H30: =+I30+K30+P30 -> 0 | K30: =+M30+O30 -> 0 | P30: =+R30+T30 -> 0 | V30: =+I30+K30+P30=E30*F30*1.1 -> FALSE | W30: =+E30*F30*1.1=I30+M30+O30+R30+T30 -> FALSE
D31: =+'GM Batch2-SPA'!C23 -> Seagol(SPA) | E31: 1050000 | F31: =+'GM Batch2-SPA'!D23 -> 993.6 | G31: =E31*F31*1.1/1470 -> 780685.71 | H31: =+I31+K31+P31 -> 0 | K31: =+M31+O31 -> 0 | P31: =+R31+T31 -> 0 | V31: =+I31+K31+P31=E31*F31*1.1 -> FALSE | W31: =+E31*F31*1.1=I31+M31+O31+R31+T31 -> FALSE
D32: =+'GM Batch2-SPA'!C29 -> Jaesan (SPA) | E32: 1050000 | F32: =+'GM Batch2-SPA'!D29 -> 993.6 | G32: =E32*F32*1.1/1470 -> 780685.71 | H32: =+I32+K32+P32 -> 0 | K32: =+M32+O32 -> 0 | P32: =+R32+T32 -> 0 | V32: =+I32+K32+P32=E32*F32*1.1 -> FALSE | W32: =+E32*F32*1.1=I32+M32+O32+R32+T32 -> FALSE
D33: Total | F33: =SUM(F29:F32) -> 3974.4 | G33: =SUM(G29:G32) -> 3122742.9 | I33: =I34/1470 -> 0 | K33: =K34/1470 -> 0 | M33: =M34/1470 -> 0 | O33: =O34/1470 -> 0 | P33: =P34/1470 -> 0 | R33: =R34/1470 -> 0 | T33: =T34/1470 -> 0
H34: =+SUM(H29:H32) -> 0 | I34: =+SUM(I29:I32) -> 0 | K34: =+SUM(K29:K32) -> 0 | M34: =+SUM(M29:M32) -> 0 | O34: =+SUM(O29:O32) -> 0 | P34: =+SUM(P29:P32) -> 0 | R34: =+SUM(R29:R32) -> 0 | T34: =+SUM(T29:T32) -> 0 | V34: =+#REF!=H34 -> #REF!
C35: DG_M&A_SPA_POSN | D35: =+'DG M&A-SPA_POSN'!C11 -> POS-1 | E35: =+'PAYMENT RATIO_RAW'!BK53/1000 -> 1125915.1 | F35: =+'DG M&A-SPA_POSN'!D11 -> 340.8 | G35: =E35*F35*1.1/1470 -> 287131.34 | H35: =+I35+K35+P35 -> 0 | K35: =+M35+O35 -> 0 | P35: =+R35+T35 -> 0 | V35: =+I35+K35+P35=E35*F35*1.1 -> FALSE | W35: =+E35*F35*1.1=I35+M35+O35+R35+T35 -> FALSE
D36: =+'DG M&A-SPA_POSN'!C17 -> POS-3 | E36: =+'PAYMENT RATIO_RAW'!BK54/1000 -> 1125915.1 | F36: =+'DG M&A-SPA_POSN'!D17 -> 144.84 | G36: =E36*F36*1.1/1470 -> 122030.82 | H36: =+I36+K36+P36 -> 0 | K36: =+M36+O36 -> 0 | P36: =+R36+T36 -> 0 | V36: =+I36+K36+P36=E36*F36*1.1 -> FALSE
D37: =+'DG M&A-SPA_POSN'!C23 -> POS-4 | E37: =+'PAYMENT RATIO_RAW'!BK55/1000 -> 1125915.1 | F37: =+'DG M&A-SPA_POSN'!D23 -> 807.98 | G37: =E37*F37*1.1/1470 -> 680740.54 | H37: =+I37+K37+P37 -> 0 | K37: =+M37+O37 -> 0 | P37: =+R37+T37 -> 0 | V37: =+I37+K37+P37=E37*F37*1.1 -> FALSE
D38: =+'DG M&A-SPA_POSN'!C29 -> POS-8 | E38: =+'PAYMENT RATIO_RAW'!BK56/1000 -> 1125915.1 | F38: =+'DG M&A-SPA_POSN'!D29 -> 249.92 | G38: =E38*F38*1.1/1470 -> 210562.98 | H38: =+I38+K38+P38 -> 0 | K38: =+M38+O38 -> 0 | P38: =+R38+T38 -> 0 | V38: =+I38+K38+P38=E38*F38*1.1 -> FALSE | W38: =+E38*F38*1.1=I38+M38+O38+R38+T38 -> FALSE
D39: Total | F39: =+SUM(F35:F38) -> 1543.54 | G39: =+SUM(G35:G38) -> 1300465.7 | H39: =H40/1470 -> 0 | I39: =I40/1470 -> 0 | J39: =J40/1470 -> 378254.36 | K39: =K40/1470 -> 0 | M39: =M40/1470 -> 0 | O39: =O40/1470 -> 0 | P39: =P40/1470 -> 0 | R39: =R40/1470 -> 0 | T39: =T40/1470 -> 0
H40: =+SUM(H35:H38) -> 0 | I40: =+SUM(I35:I38) -> 0 | J40: =+Summary!E7 -> 5.5603391e+08 | K40: =+SUM(K35:K38) -> 0 | M40: =+SUM(M35:M38) -> 0 | O40: =+SUM(O35:O38) -> 0 | P40: =+SUM(P35:P38) -> 0 | R40: =+SUM(R35:R38) -> 0 | T40: =+SUM(T35:T38) -> 0 | V40: =+#REF!=H40 -> #REF!
C41: GM_Batch1,2 | F41: =+F19+F27+F33 -> 14369.04 | G41: =+G33+G27+G19 -> 11289960 | H41: =H42/1470 -> 0 | I41: =I42/1470 -> 0 | J41: =J42/1470 -> 0 | K41: =K42/1470 -> 0 | M41: =M42/1470 -> 0 | O41: =O42/1470 -> 0 | P41: =P42/1470 -> 0 | R41: =R42/1470 -> 0 | T41: =T42/1470 -> 0
H42: =+H20+H28+H34 -> 0 | I42: =+I20+I28+I34 -> 0 | J42: =+J20+J28+J34 -> 0 | K42: =+K20+K28+K34 -> 0 | M42: =+M20+M28+M34 -> 0 | O42: =+O20+O28+O34 -> 0 | P42: =+P20+P28+P34 -> 0 | R42: =+R20+R28+R34 -> 0 | T42: =+T20+T28+T34 -> 0
C43: DG_M&A_SPA_POSN | F43: =+F39 -> 1543.54 | G43: =+G39 -> 1300465.7 | H43: =H44/1470 -> 0 | I43: =I44/1470 -> 0 | J43: =J44/1470 -> 378254.36 | K43: =K44/1470 -> 0 | M43: =M44/1470 -> 0 | O43: =O44/1470 -> 0 | P43: =P44/1470 -> 0 | R43: =R44/1470 -> 0 | T43: =T44/1470 -> 0
H44: =+H40 -> 0 | I44: =+I40 -> 0 | J44: =+J40 -> 5.5603391e+08 | K44: =+K40 -> 0 | M44: =+M40 -> 0 | O44: =+O40 -> 0 | P44: =+P40 -> 0 | R44: =+R40 -> 0 | T44: =+T40 -> 0
B45: Total | F45: =+F41+F43 -> 15912.58 | G45: =+G41+G43 -> 12590426 | H45: =H46/1470 -> 0 | I45: =I46/1470 -> 0 | J45: =J46/1470 -> 378254.36 | K45: =K46/1470 -> 0 | M45: =M46/1470 -> 0 | O45: =O46/1470 -> 0 | P45: =P46/1470 -> 0 | R45: =R46/1470 -> 0 | T45: =T46/1470 -> 0
H46: =+H44+H42 -> 0 | I46: =+I44+I42 -> 0 | J46: =+J44+J42 -> 5.5603391e+08 | K46: =+K44+K42 -> 0 | M46: =+M44+M42 -> 0 | O46: =+O44+O42 -> 0 | P46: =+P44+P42 -> 0 | R46: =+R44+R42 -> 0 | T46: =+T44+T42 -> 0

Sheet INPUTSHEET(Batch2)
A1: Input sheet for financial modelling purpose
E2: Project 1 | F2: Project 2 | G2: Project 3 | H2: Project 4 | I2: Project 5 | J2: Project 6 | K2: Project 7 | L2: Project 8 | M2: Project 9 | N2: Project 10 | O2: Project 10 | R2: Project 1 | S2: Project 2 | T2: Project 3 | U2: Project 4 | V2: Project 5 | W2: Project 6
B3: General inputs
N4: [Unit: KRW]
B5: Seller/developer name | C5: name | E5: Ssoltop Miracle Inc. | F5: Ssoltop Masan 1 Solar | G5: Mugok Inc. | H5: Jigyeong Inc. | I5: Seongsi 3 Solar | J5: Hoduck 4 Solar | K5: Galsan Solar | L5: Mineuri Solar | M5: Saegol Solar | N5: Jaesan Solar | R5: =+'[3]BT 2HO'!R11 -> 0 | S5: =+'[3]BT 2HO'!R16 -> 0 | T5: =+'[3]BT 2HO'!R21 -> 0 | U5: =+'[3]BT 2HO'!R26 -> 0 | V5: =+'[3]BT 2HO'!R31 -> 0 | W5: =+'[3]BT 2HO'!R41 -> 0
B6: Project name | C6: name | E6: Jangchon 1 | F6: Soltop Masan 1 | G6: Hanil Mugok 15 | H6: Hanil Jigyeong 1 | I6: Hanil Jigyeong 2 | J6: Ho Duck4 | K6: Galsan Solar | L6: Mineuri Solar | M6: Saegol Solar | N6: Jaesan Solar | R6: =+R5 -> 0 | S6: =+S5 -> 0 | T6: =+T5 -> 0 | U6: =+U5 -> 0 | V6: =+V5 -> 0 | W6: =+W5 -> 0
B7: Country | C7: Please select -- | E7: Korea | F7: Korea | G7: Korea | H7: Korea | I7: Korea | J7: Korea | K7: Korea | L7: Korea | M7: Korea | N7: Korea | O7: Korea | R7: Korea | S7: Korea | T7: Korea | U7: Korea | V7: Korea | W7: Korea
B8: Region | C8: Please specify the location of the plant | E8: Haenam-gun, Jeollanam-do | F8: Youngdong-gun, Chungcheongbuk-do | G8: Hapcheon-gun, Gyeongsangnam-do | H8: Youngyang-gun, Gyeongsangbuk-do | I8: Youngyang-gun, Gyeongsangbuk-do | J8: Goheung-gun, Jeollanam-do | K8: Bonghwa-gun, Gyeongsangbuk-do | L8: Bonghwa-gun, Gyeongsangbuk-do | M8: Bonghwa-gun, Gyeongsangbuk-do | N8: Bonghwa-gun, Gyeongsangbuk-do | R8: Busan | S8: Busan | T8: Chungcheongbuk-do | U8: Gyeonggi-do | V8: Gyeonggi-do | W8: Gyeonggi-do
B9: Technology | C9: Please select -- | E9: PV | F9: PV | G9: PV | H9: PV | I9: PV | J9: PV | K9: PV | L9: PV | M9: PV | N9: PV | O9: PV | R9: PV | S9: PV | T9: PV | U9: PV | V9: PV | W9: PV
B10: Project Status | C10: Please select -- | E10: =+'[4]입력 시트(0124)'!E10 -> RTB | F10: =+'[4]입력 시트(0124)'!F10 -> RTB | G10: =+'[4]입력 시트(0124)'!G10 -> RTB | H10: =+'[4]입력 시트(0124)'!H10 -> RTB | I10: =+'[4]입력 시트(0124)'!I10 -> RTB | J10: =+'[4]입력 시트(0124)'!J10 -> RTB | K10: =+'[4]입력 시트(0124)'!K10 -> RTB | L10: =+'[4]입력 시트(0124)'!L10 -> RTB | ... N10: =+'[4]입력 시트(0124)'!N10 -> RTB | O10: EBL | R10: RtB | S10: RtB | T10: RtB | U10: RtB | V10: RtB | W10: EBL
B11: Transaction structure | C11: Please provide background on the deal | E11: Ground | F11: Ground | G11: Ground | H11: Ground | I11: Ground | J11: Ground | K11: Ground | L11: Ground | M11: Ground | N11: Ground | O11: ROOFTOP | R11: ROOFTOP | S11: ROOFTOP | T11: ROOFTOP | U11: ROOFTOP | V11: ROOFTOP | W11: ROOFTOP
B12: Input source | C12: Please specify if this input list is based on internal assumptions or seller assumptions. | E12: Internal assumptions | F12: Internal assumptions | G12: Internal assumptions | H12: Internal assumptions | I12: Internal assumptions | J12: Internal assumptions | K12: Internal assumptions | L12: Internal assumptions | M12: Internal assumptions | N12: Internal assumptions | O12: Internal assumptions | R12: Internal assumptions | S12: Internal assumptions | T12: Internal assumptions | U12: Internal assumptions | V12: Internal assumptions | W12: Internal assumptions
B14: Currency | C14: Please select currency for financial modelling purposes -- | E14: KRW | F14: KRW | G14: KRW | H14: KRW | I14: KRW | J14: KRW | K14: KRW | L14: KRW | M14: KRW | N14: KRW | O14: KRW | R14: KRW | S14: KRW | T14: KRW | U14: KRW | V14: KRW | W14: KRW
B16: RTB date | C16: date (day/month/year) | E16: 46143 | F16: 46143 | G16: 46143 | H16: 46143 | I16: 46143 | J16: 46143 | K16: 46266 | L16: 46266 | M16: 46266 | N16: 46266 | O16: 46022 | R16: 45962 | S16: 45962 | T16: 45962 | U16: 45962 | V16: 45962 | W16: 46022
B17: Construction phase | C17: Months | E17: 5 | F17: 5 | G17: 5 | H17: 5 | I17: 5 | J17: 5 | K17: 5 | L17: 5 | M17: 5 | N17: 5 | O17: 5 | R17: 5 | S17: 5 | T17: 5 | U17: 5 | V17: 5 | W17: 5
B18: SOC date | E18: =+EDATE(E16,2) -> 46204 | F18: =+EDATE(F16,2) -> 46204 | G18: =+EDATE(G16,2) -> 46204 | H18: =+EDATE(H16,2) -> 46204 | I18: =+EDATE(I16,2) -> 46204 | J18: =+EDATE(J16,2) -> 46204 | K18: =+EDATE(K16,2) -> 46327 | L18: =+EDATE(L16,2) -> 46327 | ... N18: =+EDATE(N16,2) -> 46327 | R18: 46053 | S18: 46022 | T18: 46022 | U18: 46022 | V18: 46022 | W18: 46053
B19: COD date | C19: date (day/month/year) | E19: =+EDATE(E16,5) -> 46296 | F19: =+EDATE(F16,5) -> 46296 | G19: =+EDATE(G16,5) -> 46296 | H19: =+EDATE(H16,5) -> 46296 | I19: =+EDATE(I16,5) -> 46296 | J19: =+EDATE(J16,5) -> 46296 | K19: =+EDATE(K16,5) -> 46419 | L19: =+EDATE(L16,5) -> 46419 | ... N19: =+EDATE(N16,5) -> 46419 | O19: 46203 | R19: 46203 | S19: 46173 | T19: 46173 | U19: 46173 | V19: 46173 | W19: 46203
B20: Asset Useful Life | C20: years | D20: Default will be 20 years | E20: 35 | F20: 35 | G20: 35 | H20: 35 | I20: 35 | J20: 35 | K20: 35 | L20: 35 | M20: 35 | N20: 35 | O20: 20 | R20: 20 | S20: 20 | T20: 20 | U20: 20 | V20: 20 | W20: 20
B22: WTG / Panels number | C22: If PV in E9 please put N/A | E22: N/A | F22: N/A | G22: N/A | H22: N/A | I22: N/A | J22: N/A | K22: N/A | L22: N/A | M22: N/A | N22: N/A | O22: N/A | R22: N/A | S22: N/A | T22: N/A | U22: N/A | V22: N/A | W22: N/A
B23: WTG / Panels name | C23: If PV in E9 please put N/A | E23: N/A | F23: N/A | G23: N/A | H23: N/A | I23: N/A | J23: N/A | K23: N/A | L23: N/A | M23: N/A | N23: N/A | O23: N/A | R23: N/A | S23: N/A | T23: N/A | U23: N/A | V23: N/A | W23: N/A
B24: Total Capacity DC | C24: MWp | E24: =+'Input 기초'!F19/1000 -> 0.55104 | F24: =+'Input 기초'!G19/1000 -> 0.39904 | G24: =+'Input 기초'!H19/1000 -> 0.49996 | H24: =+'Input 기초'!I19/1000 -> 0.49996 | I24: =+'Input 기초'!J19/1000 -> 0.14964 | J24: =+'Input 기초'!K19/1000 -> 0.29928 | K24: =+'Input 기초'!L19/1000 -> 0.61776 | L24: =+'Input 기초'!M19/1000 -> 0.56496 | ... N24: =+'Input 기초'!O19/1000 -> 0.62568 | R24: =+'[3]CAPEX_Input_3,7HO(수정용)'!T40 -> 0.084744677 | S24: =+'[3]CAPEX_Input_3,7HO(수정용)'!T33 -> 0.024285621 | T24: =+'[3]CAPEX_Input_3,7HO(수정용)'!T34 -> 0.036847296 | U24: =+'[3]CAPEX_Input_3,7HO(수정용)'!T35 -> 0.019635 | V24: =+'[3]CAPEX_Input_3,7HO(수정용)'!T37 -> 0.0112118 | W24: =+'[3]CAPEX_Input_3,7HO(수정용)'!T41 -> 0.0423984
B25: Total Capacity AC | C25: Mwac . If Wind in E9 please put N/A
B26: DC/AC ratio | C26: If Wind in E9 please put N/A | E26: =+E24/E25 -> #DIV/0! | F26: =+F24/F25 -> #DIV/0! | G26: =+G24/G25 -> #DIV/0! | H26: =+H24/H25 -> #DIV/0! | I26: =+I24/I25 -> #DIV/0! | J26: =+J24/J25 -> #DIV/0! | K26: =+K24/K25 -> #DIV/0! | L26: =+L24/L25 -> #DIV/0! | ... O26: =+O24/O25 -> #DIV/0! | R26: =+R24/R25 -> #DIV/0! | S26: =+S24/S25 -> #DIV/0! | T26: =+T24/T25 -> #DIV/0! | U26: =+U24/U25 -> #DIV/0! | V26: =+V24/V25 -> #DIV/0! | W26: =+W24/W25 -> #DIV/0!
B28: Production
B30: Load Factor (After Curtailment)
B31: P50 | C31: %
B32: P75 | C32: %
B33: P90 | C33: %
B35: Number of Equivalent Hours (day)
B36: P50 | C36: Hours | E36: 3.5232877 | F36: 3.9013699 | G36: 3.9643836 | H36: 3.7917808 | I36: 3.7917808 | J36: 4.090411 | K36: 3.9726027 | L36: 3.9726027 | M36: 3.9671233 | N36: 3.9726027 | O36: =+'[3]CAPEX_Input_3,7HO(수정용)'!G44/365 -> 3.8630137 | R36: =+'[3]CAPEX_Input_3,7HO(수정용)'!V40/365 -> 0 | S36: =+'[3]CAPEX_Input_3,7HO(수정용)'!V33/365 -> 0 | T36: =+'[3]CAPEX_Input_3,7HO(수정용)'!V34/365 -> 0 | U36: =+'[3]CAPEX_Input_3,7HO(수정용)'!V35/365 -> 0 | V36: =+'[3]CAPEX_Input_3,7HO(수정용)'!V37/365 -> 0 | W36: =+'[3]CAPEX_Input_3,7HO(수정용)'!V41/365 -> 0
B37: P75 | C37: Hours
B38: P90 | C38: Hours
B40: Production
B41: P50 | C41: MWh | E41: =+E24*E36*365 -> 708.63744 | F41: =+F24*F36*365 -> 568.23296 | G41: =+G24*G36*365 -> 723.44212 | H41: =+H24*H36*365 -> 691.94464 | I41: =+I24*I36*365 -> 207.10176 | J41: =+J24*J36*365 -> 446.82504 | K41: =+K24*K36*365 -> 895.752 | L41: =+L24*L36*365 -> 819.192 | ... O41: =+O24*O36*365 -> 0 | R41: =+R24*R36*365 -> 0 | S41: =+S24*S36*365 -> 0 | T41: =+T24*T36*365 -> 0 | U41: =+U24*U36*365 -> 0 | V41: =+V24*V36*365 -> 0 | W41: =+W24*W36*365 -> 0
B42: P75 | C42: MWh
B43: Specific Production | C43: [kWh/kWp]
B45: Availability | C45: %
B47: Months before degradation | C47: %
B48: Start of degradation | C48: %
B49: Degradation Factor | C49: % | D49: Default will be 20 years | E49: 0.004 | F49: 0.004 | G49: 0.004 | H49: 0.004 | I49: 0.004 | J49: 0.004 | K49: 0.004 | L49: 0.004 | M49: 0.004 | N49: 0.004 | O49: 0.002 | R49: 0.002 | S49: 0.002 | T49: 0.002 | U49: 0.002 | V49: 0.002 | W49: 0.002
B51: Electricity losses | C51: % | E51: 0.02 | F51: 0.02 | G51: 0.02 | H51: 0.02 | I51: 0.02 | J51: 0.02 | K51: 0.02 | L51: 0.02 | M51: 0.02 | N51: 0.02 | O51: 0.02 | R51: 0.02 | S51: 0.02 | T51: 0.02 | U51: 0.02 | V51: 0.02 | W51: 0.02
B53: Grid and BoS losses | C53: %
B55: Other losses | C55: %
B57: Opex - year 1 | D57: Unit | E57: Cost | F57: Cost | G57: Cost | H57: Cost | I57: Cost | J57: Cost | K57: Cost | L57: Cost | M57: Cost | N57: Cost | O57: Cost | R57: Cost | S57: Cost | T57: Cost | U57: Cost | V57: Cost | W57: Cost
J58: =+J61+J106+IFERROR(J125,0) -> 5536680 | K58: =+K61+K106+IFERROR(K125,0) -> 11428560 | L58: =+L61+L106+IFERROR(L125,0) -> 10451760 | M58: =+M61+M106+IFERROR(M125,0) -> 11746020 | N58: =+'[5]O&M'!N14 -> 0 | O58: =+'[5]O&M'!Q14 -> 0 | R58: =+'[5]O&M'!T14 -> 0 | W58: =+W61+W106+IFERROR(W125,0) -> #REF!
B59: O&M | E59: =+E61+E88+E106+E152='Input 기초'!F21 -> TRUE | F59: =+F61+F88+F106+F152='Input 기초'!G21 -> TRUE | G59: =+G61+G88+G106+G152='Input 기초'!H21 -> TRUE | H59: =+H61+H88+H106+H152='Input 기초'!I21 -> TRUE | I59: =+I61+I88+I106+I152='Input 기초'!J21 -> TRUE | J59: =+J61+J88+J106+J152='Input 기초'!K21 -> TRUE | K59: =+K61+K88+K106+K152='Input 기초'!L21 -> TRUE | L59: =+L61+L88+L106+L152='Input 기초'!M21 -> TRUE | ... N59: =+N61+N88+N106+N152='Input 기초'!O21 -> TRUE | R59: =+R61+R70+R88+R106+R115+R125+R134+R143+R152='Input 기초'!#REF! -> #REF! | S59: =+S61+S70+S88+S106+S115+S125+S134+S143+S152='Input 기초'!#REF! -> #REF! | T59: =+T61+T70+T88+T106+T115+T125+T134+T143+T152='Input 기초'!#REF! -> #REF! | U59: =+U61+U70+U88+U106+U115+U125+U134+U143+U152='Input 기초'!#REF! -> #REF! | V59: =+V61+V70+V88+V106+V115+V125+V134+V143+V152='Input 기초'!#REF! -> #REF! | W59: =+W61+W70+W88+W106+W115+W125+W134+W143+W152='Input 기초'!#REF! -> #REF!
B60: Currency
B61: Cost | C61: Please select D60 -- | D61: 000/year | E61: =+'Input 기초'!F22 -> 6888000 | F61: =+'Input 기초'!G22 -> 4988000 | G61: =+'Input 기초'!H22 -> 6249500 | H61: =+'Input 기초'!I22 -> 6249500 | I61: =+'Input 기초'!J22 -> 1870500 | J61: =+'Input 기초'!K22 -> 3741000 | K61: =+'Input 기초'!L22 -> 7722000 | L61: =+'Input 기초'!M22 -> 7062000 | ... N61: =+'Input 기초'!O22 -> 7821000 | O61: =+'Input 기초'!#REF! -> #REF! | R61: =+'Input 기초'!#REF! -> #REF! | S61: =+'Input 기초'!#REF! -> #REF! | T61: =+'Input 기초'!#REF! -> #REF! | U61: =+'Input 기초'!#REF! -> #REF! | V61: =+'Input 기초'!#REF! -> #REF! | W61: =+'Input 기초'!#REF! -> #REF!
B62: Indexed? | C62: 0 or 1 | E62: No | F62: No | G62: No | H62: No | I62: No | J62: No | K62: No | L62: No | M62: No | N62: No | O62: No | R62: No | S62: No | T62: No | U62: No | V62: No | W62: No
B63: Indexation reference date | C63: date | D63: Default will be 2026 | E63: =+E18 -> 46204 | F63: =+F18 -> 46204 | G63: =+G18 -> 46204 | H63: =+H18 -> 46204 | I63: =+I18 -> 46204 | J63: =+J18 -> 46204 | K63: =+K18 -> 46327 | L63: =+L18 -> 46327 | ... O63: =+O18 -> 0 | R63: 46112 | S63: 46112 | T63: 46112 | U63: 46112 | V63: 46112 | W63: 46112
B64: Indexation % | C64: % | D64: Please specify if it's CPI or other | E64: CPI | F64: CPI | G64: CPI | H64: CPI | I64: CPI | J64: CPI | K64: CPI | L64: CPI | M64: CPI | N64: CPI | O64: CPI | R64: CPI | S64: CPI | T64: CPI | U64: CPI | V64: CPI | W64: CPI
B65: Cost starting date | C65: date | E65: =+E19 -> 46296 | F65: =+F19 -> 46296 | G65: =+G19 -> 46296 | H65: =+H19 -> 46296 | I65: =+I19 -> 46296 | J65: =+J19 -> 46296 | K65: =+K19 -> 46419 | L65: =+L19 -> 46419 | ... O65: =+O19 -> 46203 | R65: =R19 -> 46203 | S65: =S19 -> 46173 | T65: =T19 -> 46173 | U65: =U19 -> 46173 | V65: =V19 -> 46173 | W65: =W19 -> 46203
B66: Comments | C66: The total amount of O&M is KRW 12.5 million/MW. OR intends to proceed O&M through an outsourced O&M company.
B68: Asset Management
B69: Currency
B70: Cost | C70: Please select D60 -- | D70: 000/year | E70: =+'Input 기초'!F23 -> 0 | F70: =+'Input 기초'!G23 -> 0 | G70: =+'Input 기초'!H23 -> 0 | H70: =+'Input 기초'!I23 -> 0 | I70: =+'Input 기초'!J23 -> 0 | J70: =+'Input 기초'!K23 -> 0 | K70: =+'Input 기초'!L23 -> 0 | L70: =+'Input 기초'!M23 -> 0 | ... N70: =+'Input 기초'!O23 -> 0 | O70: =+'Input 기초'!#REF! -> #REF! | R70: =+'Input 기초'!#REF! -> #REF! | S70: =+'Input 기초'!#REF! -> #REF! | T70: =+'Input 기초'!#REF! -> #REF! | U70: =+'Input 기초'!#REF! -> #REF! | V70: =+'Input 기초'!#REF! -> #REF! | W70: =+'Input 기초'!#REF! -> #REF!
B71: Indexed? | C71: 0 or 1 | E71: 1 | F71: 1 | G71: 1 | H71: 1 | I71: 1 | J71: 1 | K71: 1 | L71: 1 | M71: 1 | N71: 1 | O71: 1 | R71: 1 | S71: 1 | T71: 1 | U71: 1 | V71: 1 | W71: 1
B72: Indexation reference date | C72: date | D72: Default will be 2026 | E72: - | F72: - | G72: - | H72: - | I72: - | J72: - | K72: - | L72: - | M72: - | N72: - | O72: - | R72: =+EDATE(R16,-25) -> 45200 | S72: =+EDATE(S16,-25) -> 45200 | T72: =+EDATE(T16,-25) -> 45200 | U72: =+EDATE(U16,-25) -> 45200 | V72: =+EDATE(V16,-25) -> 45200 | W72: =+EDATE(W16,-25) -> 45260
B73: Indexation % | C73: % | D73: Please specify if it's CPI or other | E73: =+'[5]입력 시트(0124)'!E72 -> CPI | F73: =+'[5]입력 시트(0124)'!F72 -> CPI | G73: =+'[5]입력 시트(0124)'!G72 -> CPI | H73: CPI | I73: CPI | J73: CPI | K73: CPI | L73: CPI | M73: CPI | N73: CPI | O73: CPI | R73: =+'[5]입력 시트(0124)'!T72 -> 0 | S73: =+'[5]입력 시트(0124)'!U72 -> 0 | T73: =+'[5]입력 시트(0124)'!V72 -> 0 | U73: =+'[5]입력 시트(0124)'!W72 -> 0 | V73: =+'[5]입력 시트(0124)'!X72 -> 0 | W73: CPI
B74: Cost starting date | C74: date | E74: - | F74: - | G74: - | H74: - | I74: - | J74: - | K74: - | L74: - | M74: - | N74: - | O74: - | R74: =R19 -> 46203 | S74: =S19 -> 46173 | T74: =T19 -> 46173 | U74: =U19 -> 46173 | V74: =V19 -> 46173 | W74: =W19 -> 46203
B75: Comments
B77: Security Services
B78: Currency | E78: EUR | F78: EUR | G78: EUR | H78: EUR | I78: EUR | J78: EUR | K78: EUR | L78: EUR | M78: EUR | N78: EUR | O78: EUR | R78: EUR | S78: EUR | T78: EUR | U78: EUR | V78: EUR | W78: EUR
B79: Cost | C79: Please select D60 -- | D79: 000/year
B80: Indexed? | C80: 0 or 1 | E80: 1 | F80: 1 | G80: 1 | H80: 1 | I80: 1 | J80: 1 | K80: 1 | L80: 1 | M80: 1 | N80: 1 | O80: 1 | R80: 1 | S80: 1 | T80: 1 | U80: 1 | V80: 1 | W80: 1
B81: Indexation reference date | C81: date | D81: Default will be 2023 | E81: =+'[5]입력 시트(0124)'!E80 -> 45901 | F81: =+'[5]입력 시트(0124)'!F80 -> 45901 | G81: =+'[5]입력 시트(0124)'!G80 -> 45901 | H81: =+'[5]입력 시트(0124)'!H80 -> 45901 | I81: =+'[5]입력 시트(0124)'!I80 -> 45931 | J81: =+'[5]입력 시트(0124)'!F80 -> 45901 | K81: =+'[5]입력 시트(0124)'!G80 -> 45901 | L81: =+'[5]입력 시트(0124)'!H80 -> 45901 | M81: =+'[5]입력 시트(0124)'!I80 -> 45931 | N81: =+'[5]입력 시트(0124)'!N80 -> 0 | O81: =+'[5]입력 시트(0124)'!Q80 -> 0 | R81: =+'[5]입력 시트(0124)'!T80 -> 0 | S81: =+'[5]입력 시트(0124)'!U80 -> 0 | T81: =+'[5]입력 시트(0124)'!V80 -> 0 | U81: =+'[5]입력 시트(0124)'!W80 -> 0 | V81: =+'[5]입력 시트(0124)'!X80 -> 0 | W81: =+'[5]입력 시트(0124)'!U80 -> 0
B82: Indexation % | C82: % | D82: Please specify if it's CPI or other | E82: =+'[5]입력 시트(0124)'!E81 -> CPI | F82: =+'[5]입력 시트(0124)'!F81 -> CPI | G82: =+'[5]입력 시트(0124)'!G81 -> CPI | H82: =+'[5]입력 시트(0124)'!H81 -> CPI | I82: =+'[5]입력 시트(0124)'!I81 -> CPI | J82: =+'[5]입력 시트(0124)'!F81 -> CPI | K82: =+'[5]입력 시트(0124)'!G81 -> CPI | L82: =+'[5]입력 시트(0124)'!H81 -> CPI | M82: =+'[5]입력 시트(0124)'!I81 -> CPI | N82: =+'[5]입력 시트(0124)'!N81 -> 0 | O82: =+'[5]입력 시트(0124)'!Q81 -> 0 | R82: =+'[5]입력 시트(0124)'!T81 -> 0 | S82: =+'[5]입력 시트(0124)'!U81 -> 0 | T82: =+'[5]입력 시트(0124)'!V81 -> 0 | U82: =+'[5]입력 시트(0124)'!W81 -> 0 | V82: =+'[5]입력 시트(0124)'!X81 -> 0 | W82: =+'[5]입력 시트(0124)'!U81 -> 0
B83: Cost starting date | C83: date | E83: =+'[5]입력 시트(0124)'!E82 -> 45901 | F83: =+'[5]입력 시트(0124)'!F82 -> 45901 | G83: =+'[5]입력 시트(0124)'!G82 -> 45901 | H83: =+'[5]입력 시트(0124)'!H82 -> 45901 | I83: =+'[5]입력 시트(0124)'!I82 -> 45931 | J83: =+'[5]입력 시트(0124)'!F82 -> 45901 | K83: =+'[5]입력 시트(0124)'!G82 -> 45901 | L83: =+'[5]입력 시트(0124)'!H82 -> 45901 | M83: =+'[5]입력 시트(0124)'!I82 -> 45931 | N83: =+'[5]입력 시트(0124)'!N82 -> 0 | O83: =+'[5]입력 시트(0124)'!Q82 -> 0 | R83: =+'[5]입력 시트(0124)'!T82 -> 0 | S83: =+'[5]입력 시트(0124)'!U82 -> 0 | T83: =+'[5]입력 시트(0124)'!V82 -> 0 | U83: =+'[5]입력 시트(0124)'!W82 -> 0 | V83: =+'[5]입력 시트(0124)'!X82 -> 0 | W83: =+'[5]입력 시트(0124)'!U82 -> 0
B84: Comments | C84: Included in O&M cost
B86: MAS (accounting and other administrative not included AM)
B87: Currency
B88: Cost | C88: Please select D60 -- | D88: 000/year | E88: =+'Input 기초'!F24 -> 1432704 | F88: =+'Input 기초'!G24 -> 1037504 | G88: =+'Input 기초'!H24 -> 1299896 | H88: =+'Input 기초'!I24 -> 1299896 | I88: =+'Input 기초'!J24 -> 389064 | J88: =+'Input 기초'!K24 -> 778128 | K88: =+'Input 기초'!L24 -> 1606176 | L88: =+'Input 기초'!M24 -> 1468896 | ... N88: =+'Input 기초'!O24 -> 1626768 | O88: =+'Input 기초'!#REF! -> #REF! | R88: =+'Input 기초'!#REF! -> #REF! | S88: =+'Input 기초'!#REF! -> #REF! | T88: =+'Input 기초'!#REF! -> #REF! | U88: =+'Input 기초'!#REF! -> #REF! | V88: =+'Input 기초'!#REF! -> #REF! | W88: =+'Input 기초'!#REF! -> #REF!
B89: Indexed? | C89: 0 or 1 | E89: 1 | F89: 1 | G89: 1 | H89: 1 | I89: 1 | J89: 1 | K89: 1 | L89: 1 | M89: 1 | N89: 1 | O89: 1 | R89: 1 | S89: 1 | T89: 1 | U89: 1 | V89: 1 | W89: 1
B90: Indexation reference date | C90: date | D90: Default will be 2026 | E90: =+E18 -> 46204 | F90: =+F18 -> 46204 | G90: =+G18 -> 46204 | H90: =+H18 -> 46204 | I90: =+I18 -> 46204 | J90: =+J18 -> 46204 | K90: =+K18 -> 46327 | L90: =+L18 -> 46327 | ... O90: =+O18 -> 0 | R90: 46112 | S90: 46112 | T90: 46112 | U90: 46112 | V90: 46112 | W90: 46112
B91: Indexation % | C91: % | D91: Please specify if it's CPI or other | E91: =+'[5]입력 시트(0124)'!E90 -> CPI | F91: CPI | G91: CPI | H91: CPI | I91: CPI | J91: CPI | K91: CPI | L91: CPI | M91: CPI | N91: CPI | O91: CPI | R91: =+'[5]입력 시트(0124)'!T90 -> 0 | S91: CPI | T91: CPI | U91: CPI | V91: CPI | W91: CPI
B92: Cost starting date | C92: date | E92: =+E19 -> 46296 | F92: =+F19 -> 46296 | G92: =+G19 -> 46296 | H92: =+H19 -> 46296 | I92: =+I19 -> 46296 | J92: =+J19 -> 46296 | K92: =+K19 -> 46419 | L92: =+L19 -> 46419 | ... O92: =+O19 -> 46203 | R92: =R19 -> 46203 | S92: =S19 -> 46173 | T92: =T19 -> 46173 | U92: =U19 -> 46173 | V92: =V19 -> 46173 | W92: =W19 -> 46203
B93: Comments | C93: Calculated as KRW 2.6 Million/MW
B95: Energy Consumption
B96: Currency
B97: Cost | C97: Please select D60 -- | D97: % Revenue | E97: - | F97: - | G97: - | H97: - | I97: - | J97: - | K97: - | L97: - | M97: - | N97: - | O97: - | R97: - | S97: - | T97: - | U97: - | V97: - | W97: -
B98: Indexed? | C98: 0 or 1 | E98: No | F98: No | G98: No | H98: No | I98: No | J98: No | K98: No | L98: No | M98: No | N98: No | O98: No | R98: No | S98: No | T98: No | U98: No | V98: No | W98: No
B99: Indexation reference date | C99: date | D99: Default will be 2023 | E99: =+EDATE(E16,-25) -> 45383 | F99: =+EDATE(F16,-25) -> 45383 | G99: =+EDATE(G16,-25) -> 45383 | H99: =+EDATE(H16,-25) -> 45383 | I99: =+EDATE(I16,-25) -> 45383 | J99: =+EDATE(J16,-25) -> 45383 | K99: =+EDATE(K16,-25) -> 45505 | L99: =+EDATE(L16,-25) -> 45505 | ... O99: =+EDATE(O16,-25) -> 45260 | R99: =+EDATE(R16,-25) -> 45200 | S99: =+EDATE(S16,-25) -> 45200 | T99: =+EDATE(T16,-25) -> 45200 | U99: =+EDATE(U16,-25) -> 45200 | V99: =+EDATE(V16,-25) -> 45200 | W99: =+EDATE(W16,-25) -> 45260
B100: Indexation % | C100: % | D100: Please specify if it's CPI or other | E100: =+'[5]입력 시트(0124)'!E99 -> N/A | F100: =+'[5]입력 시트(0124)'!F99 -> N/A | G100: =+'[5]입력 시트(0124)'!G99 -> N/A | H100: =+'[5]입력 시트(0124)'!H99 -> N/A | I100: =+'[5]입력 시트(0124)'!I99 -> N/A | J100: N/A | K100: N/A | L100: N/A | M100: N/A | N100: =+'[5]입력 시트(0124)'!N99 -> 0 | O100: =+'[5]입력 시트(0124)'!Q99 -> 0 | R100: =+'[5]입력 시트(0124)'!T99 -> 0 | S100: =+'[5]입력 시트(0124)'!U99 -> 0 | T100: =+'[5]입력 시트(0124)'!V99 -> 0 | U100: =+'[5]입력 시트(0124)'!W99 -> 0 | V100: =+'[5]입력 시트(0124)'!X99 -> 0 | W100: N/A
B101: Cost starting date | C101: date | E101: =+'[5]입력 시트(0124)'!E100 -> 45901 | F101: =+'[5]입력 시트(0124)'!F100 -> 45901 | G101: =+'[5]입력 시트(0124)'!G100 -> 45901 | H101: =+'[5]입력 시트(0124)'!H100 -> 45901 | I101: =+'[5]입력 시트(0124)'!I100 -> 45931 | J101: =+'[5]입력 시트(0124)'!J100 -> 0 | K101: =+'[5]입력 시트(0124)'!K100 -> 0 | L101: =+'[5]입력 시트(0124)'!L100 -> 0 | ... N101: =+'[5]입력 시트(0124)'!N100 -> 0 | O101: =+'[5]입력 시트(0124)'!Q100 -> 0 | R101: =+'[5]입력 시트(0124)'!T100 -> 0 | S101: =+'[5]입력 시트(0124)'!U100 -> 0 | T101: =+'[5]입력 시트(0124)'!V100 -> 0 | U101: =+'[5]입력 시트(0124)'!W100 -> 0 | V101: =+'[5]입력 시트(0124)'!X100 -> 0 | W101: =+'[5]입력 시트(0124)'!Y100 -> 0
B102: Comments | C102: Included in O&M cost
B104: Insurance
B105: Currency
B106: Cost | C106: Please select D60 -- | D106: 000/year | E106: =+'Input 기초'!F25 -> 3306240 | F106: =+'Input 기초'!G25 -> 2394240 | G106: =+'Input 기초'!H25 -> 2999760 | H106: =+'Input 기초'!I25 -> 2999760 | I106: =+'Input 기초'!J25 -> 897840 | J106: =+'Input 기초'!K25 -> 1795680 | K106: =+'Input 기초'!L25 -> 3706560 | L106: =+'Input 기초'!M25 -> 3389760 | ... N106: =+'Input 기초'!O25 -> 3754080 | O106: =+'Input 기초'!#REF! -> #REF! | R106: =+'Input 기초'!#REF! -> #REF! | S106: =+'Input 기초'!#REF! -> #REF! | T106: =+'Input 기초'!#REF! -> #REF! | U106: =+'Input 기초'!#REF! -> #REF! | V106: =+'Input 기초'!#REF! -> #REF! | W106: =+'Input 기초'!#REF! -> #REF!
B107: Indexed? | C107: 0 or 1 | E107: No | F107: No | G107: No | H107: No | I107: No | J107: No | K107: No | L107: No | M107: No | N107: No | O107: No | R107: No | S107: No | T107: No | U107: No | V107: No | W107: No
B108: Indexation reference date | C108: date | D108: Default will be 2026 | E108: =+E18 -> 46204 | F108: =+F18 -> 46204 | G108: =+G18 -> 46204 | H108: =+H18 -> 46204 | I108: =+I18 -> 46204 | J108: =+J18 -> 46204 | K108: =+K18 -> 46327 | L108: =+L18 -> 46327 | ... O108: =+O18 -> 0 | R108: 46112 | S108: 46112 | T108: 46112 | U108: 46112 | V108: 46112 | W108: 46112
B109: Indexation % | C109: % | D109: Please specify if it's CPI or other | E109: =+'[5]입력 시트(0124)'!E108 -> N/A | F109: =+'[5]입력 시트(0124)'!F108 -> N/A | G109: =+'[5]입력 시트(0124)'!G108 -> N/A | H109: =+'[5]입력 시트(0124)'!H108 -> N/A | I109: =+'[5]입력 시트(0124)'!I108 -> N/A | J109: N/A | K109: N/A | L109: N/A | M109: N/A | N109: N/A | O109: N/A | R109: =+'[5]입력 시트(0124)'!T108 -> 0 | S109: =+'[5]입력 시트(0124)'!U108 -> 0 | T109: =+'[5]입력 시트(0124)'!V108 -> 0 | U109: =+'[5]입력 시트(0124)'!W108 -> 0 | V109: =+'[5]입력 시트(0124)'!X108 -> 0 | W109: N/A
B110: Cost starting date | C110: date | E110: =+E19 -> 46296 | F110: =+F19 -> 46296 | G110: =+G19 -> 46296 | H110: =+H19 -> 46296 | I110: =+I19 -> 46296 | J110: =+J19 -> 46296 | K110: =+K19 -> 46419 | L110: =+L19 -> 46419 | ... O110: =+O19 -> 46203 | R110: =R19 -> 46203 | S110: =S19 -> 46173 | T110: =T19 -> 46173 | U110: =U19 -> 46173 | V110: =V19 -> 46173 | W110: =W19 -> 46203
B111: Comments | C111: Calculated as KRW 6 Million/MW
B113: Local tax payment
B114: Currency
B115: Cost | C115: Please select D60 -- | D115: % Revenue
B116: Indexed? | C116: 0 or 1 | E116: No | F116: No | G116: No | H116: No | I116: No | J116: No | K116: No | L116: No | M116: No | N116: No | O116: No | R116: No | S116: No | T116: No | U116: No | V116: No | W116: No
B117: Indexation reference date | C117: date | D117: Default will be 2026 | E117: - | F117: - | G117: - | H117: =+'[5]입력 시트(0124)'!H116 -> 45901 | I117: =+'[5]입력 시트(0124)'!I116 -> 45931 | J117: 45931 | K117: 45931 | L117: 45931 | M117: 45931 | N117: =+'[5]입력 시트(0124)'!N116 -> 0 | O117: =+'[5]입력 시트(0124)'!Q116 -> 0 | R117: =+'[5]입력 시트(0124)'!T116 -> 0 | S117: =+'[5]입력 시트(0124)'!U116 -> 0 | T117: =+'[5]입력 시트(0124)'!V116 -> 0 | U117: =+'[5]입력 시트(0124)'!W116 -> 0 | V117: =+'[5]입력 시트(0124)'!X116 -> 0 | W117: 45931
B118: Indexation % | C118: % | D118: Please specify if it's CPI or other | E118: =+'[5]입력 시트(0124)'!E117 -> N/A | F118: =+'[5]입력 시트(0124)'!F117 -> N/A | G118: =+'[5]입력 시트(0124)'!G117 -> N/A | H118: =+'[5]입력 시트(0124)'!H117 -> N/A | I118: =+'[5]입력 시트(0124)'!I117 -> N/A | J118: N/A | K118: N/A | L118: N/A | M118: N/A | N118: N/A | O118: N/A | R118: =+'[5]입력 시트(0124)'!T117 -> 0 | S118: =+'[5]입력 시트(0124)'!U117 -> 0 | T118: =+'[5]입력 시트(0124)'!V117 -> 0 | U118: =+'[5]입력 시트(0124)'!W117 -> 0 | V118: =+'[5]입력 시트(0124)'!X117 -> 0 | W118: N/A
B119: Cost starting date | C119: date | E119: - | F119: - | G119: - | H119: =+'[5]입력 시트(0124)'!H118 -> 45901 | I119: =+'[5]입력 시트(0124)'!I118 -> 45931 | J119: 45931 | K119: 45931 | L119: 45931 | M119: 45931 | N119: =+'[5]입력 시트(0124)'!N118 -> 0 | O119: =+'[5]입력 시트(0124)'!Q118 -> 0 | R119: =+'[5]입력 시트(0124)'!T118 -> 0 | S119: =+'[5]입력 시트(0124)'!U118 -> 0 | T119: =+'[5]입력 시트(0124)'!V118 -> 0 | U119: =+'[5]입력 시트(0124)'!W118 -> 0 | V119: =+'[5]입력 시트(0124)'!X118 -> 0 | W119: 45931
...

Sheet Input 기초
B2: 기존 OPEX
E3: =+SUM(E4:E8) -> 24990000
B4: O&M | E4: 11995200 | F4: =+E4/$E$3 -> 0.48 | H4: CAPEX | I4: =+I5+I6 -> 800865800 | K4: 1100000000
B5: Asset Management | E5: 6997200 | F5: =+E5/$E$3 -> 0.28 | H5: BOS | I5: =+'[3]INPUTSHEET(BOLT 2)'!E165 -> 653768000 | J5: =+I5/$I$4 -> 0.81632653 | K5: =+K4-K6-K7 -> 870000000 | L5: =+K5/$K$4 -> 0.79090909
B6: MAS (accounting and other administrative not included AM) | E6: 999600 | F6: =+E6/$E$3 -> 0.04 | H6: Modules | I6: =+'[3]INPUTSHEET(BOLT 2)'!E197 -> 147097800 | J6: =+I6/$I$4 -> 0.18367347 | K6: 180000000 | L6: =+K6/$K$4 -> 0.16363636
B7: Insurance | E7: 1999200 | F7: =+E7/$E$3 -> 0.08 | H7: Grid Connection Cost | K7: 50000000 | L7: =+K7/$K$4 -> 0.045454545
B8: Contingency | E8: 2998800 | F8: =+E8/$E$3 -> 0.12
B10: 설정 | E10: 25000000
B11: O&M | E11: 12500000
B12: Asset Management | E12: 2600000
B13: MAS (accounting and other administrative not included AM)
B14: Insurance | E14: 6000000
B15: Contingency | E15: =+E10-E11-E12-E13-E14 -> 3900000
B16: Land lease | E16: 40000000
A18: BOLT 3 | C18: 지급비율 | D18: 지급일시 | F18: =+'DEVEX 지급현황'!C20 -> Jangchon 1 (APA) | G18: =+'DEVEX 지급현황'!C21 -> Soltop Masan 1 (APA) | H18: =+'DEVEX 지급현황'!C22 -> Hanil Mugok 15 (APA) | I18: =+'DEVEX 지급현황'!C23 -> Hanil Jigyeong 1 (APA) | J18: =+'DEVEX 지급현황'!C24 -> Hanil Jigyeong 2 (APA) | K18: =+'DEVEX 지급현황'!C25 -> Ho Duck4 (APA) | L18: =+'DEVEX 지급현황'!C34 -> Galsan (SPA) | M18: =+'DEVEX 지급현황'!C35 -> Mineuri (SPA) | N18: =+'DEVEX 지급현황'!C36 -> Seagol(SPA) | O18: =+'DEVEX 지급현황'!C37 -> Jaesan (SPA) | P18: =+'[3]INPUTSHEET(BOLT 3)'!O5 -> 0 | Q18: =+'[3]INPUTSHEET(BOLT 3)'!P5 -> 0
B19: 용량 | F19: =+'DEVEX 지급현황'!D20 -> 551.04 | G19: =+'DEVEX 지급현황'!D21 -> 399.04 | H19: =+'DEVEX 지급현황'!D22 -> 499.96 | I19: =+'DEVEX 지급현황'!D23 -> 499.96 | J19: =+'DEVEX 지급현황'!D24 -> 149.64 | K19: =+'DEVEX 지급현황'!D25 -> 299.28 | L19: =+'DEVEX 지급현황'!D34 -> 617.76 | M19: =+'DEVEX 지급현황'!D35 -> 564.96 | N19: =+'DEVEX 지급현황'!D36 -> 634.92 | O19: =+'DEVEX 지급현황'!D37 -> 625.68 | P19: =+'[3]INPUTSHEET(BOLT 3)'!O24 -> 0 | Q19: =+'[3]INPUTSHEET(BOLT 3)'!P24 -> 0
B21: OPEX | E21: 25000000 | F21: =+SUM(F22:F27) -> 13776000 | G21: =+SUM(G22:G27) -> 9976000 | H21: =+SUM(H22:H27) -> 12499000 | I21: =+SUM(I22:I27) -> 12499000 | J21: =+SUM(J22:J27) -> 3741000 | K21: =+SUM(K22:K27) -> 7482000 | L21: =+SUM(L22:L27) -> 15444000 | M21: =+SUM(M22:M27) -> 14124000 | ... Q21: =+SUM(Q22:Q27) -> 0
B22: O&M | E22: 12500000 | F22: =+$E22*F19/1000 -> 6888000 | G22: =+$E22*G19/1000 -> 4988000 | H22: =+$E22*H19/1000 -> 6249500 | I22: =+$E22*I19/1000 -> 6249500 | J22: =+$E22*J19/1000 -> 1870500 | K22: =+$E22*K19/1000 -> 3741000 | L22: =+$E22*L19/1000 -> 7722000 | M22: =+$E22*M19/1000 -> 7062000 | ... O22: =+$E22*O19/1000 -> 7821000 | P22: =+$E22*P19 -> 0 | Q22: =+$E22*Q19 -> 0
B23: Asset Management | F23: =+$E23*F19 -> 0 | G23: =+$E23*G19 -> 0 | H23: =+$E23*H19 -> 0 | I23: =+$E23*I19 -> 0 | J23: =+$E23*J19 -> 0 | K23: =+$E23*K19 -> 0 | L23: =+$E23*L19 -> 0 | M23: =+$E23*M19 -> 0 | ... Q23: =+$E23*Q19 -> 0
B24: MAS (accounting and other administrative not included AM) | E24: 2600000 | F24: =+$E24*F19/1000 -> 1432704 | G24: =+$E24*G19/1000 -> 1037504 | H24: =+$E24*H19/1000 -> 1299896 | I24: =+$E24*I19/1000 -> 1299896 | J24: =+$E24*J19/1000 -> 389064 | K24: =+$E24*K19/1000 -> 778128 | L24: =+$E24*L19/1000 -> 1606176 | M24: =+$E24*M19/1000 -> 1468896 | ... O24: =+$E24*O19/1000 -> 1626768 | P24: =+$E24*P19 -> 0 | Q24: =+$E24*Q19 -> 0
B25: Insurance | E25: 6000000 | F25: =+$E25*F19/1000 -> 3306240 | G25: =+$E25*G19/1000 -> 2394240 | H25: =+$E25*H19/1000 -> 2999760 | I25: =+$E25*I19/1000 -> 2999760 | J25: =+$E25*J19/1000 -> 897840 | K25: =+$E25*K19/1000 -> 1795680 | L25: =+$E25*L19/1000 -> 3706560 | M25: =+$E25*M19/1000 -> 3389760 | ... O25: =+$E25*O19/1000 -> 3754080 | P25: =+$E25*P19 -> 0 | Q25: =+$E25*Q19 -> 0
B26: Contingency | E26: 3900000 | F26: =+$E26*F19/1000 -> 2149056 | G26: =+$E26*G19/1000 -> 1556256 | H26: =+$E26*H19/1000 -> 1949844 | I26: =+$E26*I19/1000 -> 1949844 | J26: =+$E26*J19/1000 -> 583596 | K26: =+$E26*K19/1000 -> 1167192 | L26: =+$E26*L19/1000 -> 2409264 | M26: =+$E26*M19/1000 -> 2203344 | ... O26: =+$E26*O19/1000 -> 2440152 | P26: =+$E26*P19 -> 0 | Q26: =+$E26*Q19 -> 0
B27: Land lease | F27: =+$E27*F19/1000 -> 0 | G27: =+$E27*G19/1000 -> 0 | H27: =+$E27*H19/1000 -> 0 | I27: =+$E27*I19/1000 -> 0 | J27: =+$E27*J19/1000 -> 0 | K27: =+$E27*K19/1000 -> 0 | L27: =+$E27*L19/1000 -> 0 | M27: =+$E27*M19/1000 -> 0 | ... O27: =+$E27*O19/1000 -> 0 | P27: =+$E27*P19 -> 0 | Q27: =+$E27*Q19 -> 0
F28: =+F29+F34 -> 1046976000 | G28: =+G29+G34 -> 758176000 | H28: =+H29+H34 -> 949924000 | I28: =+I29+I34 -> 949924000 | J28: =+J29+J34 -> 2.84316e+08 | K28: =+K29+K34 -> 5.68632e+08 | L28: =+L29+L34 -> 996020970 | M28: =+M29+M34 -> 816618040 | ... O28: =+O29+O34 -> 1240579720
B29: CAPEX | E29: 1050000000 | F29: =+SUM(F30:F32) -> 578592000 | G29: =+SUM(G30:G32) -> 418992000 | H29: =+SUM(H30:H32) -> 524958000 | I29: =+SUM(I30:I32) -> 524958000 | J29: =+SUM(J30:J32) -> 1.57122e+08 | K29: =+SUM(K30:K32) -> 3.14244e+08 | L29: =+SUM(L30:L32) -> 648648000 | M29: =+SUM(M30:M32) -> 593208000 | ... Q29: =+SUM(Q30:Q32) -> 0
B30: =+'[3]INPUTSHEET(BOLT 3)'!B163 -> BOS | E30: 800000000 | F30: =+$E30*F$19/1000 -> 440832000 | G30: =+$E30*G$19/1000 -> 319232000 | H30: =+$E30*H$19/1000 -> 399968000 | I30: =+$E30*I$19/1000 -> 399968000 | J30: =+$E30*J$19/1000 -> 1.19712e+08 | K30: =+$E30*K$19/1000 -> 2.39424e+08 | L30: =+$E30*L$19/1000 -> 494208000 | M30: =+$E30*M$19/1000 -> 451968000 | ... O30: =+$E30*O$19/1000 -> 5.00544e+08 | P30: =+$E30*P19 -> 0 | Q30: =+$E30*Q19 -> 0
B31: =+'[3]INPUTSHEET(BOLT 3)'!B181 -> Modules | E31: 180000000 | F31: =+$E31*F$19/1000 -> 99187200 | G31: =+$E31*G$19/1000 -> 71827200 | H31: =+$E31*H$19/1000 -> 89992800 | I31: =+$E31*I$19/1000 -> 89992800 | J31: =+$E31*J$19/1000 -> 26935200 | K31: =+$E31*K$19/1000 -> 53870400 | L31: =+$E31*L$19/1000 -> 111196800 | M31: =+$E31*M$19/1000 -> 101692800 | ... O31: =+$E31*O$19/1000 -> 1.126224e+08 | P31: =+$E31*P19 -> 0 | Q31: =+$E31*Q19 -> 0
B32: =+'[3]INPUTSHEET(BOLT 3)'!B199 -> Grid Connection Cost | E32: =120000000-50000000 -> 70000000 | F32: =+$E32*F$19/1000 -> 38572800 | G32: =+$E32*G$19/1000 -> 27932800 | H32: =+$E32*H$19/1000 -> 34997200 | I32: =+$E32*I$19/1000 -> 34997200 | J32: =+$E32*J$19/1000 -> 10474800 | K32: =+$E32*K$19/1000 -> 20949600 | L32: =+$E32*L$19/1000 -> 43243200 | M32: =+$E32*M$19/1000 -> 39547200 | ... O32: =+$E32*O$19/1000 -> 43797600 | P32: =+$E32*P19 -> 0 | Q32: =+$E32*Q19 -> 0
B34: DEVEX | F34: =+F35+F38+F40 -> 468384000 | G34: =+G35+G38+G40 -> 339184000 | H34: =+H35+H38+H40 -> 424966000 | I34: =+I35+I38+I40 -> 424966000 | J34: =+J35+J38+J40 -> 1.27194e+08 | K34: =+K35+K38+K40 -> 2.54388e+08 | L34: =+L35+L38+L40 -> 347372970 | M34: =+M35+M38+M40 -> 223410040 | ... O34: =+O35+O38+O40 -> 583615720
B35: Development cost | F35: =+F19*(F36)/1000 -> 192864000 | G35: =+G19*(G36)/1000 -> 139664000 | H35: =+H19*(H36)/1000 -> 174986000 | I35: =+I19*(I36)/1000 -> 174986000 | J35: =+J19*(J36)/1000 -> 52374000 | K35: =+K19*(K36)/1000 -> 1.04748e+08 | L35: =+L36 -> 223820970 | M35: =+M36 -> 110418040 | N35: =+N36 -> 108773270 | O35: =+O36 -> 458479720 | P35: =+P19*P36 -> 0 | Q35: =+Q19*Q36 -> 0
B36: 기준 | F36: 350000000 | G36: 350000000 | H36: 350000000 | I36: 350000000 | J36: 350000000 | K36: 350000000 | L36: =+'DEVEX 지급현황'!J34 -> 223820970 | M36: =+'DEVEX 지급현황'!J35 -> 110418040 | N36: =+'DEVEX 지급현황'!J36 -> 108773270 | O36: =+'DEVEX 지급현황'!J37 -> 458479720 | P36: 500000000 | Q36: 500000000
B37: Land Purchase/MW | F37: 300000000 | G37: 300000000 | H37: 300000000 | I37: 300000000 | J37: 300000000 | K37: 300000000
B38: Land Purchase | F38: =+F37*F19/1000 -> 165312000 | G38: =+G37*G19/1000 -> 119712000 | H38: =+H37*H19/1000 -> 149988000 | I38: =+I37*I19/1000 -> 149988000 | J38: =+J37*J19/1000 -> 44892000 | K38: =+K37*K19/1000 -> 89784000
B39: Broker Fee/MW | F39: 200000000 | G39: 200000000 | H39: 200000000 | I39: 200000000 | J39: 200000000 | K39: 200000000 | L39: 200000000 | M39: 200000000 | N39: 200000000 | O39: 200000000
B40: Broker Fee | F40: =+F39*F19/1000 -> 110208000 | G40: =+G39*G19/1000 -> 79808000 | H40: =+H39*H19/1000 -> 99992000 | I40: =+I39*I19/1000 -> 99992000 | J40: =+J39*J19/1000 -> 29928000 | K40: =+K39*K19/1000 -> 59856000 | L40: =+L39*L19/1000 -> 123552000 | M40: =+M39*M19/1000 -> 112992000 | ... O40: =+O39*O19/1000 -> 1.25136e+08
B42: 기타
B43: =+'[3]INPUTSHEET(BOLT 2)'!B293 -> Other | F43: =+F19*F44 -> 0 | G43: =+G19*G44 -> 0 | H43: =+H19*H44 -> 0 | I43: =+I19*I44 -> 0 | J43: =+J19*J44 -> 0 | K43: =+K19*K44 -> 0 | L43: =+L19*L44 -> 0 | M43: =+M19*M44 -> 0 | ... Q43: =+Q19*Q44 -> 0
B44: 5년 선납비용 | P44: 40000000 | Q44: 40000000

Sheet Amount to be paid_GM_Batch1
B2: SPV Name | D2: Bolt Taeyanggwang 1HO
B3: Business License Number | D3: 388-86-03459
B4: Corporate Registry Number | D4: 110111-9077515
B5: SPV Address | D5: #214, 42, Eonju-ro 147-gil, Gangnam-gu, Seoul, Korea
B6: Project Tech. | D6: GM_Batch1,2, DG_M&A
B7: Bank & Bank account Number | D7: KB Bank : 096368-11-010020
M8: 30% of CAPEX | O8: 40% of CAPEX | T8: [Unit : KRW, EUR / 1EUR=1,470KRW]
B9: SPV | C9: Batch | D9: Name of Project | E9: CAPEX per kWp | F9: Capacity (kWp) | G9: Total amount to be settled | H9: Total | I9: Paid (By Aug. 31, 2025) | J9: Balance on Aug. 20, 2025 | K9: Amount scheduled to be paid in Aug. to Sep. (2nd Drawdown Amount) | L9: Sep. | N9: Oct. | P9: Amount scheduled to be paid in Oct. to After Oct. (3rd Drawdown Amount) | Q9: Nov. | S9: After Nov. | V9: Review
L10: Date | M10: Payment | N10: Date | O10: Payment | Q10: Date | R10: Payment
B11: Bolt Taeyanggwang 1HO | C11: GM_Batch1 | D11: =+'GM Batch1'!C11 -> YJ NANSAN 1 | E11: 1050000 | F11: =+'GM Batch1'!D11 -> 999.58 | G11: =+E11*F11*1.1/1470 -> 785384.29 | H11: =+I11+K11+P11 -> 2.8862873e+08 | K11: =+M11+O11 -> 2.3090298e+08 | L11: =+'GM Batch1'!AA11 -> 45920 | M11: =+'GM Batch1'!AD11 -> 2.3090298e+08 | N11: =+'GM Batch1'!AH11 -> 45950 | O11: =+'GM Batch1'!AK11 -> 0 | P11: =+R11+T11 -> 57725745 | T11: =+'GM Batch1'!BM11 -> 57725745 | V11: =+I11+K11+P11=E11*F11*1.1 -> FALSE
D12: =+'GM Batch1'!C17 -> YJ NANSAN 2 | E12: 1050000 | F12: =+'GM Batch1'!D17 -> 999.58 | G12: =+E12*F12*1.1/1470 -> 785384.29 | H12: =+I12+K12+P12 -> 2.8862873e+08 | K12: =+M12+O12 -> 2.3090298e+08 | L12: =+'GM Batch1'!AA17 -> 45920 | M12: =+'GM Batch1'!AD17 -> 2.3090298e+08 | N12: =+'GM Batch1'!AH17 -> 45950 | O12: =+'GM Batch1'!AK17 -> 0 | P12: =+R12+T12 -> 57725745 | T12: =+'GM Batch1'!BM17 -> 57725745 | V12: =+I12+K12+P12=E12*F12*1.1 -> FALSE
D13: =+'GM Batch1'!C23 -> YJ GASI 1 | E13: 1050000 | F13: =+'GM Batch1'!D23 -> 999.6 | G13: =+E13*F13*1.1/1470 -> 785400 | H13: =+I13+K13+P13 -> 2.886345e+08 | K13: =+M13+O13 -> 2.309076e+08 | L13: =+'GM Batch1'!AA23 -> 45920 | M13: =+'GM Batch1'!AD23 -> 2.309076e+08 | N13: =+'GM Batch1'!AH23 -> 45950 | O13: =+'GM Batch1'!AK23 -> 0 | P13: =+R13+T13 -> 57726900 | T13: =+'GM Batch1'!BM23 -> 57726900 | V13: =+I13+K13+P13=E13*F13*1.1 -> FALSE
D14: =+'GM Batch1'!C29 -> YJ GASI 2 | E14: 1050000 | F14: =+'GM Batch1'!D29 -> 999.6 | G14: =+E14*F14*1.1/1470 -> 785400 | H14: =+I14+K14+P14 -> 2.886345e+08 | K14: =+M14+O14 -> 2.309076e+08 | L14: =+'GM Batch1'!AA29 -> 45920 | M14: =+'GM Batch1'!AD29 -> 2.309076e+08 | N14: =+'GM Batch1'!AH29 -> 45950 | O14: =+'GM Batch1'!AK29 -> 0 | P14: =+R14+T14 -> 57726900 | T14: =+'GM Batch1'!BM29 -> 57726900 | V14: =+I14+K14+P14=E14*F14*1.1 -> FALSE
D15: =+'GM Batch1'!C35 -> Dream 1 | E15: 1050000 | F15: =+'GM Batch1'!D35 -> 999.24 | G15: =+E15*F15*1.1/1470 -> 785117.14 | H15: =+I15+K15+P15 -> 2.8853055e+08 | K15: =+M15+O15 -> 0 | P15: =+R15+T15 -> 2.8853055e+08 | T15: =+'GM Batch1'!AD35+'GM Batch1'!AK35+'GM Batch1'!BM35 -> 2.8853055e+08 | V15: =+I15+K15+P15=E15*F15*1.1 -> FALSE
D16: =+'GM Batch1'!C41 -> Dream 2 | E16: 1050000 | F16: =+'GM Batch1'!D41 -> 999.24 | G16: =+E16*F16*1.1/1470 -> 785117.14 | H16: =+I16+K16+P16 -> 2.8853055e+08 | K16: =+M16+O16 -> 0 | P16: =+R16+T16 -> 2.8853055e+08 | T16: =+'GM Batch1'!AD41+'GM Batch1'!AK41+'GM Batch1'!BM41 -> 2.8853055e+08 | V16: =+I16+K16+P16=E16*F16*1.1 -> FALSE
D17: =+'GM Batch1'!C47 -> JEIL TECH 1 | E17: 1050000 | F17: =+'GM Batch1'!D47 -> 999.44 | G17: =+E17*F17*1.1/1470 -> 785274.29 | H17: =+I17+K17+P17 -> 2.885883e+08 | K17: =+M17+O17 -> 0 | P17: =+R17+T17 -> 2.885883e+08 | T17: =+'GM Batch1'!AD47+'GM Batch1'!AK47+'GM Batch1'!BM47 -> 2.885883e+08 | V17: =+I17+K17+P17=E17*F17*1.1 -> FALSE
D18: =+'GM Batch1'!C53 -> JEIL TECH 2 | E18: 1050000 | F18: =+'GM Batch1'!D53 -> 999.44 | G18: =+E18*F18*1.1/1470 -> 785274.29 | H18: =+I18+K18+P18 -> 2.885883e+08 | K18: =+M18+O18 -> 0 | P18: =+R18+T18 -> 2.885883e+08 | T18: =+'GM Batch1'!AD53+'GM Batch1'!AK53+'GM Batch1'!BM53 -> 2.885883e+08 | V18: =+I18+K18+P18=E18*F18*1.1 -> FALSE
D19: Total | F19: =SUM(F11:F18) -> 7995.72 | G19: =SUM(G11:G18) -> 6282351.4 | H19: =H20/1470 -> 1570587.9 | I19: =I20/1470 -> 0 | K19: =K20/1470 -> 628313.71 | M19: =M20/1470 -> 628313.71 | O19: =O20/1470 -> 0 | P19: =P20/1470 -> 942274.14 | R19: =R20/1470 -> 0 | T19: =T20/1470 -> 942274.14
H20: =+SUM(H11:H18) -> 2.3087642e+09 | I20: =+SUM(I11:I18) -> 0 | K20: =+SUM(K11:K18) -> 9.2362116e+08 | M20: =+SUM(M11:M18) -> 9.2362116e+08 | O20: =+SUM(O11:O18) -> 0 | P20: =+SUM(P11:P18) -> 1.385143e+09 | R20: =+SUM(R11:R18) -> 0 | T20: =+SUM(T11:T18) -> 1.385143e+09
B21: Total | F21: =+F19 -> 7995.72 | G21: =+G19 -> 6282351.4 | H21: =H22/1470 -> 1570587.9 | I21: =I22/1470 -> 0 | J21: =J22/1470 -> 378254.36 | K21: =K22/1470 -> 628313.71 | M21: =M22/1470 -> 628313.71 | O21: =O22/1470 -> 0 | P21: =P22/1470 -> 942274.14 | R21: =R22/1470 -> 0 | T21: =T22/1470 -> 942274.14
H22: =+H20 -> 2.3087642e+09 | I22: =+I20 -> 0 | J22: =+'Amount to be paid in 2025(Total'!J46 -> 5.5603391e+08 | K22: =+K20 -> 9.2362116e+08 | M22: =+M20 -> 9.2362116e+08 | O22: =+O20 -> 0 | P22: =+P20 -> 1.385143e+09 | R22: =+R20 -> 0 | T22: =+T20 -> 1.385143e+09
D25: 추가 비용(감리 및 안전용역) | E25: 220000000
D27: YJ NANSAN 1 | E27: =+$E$25/8 -> 27500000
D28: YJ NANSAN 2 | E28: =+$E$25/8 -> 27500000
D29: YJ GASI 1 | E29: =+$E$25/8 -> 27500000
D30: YJ GASI 2 | E30: =+$E$25/8 -> 27500000
D31: Dream 1 | E31: =+$E$25/8 -> 27500000
D32: Dream 2 | E32: =+$E$25/8 -> 27500000
D33: JEIL TECH 1 | E33: =+$E$25/8 -> 27500000
D34: JEIL TECH 2 | E34: =+$E$25/8 -> 27500000

Sheet SPV별 CAPEX 현황
B2: SPV | C2: Project | D2: Capacity (kWp) | E2: Capacity 계약(kWp) | F2: CAPEX/MW EPC 계약 | G2: CAPEX/MW COD 적용 | H2: Total | I2: 지급완료 | J2: Drop 지급액 | K2: 계통연계비 | S2: Milestone 1(DP) | X2: Milestone 2(NTP) | AC2: Milestone 3(토목,전기) | AH2: Milestone 4(구조물 현장입고) | AM2: Milestone 5(모듈 현장입고) | AR2: Milestone 6(사용전검사) | AW2: Milestone 7(COD)
K3: 선로비 Total | L3: 기타시설부담금1 | M3: 기타시설부담금2 | N3: 기술검토비 | O3: 표준시설부담금 | P3: Payment Date | Q3: Paid Amount | R3: 미지급액 | S3: Date | T3: 0.1 | U3: Date | V3: 지급금액 | W3: 차액 | X3: Date | Y3: 0.1 | Z3: Date | AA3: 지급금액 | AB3: 차액 | AC3: Date | AD3: 0.1 | AE3: Date | AF3: 지급금액 | AG3: 차액 | AH3: Date | AI3: 0.1 | AJ3: Date | AK3: 지급금액 | AL3: 차액 | AM3: Date | AN3: 0.3 | AO3: Date | AP3: 지급금액 | AQ3: 차액 | AR3: Date | AS3: 0.25 | AT3: Date | AU3: 지급금액 | AV3: 차액 | AW3: Date | AX3: 0.05 | AY3: Date | AZ3: 지급금액 | BA3: 차액
B4: Bolt #1 | D4: =+SUM(D5:D18) -> 7995.72 | E4: =+SUM(E5:E18) -> 8000 | F4: =+F5 -> 1050000 | G4: 1050000 | H4: =+SUM(H5:H18) -> 9240000000 | I4: =+SUM(I5:I18) -> 3234000000 | J4: =+SUM(J5:J18) -> 0 | K4: =+SUM(K5:K18) -> 0 | L4: =+SUM(L5:L18) -> 0 | M4: =+SUM(M5:M18) -> 0 | N4: =+SUM(N5:N18) -> 0 | O4: =+SUM(O5:O18) -> 0 | Q4: =+SUM(Q5:Q18) -> 0 | R4: =+SUM(R5:R18) -> 0 | T4: =+SUM(T5:T18) -> 924000000 | V4: =+SUM(V5:V18) -> 462000000 | W4: =+SUM(W5:W18) -> 462000000 | Y4: =+SUM(Y5:Y18) -> 924000000 | AA4: =+SUM(AA5:AA18) -> 462000000 | AB4: =+SUM(AB5:AB18) -> 462000000 | AD4: =+SUM(AD5:AD18) -> 924000000 | AF4: =+SUM(AF5:AF18) -> 462000000 | AG4: =+SUM(AG5:AG18) -> 462000000 | AI4: =+SUM(AI5:AI18) -> 924000000 | AK4: =+SUM(AK5:AK18) -> 462000000 | AL4: =+SUM(AL5:AL18) -> 462000000 | AN4: =+SUM(AN5:AN18) -> 2772000000 | AP4: =+SUM(AP5:AP18) -> 1386000000 | AQ4: =+SUM(AQ5:AQ18) -> 1386000000 | AS4: =+SUM(AS5:AS18) -> 2310000000 | AU4: =+SUM(AU5:AU18) -> 0 | AV4: =+SUM(AV5:AV18) -> 2310000000 | AX4: =+SUM(AX5:AX18) -> 462000000 | AZ4: =+SUM(AZ5:AZ18) -> 0 | BA4: =+SUM(BA5:BA18) -> 462000000 | BC4: =+T4+Y4+AD4+AI4+AN4+AS4+AX4=E4*G4*1.1 -> TRUE
C5: =+'GM Batch1'!C11 -> YJ NANSAN 1 | D5: =+'GM Batch1'!D11 -> 999.58 | E5: 1000 | F5: 1050000 | G5: 1050000 | H5: =+F5*E5*1.1 -> 1155000000 | I5: =+V5+AA5+AF5+AK5+AP5+AU5+AZ5 -> 808500000 | J5: 0 | K5: =+SUM(L5:O5) -> 0 | R5: =+K5-Q5 -> 0 | S5: 45915 | T5: =+ROUND($H5*T$3,) -> 115500000 | U5: 45915 | V5: 115500000 | W5: =+T5-V5 -> 0 | X5: 45915 | Y5: =+ROUND($H5*Y$3,) -> 115500000 | Z5: 45915 | AA5: 115500000 | AB5: =+Y5-AA5 -> 0 | AC5: 45980 | AD5: =+ROUND($H5*AD$3,) -> 115500000 | AE5: 45980 | AF5: 115500000 | AG5: =+AD5-AF5 -> 0 | AH5: 45980 | AI5: =+ROUND($H5*AI$3,) -> 115500000 | AJ5: 45980 | AK5: 115500000 | AL5: =+AI5-AK5 -> 0 | AM5: 46003 | AN5: =+ROUND($H5*AN$3,) -> 346500000 | AO5: 46003 | AP5: 346500000 | AQ5: =+AN5-AP5 -> 0 | AS5: =+ROUND($H5*AS$3,) -> 288750000 | AV5: =+AS5-AU5 -> 288750000 | AX5: =+ROUND($H5*AX$3,) -> 57750000 | BA5: =+AX5-AZ5 -> 57750000 | BC5: =+T5+Y5+AD5+AI5+AN5+AS5+AX5=E5*G5*1.1 -> TRUE
C6: =+'GM Batch1'!C17 -> YJ NANSAN 2 | D6: =+'GM Batch1'!D17 -> 999.58 | E6: 1000 | F6: 1050000 | G6: 1050000 | H6: =+F6*E6*1.1 -> 1155000000 | I6: =+V6+AA6+AF6+AK6+AP6+AU6+AZ6 -> 808500000 | J6: 0 | K6: =+SUM(L6:O6) -> 0 | R6: =+K6-Q6 -> 0 | S6: 45915 | T6: =+ROUND($H6*T$3,) -> 115500000 | U6: 45915 | V6: 115500000 | W6: =+T6-V6 -> 0 | X6: 45915 | Y6: =+ROUND($H6*Y$3,) -> 115500000 | Z6: 45915 | AA6: 115500000 | AB6: =+Y6-AA6 -> 0 | AC6: 45980 | AD6: =+ROUND($H6*AD$3,) -> 115500000 | AE6: 45980 | AF6: 115500000 | AG6: =+AD6-AF6 -> 0 | AH6: 45980 | AI6: =+ROUND($H6*AI$3,) -> 115500000 | AJ6: 45980 | AK6: 115500000 | AL6: =+AI6-AK6 -> 0 | AM6: 46003 | AN6: =+ROUND($H6*AN$3,) -> 346500000 | AO6: 46003 | AP6: 346500000 | AQ6: =+AN6-AP6 -> 0 | AS6: =+ROUND($H6*AS$3,) -> 288750000 | AV6: =+AS6-AU6 -> 288750000 | AX6: =+ROUND($H6*AX$3,) -> 57750000 | BA6: =+AX6-AZ6 -> 57750000 | BC6: =+T6+Y6+AD6+AI6+AN6+AS6+AX6=E6*G6*1.1 -> TRUE
C7: =+'GM Batch1'!C23 -> YJ GASI 1 | D7: =+'GM Batch1'!D23 -> 999.6 | E7: 1000 | F7: 1050000 | G7: 1050000 | H7: =+F7*E7*1.1 -> 1155000000 | I7: =+V7+AA7+AF7+AK7+AP7+AU7+AZ7 -> 808500000 | J7: 0 | K7: =+SUM(L7:O7) -> 0 | R7: =+K7-Q7 -> 0 | S7: 45915 | T7: =+ROUND($H7*T$3,) -> 115500000 | U7: 45915 | V7: 115500000 | W7: =+T7-V7 -> 0 | X7: 45915 | Y7: =+ROUND($H7*Y$3,) -> 115500000 | Z7: 45915 | AA7: 115500000 | AB7: =+Y7-AA7 -> 0 | AC7: 45980 | AD7: =+ROUND($H7*AD$3,) -> 115500000 | AE7: 45980 | AF7: 115500000 | AG7: =+AD7-AF7 -> 0 | AH7: 46003 | AI7: =+ROUND($H7*AI$3,) -> 115500000 | AJ7: 46003 | AK7: 115500000 | AL7: =+AI7-AK7 -> 0 | AM7: 46014 | AN7: =+ROUND($H7*AN$3,) -> 346500000 | AO7: 46014 | AP7: 346500000 | AQ7: =+AN7-AP7 -> 0 | AS7: =+ROUND($H7*AS$3,) -> 288750000 | AV7: =+AS7-AU7 -> 288750000 | AX7: =+ROUND($H7*AX$3,) -> 57750000 | BA7: =+AX7-AZ7 -> 57750000 | BC7: =+T7+Y7+AD7+AI7+AN7+AS7+AX7=E7*G7*1.1 -> TRUE
C8: =+'GM Batch1'!C29 -> YJ GASI 2 | D8: =+'GM Batch1'!D29 -> 999.6 | E8: 1000 | F8: 1050000 | G8: 1050000 | H8: =+F8*E8*1.1 -> 1155000000 | I8: =+V8+AA8+AF8+AK8+AP8+AU8+AZ8 -> 808500000 | J8: 0 | K8: =+SUM(L8:O8) -> 0 | R8: =+K8-Q8 -> 0 | S8: 45915 | T8: =+ROUND($H8*T$3,) -> 115500000 | U8: 45915 | V8: 115500000 | W8: =+T8-V8 -> 0 | X8: 45915 | Y8: =+ROUND($H8*Y$3,) -> 115500000 | Z8: 45915 | AA8: 115500000 | AB8: =+Y8-AA8 -> 0 | AC8: 45980 | AD8: =+ROUND($H8*AD$3,) -> 115500000 | AE8: 45980 | AF8: 115500000 | AG8: =+AD8-AF8 -> 0 | AH8: 46003 | AI8: =+ROUND($H8*AI$3,) -> 115500000 | AJ8: 46003 | AK8: 115500000 | AL8: =+AI8-AK8 -> 0 | AM8: 46014 | AN8: =+ROUND($H8*AN$3,) -> 346500000 | AO8: 46014 | AP8: 346500000 | AQ8: =+AN8-AP8 -> 0 | AS8: =+ROUND($H8*AS$3,) -> 288750000 | AV8: =+AS8-AU8 -> 288750000 | AX8: =+ROUND($H8*AX$3,) -> 57750000 | BA8: =+AX8-AZ8 -> 57750000 | BC8: =+T8+Y8+AD8+AI8+AN8+AS8+AX8=E8*G8*1.1 -> TRUE
C9: =+'GM Batch1'!C35 -> Dream 1 | D9: =+'GM Batch1'!D35 -> 999.24 | E9: 1000 | F9: 1050000 | G9: 1050000 | H9: =+F9*E9*1.1 -> 1155000000 | I9: =+V9+AA9+AF9+AK9+AP9+AU9+AZ9 -> 0 | J9: 0 | K9: =+SUM(L9:O9) -> 0 | R9: =+K9-Q9 -> 0 | T9: =+ROUND($H9*T$3,) -> 115500000 | W9: =+T9-V9 -> 115500000 | Y9: =+ROUND($H9*Y$3,) -> 115500000 | AB9: =+Y9-AA9 -> 115500000 | AD9: =+ROUND($H9*AD$3,) -> 115500000 | AG9: =+AD9-AF9 -> 115500000 | AI9: =+ROUND($H9*AI$3,) -> 115500000 | AL9: =+AI9-AK9 -> 115500000 | AN9: =+ROUND($H9*AN$3,) -> 346500000 | AQ9: =+AN9-AP9 -> 346500000 | AS9: =+ROUND($H9*AS$3,) -> 288750000 | AV9: =+AS9-AU9 -> 288750000 | AX9: =+ROUND($H9*AX$3,) -> 57750000 | BA9: =+AX9-AZ9 -> 57750000 | BC9: =+T9+Y9+AD9+AI9+AN9+AS9+AX9=E9*G9*1.1 -> TRUE
C10: =+'GM Batch1'!C41 -> Dream 2 | D10: =+'GM Batch1'!D41 -> 999.24 | E10: 1000 | F10: 1050000 | G10: 1050000 | H10: =+F10*E10*1.1 -> 1155000000 | I10: =+V10+AA10+AF10+AK10+AP10+AU10+AZ10 -> 0 | J10: 0 | K10: =+SUM(L10:O10) -> 0 | R10: =+K10-Q10 -> 0 | T10: =+ROUND($H10*T$3,) -> 115500000 | W10: =+T10-V10 -> 115500000 | Y10: =+ROUND($H10*Y$3,) -> 115500000 | AB10: =+Y10-AA10 -> 115500000 | AD10: =+ROUND($H10*AD$3,) -> 115500000 | AG10: =+AD10-AF10 -> 115500000 | AI10: =+ROUND($H10*AI$3,) -> 115500000 | AL10: =+AI10-AK10 -> 115500000 | AN10: =+ROUND($H10*AN$3,) -> 346500000 | AQ10: =+AN10-AP10 -> 346500000 | AS10: =+ROUND($H10*AS$3,) -> 288750000 | AV10: =+AS10-AU10 -> 288750000 | AX10: =+ROUND($H10*AX$3,) -> 57750000 | BA10: =+AX10-AZ10 -> 57750000 | BC10: =+T10+Y10+AD10+AI10+AN10+AS10+AX10=E10*G10*1.1 -> TRUE
C11: =+'GM Batch1'!C47 -> JEIL TECH 1 | D11: =+'GM Batch1'!D47 -> 999.44 | E11: 1000 | F11: 1050000 | G11: 1050000 | H11: =+F11*E11*1.1 -> 1155000000 | I11: =+V11+AA11+AF11+AK11+AP11+AU11+AZ11 -> 0 | J11: 0 | K11: =+SUM(L11:O11) -> 0 | R11: =+K11-Q11 -> 0 | T11: =+ROUND($H11*T$3,) -> 115500000 | W11: =+T11-V11 -> 115500000 | Y11: =+ROUND($H11*Y$3,) -> 115500000 | AB11: =+Y11-AA11 -> 115500000 | AD11: =+ROUND($H11*AD$3,) -> 115500000 | AG11: =+AD11-AF11 -> 115500000 | AI11: =+ROUND($H11*AI$3,) -> 115500000 | AL11: =+AI11-AK11 -> 115500000 | AN11: =+ROUND($H11*AN$3,) -> 346500000 | AQ11: =+AN11-AP11 -> 346500000 | AS11: =+ROUND($H11*AS$3,) -> 288750000 | AV11: =+AS11-AU11 -> 288750000 | AX11: =+ROUND($H11*AX$3,) -> 57750000 | BA11: =+AX11-AZ11 -> 57750000 | BC11: =+T11+Y11+AD11+AI11+AN11+AS11+AX11=E11*G11*1.1 -> TRUE
C12: =+'GM Batch1'!C53 -> JEIL TECH 2 | D12: =+'GM Batch1'!D53 -> 999.44 | E12: 1000 | F12: 1050000 | G12: 1050000 | H12: =+F12*E12*1.1 -> 1155000000 | I12: =+V12+AA12+AF12+AK12+AP12+AU12+AZ12 -> 0 | J12: 0 | K12: =+SUM(L12:O12) -> 0 | R12: =+K12-Q12 -> 0 | T12: =+ROUND($H12*T$3,) -> 115500000 | W12: =+T12-V12 -> 115500000 | Y12: =+ROUND($H12*Y$3,) -> 115500000 | AB12: =+Y12-AA12 -> 115500000 | AD12: =+ROUND($H12*AD$3,) -> 115500000 | AG12: =+AD12-AF12 -> 115500000 | AI12: =+ROUND($H12*AI$3,) -> 115500000 | AL12: =+AI12-AK12 -> 115500000 | AN12: =+ROUND($H12*AN$3,) -> 346500000 | AQ12: =+AN12-AP12 -> 346500000 | AS12: =+ROUND($H12*AS$3,) -> 288750000 | AV12: =+AS12-AU12 -> 288750000 | AX12: =+ROUND($H12*AX$3,) -> 57750000 | BA12: =+AX12-AZ12 -> 57750000 | BC12: =+T12+Y12+AD12+AI12+AN12+AS12+AX12=E12*G12*1.1 -> TRUE
G13: 1050000 | H13: =+F13*E13*1.1 -> 0 | I13: =+V13+AA13+AF13+AK13+AP13+AU13+AZ13 -> 0 | J13: 0 | K13: =+SUM(L13:O13) -> 0 | R13: =+K13-Q13 -> 0 | T13: =+ROUND($H13*T$3,) -> 0 | W13: =+T13-V13 -> 0 | Y13: =+ROUND($H13*Y$3,) -> 0 | AB13: =+Y13-AA13 -> 0 | AD13: =+ROUND($H13*AD$3,) -> 0 | AG13: =+AD13-AF13 -> 0 | AI13: =+ROUND($H13*AI$3,) -> 0 | AL13: =+AI13-AK13 -> 0 | AN13: =+ROUND($H13*AN$3,) -> 0 | AQ13: =+AN13-AP13 -> 0 | AS13: =+ROUND($H13*AS$3,) -> 0 | AV13: =+AS13-AU13 -> 0 | AX13: =+ROUND($H13*AX$3,) -> 0 | BA13: =+AX13-AZ13 -> 0 | BC13: =+T13+Y13+AD13+AI13+AN13+AS13+AX13=E13*G13*1.1 -> TRUE
G14: 1050000 | H14: =+F14*E14*1.1 -> 0 | I14: =+V14+AA14+AF14+AK14+AP14+AU14+AZ14 -> 0 | J14: 0 | K14: =+SUM(L14:O14) -> 0 | R14: =+K14-Q14 -> 0 | T14: =+ROUND($H14*T$3,) -> 0 | W14: =+T14-V14 -> 0 | Y14: =+ROUND($H14*Y$3,) -> 0 | AB14: =+Y14-AA14 -> 0 | AD14: =+ROUND($H14*AD$3,) -> 0 | AG14: =+AD14-AF14 -> 0 | AI14: =+ROUND($H14*AI$3,) -> 0 | AL14: =+AI14-AK14 -> 0 | AN14: =+ROUND($H14*AN$3,) -> 0 | AQ14: =+AN14-AP14 -> 0 | AS14: =+ROUND($H14*AS$3,) -> 0 | AV14: =+AS14-AU14 -> 0 | AX14: =+ROUND($H14*AX$3,) -> 0 | BA14: =+AX14-AZ14 -> 0 | BC14: =+T14+Y14+AD14+AI14+AN14+AS14+AX14=E14*G14*1.1 -> TRUE
G15: 1050000 | H15: =+F15*E15*1.1 -> 0 | I15: =+V15+AA15+AF15+AK15+AP15+AU15+AZ15 -> 0 | J15: 0 | K15: =+SUM(L15:O15) -> 0 | R15: =+K15-Q15 -> 0 | T15: =+ROUND($H15*T$3,) -> 0 | W15: =+T15-V15 -> 0 | Y15: =+ROUND($H15*Y$3,) -> 0 | AB15: =+Y15-AA15 -> 0 | AD15: =+ROUND($H15*AD$3,) -> 0 | AG15: =+AD15-AF15 -> 0 | AI15: =+ROUND($H15*AI$3,) -> 0 | AL15: =+AI15-AK15 -> 0 | AN15: =+ROUND($H15*AN$3,) -> 0 | AQ15: =+AN15-AP15 -> 0 | AS15: =+ROUND($H15*AS$3,) -> 0 | AV15: =+AS15-AU15 -> 0 | AX15: =+ROUND($H15*AX$3,) -> 0 | BA15: =+AX15-AZ15 -> 0 | BC15: =+T15+Y15+AD15+AI15+AN15+AS15+AX15=E15*G15*1.1 -> TRUE
G16: 1050000 | H16: =+F16*E16*1.1 -> 0 | I16: =+V16+AA16+AF16+AK16+AP16+AU16+AZ16 -> 0 | J16: 0 | K16: =+SUM(L16:O16) -> 0 | R16: =+K16-Q16 -> 0 | T16: =+ROUND($H16*T$3,) -> 0 | W16: =+T16-V16 -> 0 | Y16: =+ROUND($H16*Y$3,) -> 0 | AB16: =+Y16-AA16 -> 0 | AD16: =+ROUND($H16*AD$3,) -> 0 | AG16: =+AD16-AF16 -> 0 | AI16: =+ROUND($H16*AI$3,) -> 0 | AL16: =+AI16-AK16 -> 0 | AN16: =+ROUND($H16*AN$3,) -> 0 | AQ16: =+AN16-AP16 -> 0 | AS16: =+ROUND($H16*AS$3,) -> 0 | AV16: =+AS16-AU16 -> 0 | AX16: =+ROUND($H16*AX$3,) -> 0 | BA16: =+AX16-AZ16 -> 0 | BC16: =+T16+Y16+AD16+AI16+AN16+AS16+AX16=E16*G16*1.1 -> TRUE
G17: 1050000 | H17: =+F17*E17*1.1 -> 0 | I17: =+V17+AA17+AF17+AK17+AP17+AU17+AZ17 -> 0 | J17: 0 | K17: =+SUM(L17:O17) -> 0 | R17: =+K17-Q17 -> 0 | T17: =+ROUND($H17*T$3,) -> 0 | W17: =+T17-V17 -> 0 | Y17: =+ROUND($H17*Y$3,) -> 0 | AB17: =+Y17-AA17 -> 0 | AD17: =+ROUND($H17*AD$3,) -> 0 | AG17: =+AD17-AF17 -> 0 | AI17: =+ROUND($H17*AI$3,) -> 0 | AL17: =+AI17-AK17 -> 0 | AN17: =+ROUND($H17*AN$3,) -> 0 | AQ17: =+AN17-AP17 -> 0 | AS17: =+ROUND($H17*AS$3,) -> 0 | AV17: =+AS17-AU17 -> 0 | AX17: =+ROUND($H17*AX$3,) -> 0 | BA17: =+AX17-AZ17 -> 0 | BC17: =+T17+Y17+AD17+AI17+AN17+AS17+AX17=E17*G17*1.1 -> TRUE
G18: 1050000 | H18: =+F18*E18*1.1 -> 0 | I18: =+V18+AA18+AF18+AK18+AP18+AU18+AZ18 -> 0 | J18: 0 | K18: =+SUM(L18:O18) -> 0 | R18: =+K18-Q18 -> 0 | T18: =+ROUND($H18*T$3,) -> 0 | W18: =+T18-V18 -> 0 | Y18: =+ROUND($H18*Y$3,) -> 0 | AB18: =+Y18-AA18 -> 0 | AD18: =+ROUND($H18*AD$3,) -> 0 | AG18: =+AD18-AF18 -> 0 | AI18: =+ROUND($H18*AI$3,) -> 0 | AL18: =+AI18-AK18 -> 0 | AN18: =+ROUND($H18*AN$3,) -> 0 | AQ18: =+AN18-AP18 -> 0 | AS18: =+ROUND($H18*AS$3,) -> 0 | AV18: =+AS18-AU18 -> 0 | AX18: =+ROUND($H18*AX$3,) -> 0 | BA18: =+AX18-AZ18 -> 0 | BC18: =+T18+Y18+AD18+AI18+AN18+AS18+AX18=E18*G18*1.1 -> TRUE
B20: SPV | C20: Project | D20: Capacity (kWp) | F20: CAPEX/MW EPC 계약 | G20: CAPEX/MW COD 적용 | H20: Total | I20: 지급완료 | J20: Drop 지급액 | K20: 계통연계비 | S20: Milestone 1 | X20: Milestone 2 | AC20: Milestone 3 | AW20: Milestone 4
K21: 선로비 Total | L21: 기타시설부담금1 | M21: 기타시설부담금2 | N21: 기술검토비 | O21: 표준시설부담금 | P21: Payment Date | Q21: Paid Amount | R21: 미지급액 | S21: Date | T21: 0.5 | U21: Date | V21: 지급금액 | W21: 차액 | X21: Date | Y21: 0.4 | Z21: Date | AA21: 지급금액 | AB21: 차액 | AC21: Date | AD21: 0.1 | AE21: Date | AF21: 지급금액 | AG21: 차액 | AW21: Date | AX21: 0 | AY21: Date | AZ21: 지급금액 | BA21: 차액
B22: Bolt #3 | D22: =+SUM(D23:D36) -> 4242.325 | F22: 950000 | G22: 1050000 | H22: =+SUM(H23:H36) -> 4433229625 | I22: =+SUM(I23:I36) -> 0 | J22: =+SUM(J23:J36) -> 0 | K22: =+SUM(K23:K36) -> 237373380 | L22: =+SUM(L23:L36) -> 9083110 | M22: =+SUM(M23:M36) -> 14876680 | N22: =+SUM(N23:N36) -> 3300000 | O22: =+SUM(O23:O36) -> 210113590 | Q22: =+SUM(Q23:Q36) -> 124280560 | R22: =+SUM(R23:R36) -> 113092820 | T22: =+SUM(T23:T36) -> 2216614814 | V22: =+SUM(V23:V36) -> 0 | W22: =+SUM(W23:W36) -> 2216614814 | Y22: =+SUM(Y23:Y36) -> 1773291850 | AB22: =+SUM(AB23:AB36) -> 1773291850 | AD22: =+SUM(AD23:AD36) -> 672605331 | AG22: =+SUM(AG23:AG36) -> 672605331 | AX22: =+SUM(AX23:AX36) -> 0 | BA22: =+SUM(BA23:BA36) -> 0 | BC22: =T22+Y22+AD22+AX22+K22=D22*G22*1.1 -> TRUE
C23: Seun Steel Gyeongju | D23: 709.295 | F23: 950000 | G23: 1050000 | H23: =+F23*D23*1.1 -> 7.4121328e+08 | I23: =+V23+AA23+AF23+AZ23 -> 0 | K23: =+SUM(L23:O23) -> 0 | R23: =+K23-Q23 -> 0 | T23: =+ROUND($H23*T$21,) -> 370606638 | W23: =+T23-V23 -> 370606638 | Y23: =+ROUND($H23*Y$21,) -> 296485310 | AB23: =+Y23-AA23 -> 296485310 | AD23: =+ROUND(D23*G23*1.1-Y23-T23-K23,) -> 152143777 | AG23: =+AD23-AF23 -> 152143777 | AX23: =+ROUND($H23*AX$21,) -> 0 | BA23: =+AX23-AZ23 -> 0 | BC23: =T23+Y23+AD23+AX23+K23=D23*G23*1.1 -> TRUE
C24: Oneel | D24: 522.605 | F24: 950000 | G24: 1050000 | H24: =+F24*D24*1.1 -> 546122225 | I24: =+V24+AA24+AF24+AZ24 -> 0 | K24: =+SUM(L24:O24) -> 1100000 | N24: 1100000 | P24: 45966 | Q24: 1100000 | R24: =+K24-Q24 -> 0 | T24: =+ROUND($H24*T$21,) -> 273061113 | W24: =+T24-V24 -> 273061113 | Y24: =+ROUND($H24*Y$21,) -> 218448890 | AB24: =+Y24-AA24 -> 218448890 | AC24: =+'[6]BT 3HO'!AB17 -> 45930 | AD24: =+ROUND(D24*G24*1.1-Y24-T24-K24,) -> 110998772 | AG24: =+AD24-AF24 -> 110998772 | AX24: =+ROUND($H24*AX$21,) -> 0 | BA24: =+AX24-AZ24 -> 0 | BC24: =T24+Y24+AD24+AX24+K24=D24*G24*1.1 -> TRUE
C25: LSG | D25: 499.11 | F25: 950000 | G25: 1050000 | H25: =+F25*D25*1.1 -> 5.2156995e+08 | I25: =+V25+AA25+AF25+AZ25 -> 0 | K25: =+SUM(L25:O25) -> 67427460 | L25: 1808870 | M25: 3029700 | O25: 62588890 | P25: 45980 | Q25: 67427460 | R25: =+K25-Q25 -> 0 | T25: =+ROUND($H25*T$21,) -> 260784975 | W25: =+T25-V25 -> 260784975 | Y25: =+ROUND($H25*Y$21,) -> 208627980 | AB25: =+Y25-AA25 -> 208627980 | AC25: =+'[6]BT 3HO'!AB22 -> 45831 | AD25: =+ROUND(D25*G25*1.1-Y25-T25-K25,) -> 39631635 | AG25: =+AD25-AF25 -> 39631635 | AX25: =+ROUND($H25*AX$21,) -> 0 | BA25: =+AX25-AZ25 -> 0 | BC25: =T25+Y25+AD25+AX25+K25=D25*G25*1.1 -> TRUE
C26: Hanseo Motors | D26: 142.875 | F26: 950000 | G26: 1050000 | H26: =+F26*D26*1.1 -> 149304375 | I26: =+V26+AA26+AF26+AZ26 -> 0 | K26: =+SUM(L26:O26) -> 23162170 | L26: 1808870 | M26: 3029700 | O26: 18323600 | P26: 45976 | Q26: 23162170 | R26: =+K26-Q26 -> 0 | T26: =+ROUND($H26*T$21,) -> 74652188 | W26: =+T26-V26 -> 74652188 | Y26: =+ROUND($H26*Y$21,) -> 59721750 | AB26: =+Y26-AA26 -> 59721750 | AC26: =+'[6]BT 3HO'!AB27 -> 45831 | AD26: =+ROUND(D26*G26*1.1-Y26-T26-K26,) -> 7484517 | AG26: =+AD26-AF26 -> 7484517 | AX26: =+ROUND($H26*AX$21,) -> 0 | BA26: =+AX26-AZ26 -> 0 | BC26: =T26+Y26+AD26+AX26+K26=D26*G26*1.1 -> TRUE
C27: Daechon Headquarters | D27: 897.89 | F27: 950000 | G27: 1050000 | H27: =+F27*D27*1.1 -> 9.3829505e+08 | I27: =+V27+AA27+AF27+AZ27 -> 0 | K27: =+SUM(L27:O27) -> 31490930 | L27: 2433490 | M27: 4408640 | N27: 1100000 | O27: 23548800 | P27: 45980 | Q27: 31490930 | R27: =+K27-Q27 -> 0 | T27: =+ROUND($H27*T$21,) -> 469147525 | W27: =+T27-V27 -> 469147525 | Y27: =+ROUND($H27*Y$21,) -> 375318020 | AB27: =+Y27-AA27 -> 375318020 | AC27: =+'[6]BT 3HO'!AB32 -> 45930 | AD27: =+ROUND(D27*G27*1.1-Y27-T27-K27,) -> 161106475 | AG27: =+AD27-AF27 -> 161106475 | AX27: =+ROUND($H27*AX$21,) -> 0 | BA27: =+AX27-AZ27 -> 0 | BC27: =T27+Y27+AD27+AX27+K27=D27*G27*1.1 -> TRUE
C28: Changseong High Tech | D28: 166.37 | F28: 950000 | G28: 1050000 | H28: =+F28*D28*1.1 -> 173856650 | I28: =+V28+AA28+AF28+AZ28 -> 0 | K28: =+SUM(L28:O28) -> 0 | R28: =+K28-Q28 -> 0 | T28: =+ROUND($H28*T$21,) -> 86928325 | W28: =+T28-V28 -> 86928325 | Y28: =+ROUND($H28*Y$21,) -> 69542660 | AB28: =+Y28-AA28 -> 69542660 | AC28: =+'[6]BT 3HO'!AB37 -> 45930 | AD28: =+ROUND(D28*G28*1.1-Y28-T28-K28,) -> 35686365 | AG28: =+AD28-AF28 -> 35686365 | AX28: =+ROUND($H28*AX$21,) -> 0 | BA28: =+AX28-AZ28 -> 0 | BC28: =T28+Y28+AD28+AX28+K28=D28*G28*1.1 -> TRUE
C29: Daechon Busan | D29: 1155.7 | F29: 950000 | G29: 1050000 | H29: =+F29*D29*1.1 -> 1207706500 | I29: =+V29+AA29+AF29+AZ29 -> 0 | K29: =+SUM(L29:O29) -> 114192820 | L29: 3031880 | M29: 4408640 | N29: 1100000 | O29: 105652300 | Q29: 1100000 | R29: =+K29-Q29 -> 113092820 | T29: =+ROUND($H29*T$21,) -> 603853250 | W29: =+T29-V29 -> 603853250 | Y29: =+ROUND($H29*Y$21,) -> 483082600 | AB29: =+Y29-AA29 -> 483082600 | AC29: =+'[6]BT 3HO'!AB42 -> 45930 | AD29: =+ROUND(D29*G29*1.1-Y29-T29-K29,) -> 133704830 | AG29: =+AD29-AF29 -> 133704830 | AX29: =+ROUND($H29*AX$21,) -> 0 | BA29: =+AX29-AZ29 -> 0 | BC29: =T29+Y29+AD29+AX29+K29=D29*G29*1.1 -> TRUE
C30: E-Tech | D30: 148.48 | F30: 950000 | G30: 1050000 | H30: =+F30*D30*1.1 -> 155161600 | I30: =+V30+AA30+AF30+AZ30 -> 0 | K30: =+SUM(L30:O30) -> 0 | R30: =+K30-Q30 -> 0 | T30: =+ROUND($H30*T$21,) -> 77580800 | W30: =+T30-V30 -> 77580800 | Y30: =+ROUND($H30*Y$21,) -> 62064640 | AB30: =+Y30-AA30 -> 62064640 | AD30: =+ROUND(D30*G30*1.1-Y30-T30-K30,) -> 31848960 | AG30: =+AD30-AF30 -> 31848960 | AX30: =+ROUND($H30*AX$21,) -> 0 | BA30: =+AX30-AZ30 -> 0 | BC30: =T30+Y30+AD30+AX30+K30=D30*G30*1.1 -> TRUE
C31: 0 | D31: =+'[6]BT 2HO'!D69 -> 0 | F31: 950000 | G31: 1050000 | H31: =+F31*D31*1.1 -> 0 | K31: =+SUM(L31:O31) -> 0 | R31: =+K31-Q31 -> 0 | T31: =+ROUND($H31*T$21,) -> 0 | W31: =+T31-V31 -> 0 | Y31: =+ROUND($H31*Y$21,) -> 0 | AB31: =+Y31-AA31 -> 0 | AD31: =+ROUND(D31*G31*1.1-Y31-T31-K31,) -> 0 | AG31: =+AD31-AF31 -> 0 | AX31: =+ROUND($H31*AX$21,) -> 0 | BA31: =+AX31-AZ31 -> 0 | BC31: =T31+Y31+AD31+AX31+K31=D31*G31*1.1 -> TRUE
C32: 0 | D32: =+'[6]BT 2HO'!D74 -> 0 | F32: 950000 | G32: 1050000 | H32: =+F32*D32*1.1 -> 0 | K32: =+SUM(L32:O32) -> 0 | R32: =+K32-Q32 -> 0 | T32: =+ROUND($H32*T$21,) -> 0 | W32: =+T32-V32 -> 0 | Y32: =+ROUND($H32*Y$21,) -> 0 | AB32: =+Y32-AA32 -> 0 | AD32: =+ROUND(D32*G32*1.1-Y32-T32-K32,) -> 0 | AG32: =+AD32-AF32 -> 0 | AX32: =+ROUND($H32*AX$21,) -> 0 | BA32: =+AX32-AZ32 -> 0 | BC32: =T32+Y32+AD32+AX32+K32=D32*G32*1.1 -> TRUE
C33: 0 | D33: =+'[6]BT 2HO'!D79 -> 0 | F33: 950000 | G33: 1050000 | H33: =+F33*D33*1.1 -> 0 | K33: =+SUM(L33:O33) -> 0 | R33: =+K33-Q33 -> 0 | T33: =+ROUND($H33*T$21,) -> 0 | W33: =+T33-V33 -> 0 | Y33: =+ROUND($H33*Y$21,) -> 0 | AB33: =+Y33-AA33 -> 0 | AD33: =+ROUND(D33*G33*1.1-Y33-T33-K33,) -> 0 | AG33: =+AD33-AF33 -> 0 | AX33: =+ROUND($H33*AX$21,) -> 0 | BA33: =+AX33-AZ33 -> 0 | BC33: =T33+Y33+AD33+AX33+K33=D33*G33*1.1 -> TRUE
C34: 0 | D34: =+'[6]BT 2HO'!D84 -> 0 | F34: 950000 | G34: 1050000 | H34: =+F34*D34*1.1 -> 0 | K34: =+SUM(L34:O34) -> 0 | R34: =+K34-Q34 -> 0 | T34: =+ROUND($H34*T$21,) -> 0 | W34: =+T34-V34 -> 0 | Y34: =+ROUND($H34*Y$21,) -> 0 | AB34: =+Y34-AA34 -> 0 | AD34: =+ROUND(D34*G34*1.1-Y34-T34-K34,) -> 0 | AG34: =+AD34-AF34 -> 0 | AX34: =+ROUND($H34*AX$21,) -> 0 | BA34: =+AX34-AZ34 -> 0 | BC34: =T34+Y34+AD34+AX34+K34=D34*G34*1.1 -> TRUE
C35: 0 | D35: =+'[6]BT 2HO'!D89 -> 0 | F35: 950000 | G35: 1050000 | H35: =+F35*D35*1.1 -> 0 | K35: =+SUM(L35:O35) -> 0 | R35: =+K35-Q35 -> 0 | T35: =+ROUND($H35*T$21,) -> 0 | W35: =+T35-V35 -> 0 | Y35: =+ROUND($H35*Y$21,) -> 0 | AB35: =+Y35-AA35 -> 0 | AD35: =+ROUND(D35*G35*1.1-Y35-T35-K35,) -> 0 | AG35: =+AD35-AF35 -> 0 | AX35: =+ROUND($H35*AX$21,) -> 0 | BA35: =+AX35-AZ35 -> 0 | BC35: =T35+Y35+AD35+AX35+K35=D35*G35*1.1 -> TRUE
C36: 0 | D36: =+'[6]BT 2HO'!D94 -> 0 | F36: 950000 | G36: 1050000 | H36: =+F36*D36*1.1 -> 0 | K36: =+SUM(L36:O36) -> 0 | R36: =+K36-Q36 -> 0 | T36: =+ROUND($H36*T$21,) -> 0 | W36: =+T36-V36 -> 0 | Y36: =+ROUND($H36*Y$21,) -> 0 | AB36: =+Y36-AA36 -> 0 | AD36: =+ROUND(D36*G36*1.1-Y36-T36-K36,) -> 0 | AG36: =+AD36-AF36 -> 0 | AX36: =+ROUND($H36*AX$21,) -> 0 | BA36: =+AX36-AZ36 -> 0 | BC36: =T36+Y36+AD36+AX36+K36=D36*G36*1.1 -> TRUE
B38: SPV | C38: Project | D38: Capacity (kWp) | F38: CAPEX/MW EPC 계약 | G38: CAPEX/MW COD 적용 | H38: Total | I38: 지급완료 | J38: Drop 지급액 | K38: 계통연계비 | S38: Milestone 1 | X38: Milestone 2 | AC38: Milestone 3 | AW38: Milestone 4
K39: 선로비 Total | L39: 기타시설부담금1 | M39: 기타시설부담금2 | N39: 기술검토비 | O39: 표준시설부담금 | P39: Payment Date | Q39: Paid Amount | R39: 미지급액 | S39: Date | T39: 0.5 | U39: Date | V39: 지급금액 | W39: 차액 | X39: Date | Y39: 0.4 | Z39: Date | AA39: 지급금액 | AB39: 차액 | AC39: Date | AD39: 0.1 | AE39: Date | AF39: 지급금액 | AG39: 차액 | AW39: Date | AX39: 0 | AY39: Date | AZ39: 지급금액 | BA39: 차액
B40: Bolt #4 | D40: =+SUM(D41:D54) -> 3853 | F40: 950000 | G40: 1050000 | H40: =+SUM(H41:H54) -> 4026385000 | I40: =+SUM(I41:I54) -> 51975000 | J40: =+SUM(J41:J54) -> 0 | K40: =+SUM(K41:K54) -> 0 | L40: =+SUM(L41:L54) -> 0 | M40: =+SUM(M41:M54) -> 0 | N40: =+SUM(N41:N54) -> 0 | O40: =+SUM(O41:O54) -> 0 | Q40: =+SUM(Q41:Q54) -> 0 | R40: =+SUM(R41:R54) -> 0 | T40: =+SUM(T41:T54) -> 2013192500 | V40: =+SUM(V41:V54) -> 51975000 | W40: =+SUM(W41:W54) -> 1961217500 | Y40: =+SUM(Y41:Y54) -> 1610554000 | AB40: =+SUM(AB41:AB54) -> 1610554000 | AD40: =+SUM(AD41:AD54) -> 826468500 | AG40: =+SUM(AG41:AG54) -> 826468500 | AX40: =+SUM(AX41:AX54) -> 0 | BA40: =+SUM(BA41:BA54) -> 0 | BC40: =T40+Y40+AD40+AX40+K40=D40*G40*1.1 -> TRUE
C41: RMK | D41: 991 | F41: 950000 | G41: 1050000 | H41: =+F41*D41*1.1 -> 1.035595e+09 | I41: =+V41+AA41+AF41+AZ41 -> 0 | K41: =+SUM(L41:O41) -> 0 | R41: =+K41-Q41 -> 0 | T41: =+ROUND($H41*T$39,) -> 517797500 | W41: =+T41-V41 -> 517797500 | Y41: =+ROUND($H41*Y$39,) -> 414238000 | AB41: =+Y41-AA41 -> 414238000 | AD41: =+ROUND(D41*G41*1.1-Y41-T41-K41,) -> 212569500 | AG41: =+AD41-AF41 -> 212569500 | AX41: =+ROUND($H41*AX$39,) -> 0 | BA41: =+AX41-AZ41 -> 0 | BC41: =T41+Y41+AD41+AX41+K41=D41*G41*1.1 -> TRUE
C42: Daesung Fruit Industry | D42: 315 | F42: 950000 | G42: 1050000 | H42: =+F42*D42*1.1 -> 329175000 | I42: =+V42+AA42+AF42+AZ42 -> 51975000 | K42: =+SUM(L42:O42) -> 0 | R42: =+K42-Q42 -> 0 | S42: =+'[6]BT 2HO'!O82 -> 45922 | T42: =+ROUND($H42*T$39,) -> 164587500 | U42: =+'[6]BT 2HO'!O82 -> 45922 | V42: =+'[6]BT 2HO'!R82+'[6]BT 2HO'!R83 -> 51975000 | W42: =+T42-V42 -> 112612500 | Y42: =+ROUND($H42*Y$39,) -> 131670000 | AB42: =+Y42-AA42 -> 131670000 | AD42: =+ROUND(D42*G42*1.1-Y42-T42-K42,) -> 67567500 | AG42: =+AD42-AF42 -> 67567500 | AX42: =+ROUND($H42*AX$39,) -> 0 | BA42: =+AX42-AZ42 -> 0 | BC42: =T42+Y42+AD42+AX42+K42=D42*G42*1.1 -> TRUE
C43: Ilsan Metal | D43: 156 | F43: 950000 | G43: 1050000 | H43: =+F43*D43*1.1 -> 163020000 | I43: =+V43+AA43+AF43+AZ43 -> 0 | K43: =+SUM(L43:O43) -> 0 | R43: =+K43-Q43 -> 0 | T43: =+ROUND($H43*T$39,) -> 81510000 | W43: =+T43-V43 -> 81510000 | Y43: =+ROUND($H43*Y$39,) -> 65208000 | AB43: =+Y43-AA43 -> 65208000 | AD43: =+ROUND(D43*G43*1.1-Y43-T43-K43,) -> 33462000 | AG43: =+AD43-AF43 -> 33462000 | AX43: =+ROUND($H43*AX$39,) -> 0 | BA43: =+AX43-AZ43 -> 0 | BC43: =T43+Y43+AD43+AX43+K43=D43*G43*1.1 -> TRUE
C44: Ilshin Industry(HQ) | D44: 1000 | F44: 950000 | G44: 1050000 | H44: =+F44*D44*1.1 -> 1.045e+09 | I44: =+V44+AA44+AF44+AZ44 -> 0 | K44: =+SUM(L44:O44) -> 0 | R44: =+K44-Q44 -> 0 | T44: =+ROUND($H44*T$39,) -> 522500000 | W44: =+T44-V44 -> 522500000 | Y44: =+ROUND($H44*Y$39,) -> 418000000 | AB44: =+Y44-AA44 -> 418000000 | AD44: =+ROUND(D44*G44*1.1-Y44-T44-K44,) -> 214500000 | AG44: =+AD44-AF44 -> 214500000 | AX44: =+ROUND($H44*AX$39,) -> 0 | BA44: =+AX44-AZ44 -> 0 | BC44: =T44+Y44+AD44+AX44+K44=D44*G44*1.1 -> TRUE
C45: Ilshin Industry(Branch)(Drop) | D45: 200 | F45: 950000 | G45: 1050000 | H45: =+F45*D45*1.1 -> 2.09e+08 | I45: =+V45+AA45+AF45+AZ45 -> 0 | K45: =+SUM(L45:O45) -> 0 | R45: =+K45-Q45 -> 0 | T45: =+ROUND($H45*T$39,) -> 104500000 | W45: =+T45-V45 -> 104500000 | Y45: =+ROUND($H45*Y$39,) -> 83600000 | AB45: =+Y45-AA45 -> 83600000 | AD45: =+ROUND(D45*G45*1.1-Y45-T45-K45,) -> 42900000 | AG45: =+AD45-AF45 -> 42900000 | AX45: =+ROUND($H45*AX$39,) -> 0 | BA45: =+AX45-AZ45 -> 0 | BC45: =T45+Y45+AD45+AX45+K45=D45*G45*1.1 -> TRUE
C46: LC-Tech | D46: 173 | F46: 950000 | G46: 1050000 | H46: =+F46*D46*1.1 -> 180785000 | I46: =+V46+AA46+AF46+AZ46 -> 0 | K46: =+SUM(L46:O46) -> 0 | R46: =+K46-Q46 -> 0 | T46: =+ROUND($H46*T$39,) -> 90392500 | W46: =+T46-V46 -> 90392500 | Y46: =+ROUND($H46*Y$39,) -> 72314000 | AB46: =+Y46-AA46 -> 72314000 | AD46: =+ROUND(D46*G46*1.1-Y46-T46-K46,) -> 37108500 | AG46: =+AD46-AF46 -> 37108500 | AX46: =+ROUND($H46*AX$39,) -> 0 | BA46: =+AX46-AZ46 -> 0 | BC46: =T46+Y46+AD46+AX46+K46=D46*G46*1.1 -> TRUE
C47: Taeseong Mold Industry 1(Drop) | D47: =0.371*1000 -> 371 | F47: 950000 | G47: 1050000 | H47: =+F47*D47*1.1 -> 3.87695e+08 | I47: =+V47+AA47+AF47+AZ47 -> 0 | K47: =+SUM(L47:O47) -> 0 | R47: =+K47-Q47 -> 0 | T47: =+ROUND($H47*T$39,) -> 193847500 | W47: =+T47-V47 -> 193847500 | Y47: =+ROUND($H47*Y$39,) -> 155078000 | AB47: =+Y47-AA47 -> 155078000 | AD47: =+ROUND(D47*G47*1.1-Y47-T47-K47,) -> 79579500 | AG47: =+AD47-AF47 -> 79579500 | AX47: =+ROUND($H47*AX$39,) -> 0 | BA47: =+AX47-AZ47 -> 0 | BC47: =T47+Y47+AD47+AX47+K47=D47*G47*1.1 -> TRUE
C48: Taeseong Mold Industry 2(Drop) | D48: =0.187*1000 -> 187 | F48: 950000 | G48: 1050000 | H48: =+F48*D48*1.1 -> 1.95415e+08 | I48: =+V48+AA48+AF48+AZ48 -> 0 | K48: =+SUM(L48:O48) -> 0 | R48: =+K48-Q48 -> 0 | T48: =+ROUND($H48*T$39,) -> 97707500 | W48: =+T48-V48 -> 97707500 | Y48: =+ROUND($H48*Y$39,) -> 78166000 | AB48: =+Y48-AA48 -> 78166000 | AD48: =+ROUND(D48*G48*1.1-Y48-T48-K48,) -> 40111500 | AG48: =+AD48-AF48 -> 40111500 | AX48: =+ROUND($H48*AX$39,) -> 0 | BA48: =+AX48-AZ48 -> 0 | BC48: =T48+Y48+AD48+AX48+K48=D48*G48*1.1 -> TRUE
C49: Lijin Factory 1 | D49: 227 | F49: 950000 | G49: 1050000 | H49: =+F49*D49*1.1 -> 2.37215e+08 | K49: =+SUM(L49:O49) -> 0 | R49: =+K49-Q49 -> 0 | T49: =+ROUND($H49*T$39,) -> 118607500 | W49: =+T49-V49 -> 118607500 | Y49: =+ROUND($H49*Y$39,) -> 94886000 | AB49: =+Y49-AA49 -> 94886000 | AD49: =+ROUND(D49*G49*1.1-Y49-T49-K49,) -> 48691500 | AG49: =+AD49-AF49 -> 48691500 | AX49: =+ROUND($H49*AX$39,) -> 0 | BA49: =+AX49-AZ49 -> 0 | BC49: =T49+Y49+AD49+AX49+K49=D49*G49*1.1 -> TRUE
C50: Lijin Factory 2 | D50: 233 | F50: 950000 | G50: 1050000 | H50: =+F50*D50*1.1 -> 2.43485e+08 | K50: =+SUM(L50:O50) -> 0 | R50: =+K50-Q50 -> 0 | T50: =+ROUND($H50*T$39,) -> 121742500 | W50: =+T50-V50 -> 121742500 | Y50: =+ROUND($H50*Y$39,) -> 97394000 | AB50: =+Y50-AA50 -> 97394000 | AD50: =+ROUND(D50*G50*1.1-Y50-T50-K50,) -> 49978500 | AG50: =+AD50-AF50 -> 49978500 | AX50: =+ROUND($H50*AX$39,) -> 0 | BA50: =+AX50-AZ50 -> 0 | BC50: =T50+Y50+AD50+AX50+K50=D50*G50*1.1 -> TRUE
C51: =+'[6]BT 2HO'!C97 -> 0 | D51: =+'[6]BT 2HO'!D97 -> 0 | F51: 950000 | G51: 1050000 | H51: =+F51*D51*1.1 -> 0 | K51: =+SUM(L51:O51) -> 0 | R51: =+K51-Q51 -> 0 | T51: =+ROUND($H51*T$39,) -> 0 | W51: =+T51-V51 -> 0 | Y51: =+ROUND($H51*Y$39,) -> 0 | AB51: =+Y51-AA51 -> 0 | AD51: =+ROUND(D51*G51*1.1-Y51-T51-K51,) -> 0 | AG51: =+AD51-AF51 -> 0 | AX51: =+ROUND($H51*AX$39,) -> 0 | BA51: =+AX51-AZ51 -> 0 | BC51: =T51+Y51+AD51+AX51+K51=D51*G51*1.1 -> TRUE
C52: =+'[6]BT 2HO'!C102 -> 0 | D52: =+'[6]BT 2HO'!D102 -> 0 | F52: 950000 | G52: 1050000 | H52: =+F52*D52*1.1 -> 0 | K52: =+SUM(L52:O52) -> 0 | R52: =+K52-Q52 -> 0 | T52: =+ROUND($H52*T$39,) -> 0 | W52: =+T52-V52 -> 0 | Y52: =+ROUND($H52*Y$39,) -> 0 | AB52: =+Y52-AA52 -> 0 | AD52: =+ROUND(D52*G52*1.1-Y52-T52-K52,) -> 0 | AG52: =+AD52-AF52 -> 0 | AX52: =+ROUND($H52*AX$39,) -> 0 | BA52: =+AX52-AZ52 -> 0 | BC52: =T52+Y52+AD52+AX52+K52=D52*G52*1.1 -> TRUE
C53: =+'[6]BT 2HO'!C107 -> 0 | D53: =+'[6]BT 2HO'!D107 -> 0 | F53: 950000 | G53: 1050000 | H53: =+F53*D53*1.1 -> 0 | K53: =+SUM(L53:O53) -> 0 | R53: =+K53-Q53 -> 0 | T53: =+ROUND($H53*T$39,) -> 0 | W53: =+T53-V53 -> 0 | Y53: =+ROUND($H53*Y$39,) -> 0 | AB53: =+Y53-AA53 -> 0 | AD53: =+ROUND(D53*G53*1.1-Y53-T53-K53,) -> 0 | AG53: =+AD53-AF53 -> 0 | AX53: =+ROUND($H53*AX$39,) -> 0 | BA53: =+AX53-AZ53 -> 0 | BC53: =T53+Y53+AD53+AX53+K53=D53*G53*1.1 -> TRUE
C54: =+'[6]BT 2HO'!C112 -> 0 | D54: =+'[6]BT 2HO'!D112 -> 0 | F54: 950000 | G54: 1050000 | H54: =+F54*D54*1.1 -> 0 | K54: =+SUM(L54:O54) -> 0 | R54: =+K54-Q54 -> 0 | T54: =+ROUND($H54*T$39,) -> 0 | W54: =+T54-V54 -> 0 | Y54: =+ROUND($H54*Y$39,) -> 0 | AB54: =+Y54-AA54 -> 0 | AD54: =+ROUND(D54*G54*1.1-Y54-T54-K54,) -> 0 | AG54: =+AD54-AF54 -> 0 | AX54: =+ROUND($H54*AX$39,) -> 0 | BA54: =+AX54-AZ54 -> 0 | BC54: =T54+Y54+AD54+AX54+K54=D54*G54*1.1 -> TRUE
B56: SPV | C56: Project | D56: Capacity (kWp) | F56: CAPEX/MW EPC 계약 | G56: CAPEX/MW COD 적용 | H56: Total | I56: 지급완료 | J56: Drop 지급액 | K56: 계통연계비 | S56: Milestone 1 | X56: Milestone 2 | AC56: Milestone 3 | AW56: Milestone 4
K57: 선로비 Total | L57: 기타시설부담금1 | M57: 기타시설부담금2 | N57: 기술검토비 | O57: 표준시설부담금 | P57: Payment Date | Q57: Paid Amount | R57: 미지급액 | S57: Date | T57: 0.5 | U57: Date | V57: 지급금액 | W57: 차액 | X57: Date | Y57: 0.4 | Z57: Date | AA57: 지급금액 | AB57: 차액 | AC57: Date | AD57: 0.1 | AE57: Date | AF57: 지급금액 | AG57: 차액 | AW57: Date | AX57: 0 | AY57: Date | AZ57: 지급금액 | BA57: 차액
B58: Bolt #6 | D58: =+SUM(D59:D72) -> 2877.38 | F58: 950000 | G58: 1050000 | H58: =+SUM(H59:H72) -> 3006862100 | I58: =+SUM(I59:I72) -> 47583800 | J58: =+SUM(J59:J72) -> 31083800 | K58: =+SUM(K59:K72) -> 0 | L58: =+SUM(L59:L72) -> 0 | M58: =+SUM(M59:M72) -> 0 | N58: =+SUM(N59:N72) -> 0 | O58: =+SUM(O59:O72) -> 0 | Q58: =+SUM(Q59:Q72) -> 0 | R58: =+SUM(R59:R72) -> 0 | T58: =+SUM(T59:T72) -> 1503431050 | V58: =+SUM(V59:V72) -> 47583800 | W58: =+SUM(W59:W72) -> 1455847250 | Y58: =+SUM(Y59:Y72) -> 1202744840 | AB58: =+SUM(AB59:AB72) -> 1202744840 | AD58: =+SUM(AD59:AD72) -> 617198010 | AG58: =+SUM(AG59:AG72) -> 617198010 | AX58: =+SUM(AX59:AX72) -> 0 | BA58: =+SUM(BA59:BA72) -> 0 | BC58: =T58+Y58+AD58+AX58+K58=D58*G58*1.1 -> TRUE
C59: Esun | D59: =+'[6]BT 6HO'!D11 -> 150 | F59: 950000 | G59: 1050000 | H59: =+F59*D59*1.1 -> 156750000 | I59: =+V59+AA59+AF59+AZ59 -> 16500000 | K59: =+SUM(L59:O59) -> 0 | R59: =+K59-Q59 -> 0 | S59: =+'[6]BT 6HO'!N12 -> 45631 | T59: =+ROUND($H59*T$57,) -> 78375000 | U59: =+'[6]BT 6HO'!O12 -> 45631 | V59: =+'[6]BT 6HO'!R12+'[6]BT 6HO'!R13 -> 16500000 | W59: =+T59-V59 -> 61875000 | Y59: =+ROUND($H59*Y$57,) -> 62700000 | AB59: =+Y59-AA59 -> 62700000 | AD59: =+ROUND(D59*G59*1.1-Y59-T59-K59,) -> 32175000 | AG59: =+AD59-AF59 -> 32175000 | AX59: =+ROUND($H59*AX$57,) -> 0 | BA59: =+AX59-AZ59 -> 0 | BC59: =T59+Y59+AD59+AX59+K59=D59*G59*1.1 -> TRUE
C60: Sejin SMC(Drop) | D60: =+'[6]BT 6HO'!D16 -> 144.15 | F60: 950000 | G60: 1050000 | H60: =+F60*D60*1.1 -> 150636750 | I60: =+V60+AA60+AF60+AZ60 -> 15856500 | J60: =+I60 -> 15856500 | K60: =+SUM(L60:O60) -> 0 | R60: =+K60-Q60 -> 0 | S60: =+'[6]BT 6HO'!N17 -> 45631 | T60: =+ROUND($H60*T$57,) -> 75318375 | U60: =+'[6]BT 6HO'!O17 -> 45631 | V60: =+'[6]BT 6HO'!R17+'[6]BT 6HO'!R18 -> 15856500 | W60: =+T60-V60 -> 59461875 | Y60: =+ROUND($H60*Y$57,) -> 60254700 | AB60: =+Y60-AA60 -> 60254700 | AD60: =+ROUND(D60*G60*1.1-Y60-T60-K60,) -> 30920175 | AG60: =+AD60-AF60 -> 30920175 | AX60: =+ROUND($H60*AX$57,) -> 0 | BA60: =+AX60-AZ60 -> 0 | BC60: =T60+Y60+AD60+AX60+K60=D60*G60*1.1 -> TRUE
C61: Seoyong(Drop) | D61: =+'[6]BT 6HO'!D21 -> 138.43 | F61: 950000 | G61: 1050000 | H61: =+F61*D61*1.1 -> 144659350 | I61: =+V61+AA61+AF61+AZ61 -> 15227300 | J61: =+I61 -> 15227300 | K61: =+SUM(L61:O61) -> 0 | R61: =+K61-Q61 -> 0 | S61: =+'[6]BT 6HO'!N22 -> 45631 | T61: =+ROUND($H61*T$57,) -> 72329675 | U61: =+'[6]BT 6HO'!O22 -> 45631 | V61: =+'[6]BT 6HO'!R22+'[6]BT 6HO'!R23 -> 15227300 | W61: =+T61-V61 -> 57102375 | Y61: =+ROUND($H61*Y$57,) -> 57863740 | AB61: =+Y61-AA61 -> 57863740 | AD61: =+ROUND(D61*G61*1.1-Y61-T61-K61,) -> 29693235 | AG61: =+AD61-AF61 -> 29693235 | AX61: =+ROUND($H61*AX$57,) -> 0 | BA61: =+AX61-AZ61 -> 0 | BC61: =T61+Y61+AD61+AX61+K61=D61*G61*1.1 -> TRUE
C62: Cosmo chemical | D62: =+'[6]BT 6HO'!D26 -> 2444.8 | F62: 950000 | G62: 1050000 | H62: =+F62*D62*1.1 -> 2554816000 | I62: =+V62+AA62+AF62+AZ62 -> 0 | K62: =+SUM(L62:O62) -> 0 | R62: =+K62-Q62 -> 0 | T62: =+ROUND($H62*T$57,) -> 1277408000 | W62: =+T62-V62 -> 1277408000 | Y62: =+ROUND($H62*Y$57,) -> 1021926400 | AB62: =+Y62-AA62 -> 1021926400 | AD62: =+ROUND(D62*G62*1.1-Y62-T62-K62,) -> 524409600 | AG62: =+AD62-AF62 -> 524409600 | AX62: =+ROUND($H62*AX$57,) -> 0 | BA62: =+AX62-AZ62 -> 0 | BC62: =T62+Y62+AD62+AX62+K62=D62*G62*1.1 -> TRUE
C63: =+'[6]BT 2HO'!C85 -> 0 | D63: =+'[6]BT 2HO'!D85 -> 0 | F63: 950000 | G63: 1050000 | H63: =+F63*D63*1.1 -> 0 | I63: =+V63+AA63+AF63+AZ63 -> 0 | K63: =+SUM(L63:O63) -> 0 | R63: =+K63-Q63 -> 0 | T63: =+ROUND($H63*T$57,) -> 0 | W63: =+T63-V63 -> 0 | Y63: =+ROUND($H63*Y$57,) -> 0 | AB63: =+Y63-AA63 -> 0 | AD63: =+ROUND(D63*G63*1.1-Y63-T63-K63,) -> 0 | AG63: =+AD63-AF63 -> 0 | AX63: =+ROUND($H63*AX$57,) -> 0 | BA63: =+AX63-AZ63 -> 0 | BC63: =T63+Y63+AD63+AX63+K63=D63*G63*1.1 -> TRUE
C64: =+'[6]BT 2HO'!C90 -> 0 | D64: =+'[6]BT 2HO'!D90 -> 0 | F64: 950000 | G64: 1050000 | H64: =+F64*D64*1.1 -> 0 | I64: =+V64+AA64+AF64+AZ64 -> 0 | K64: =+SUM(L64:O64) -> 0 | R64: =+K64-Q64 -> 0 | T64: =+ROUND($H64*T$57,) -> 0 | W64: =+T64-V64 -> 0 | Y64: =+ROUND($H64*Y$57,) -> 0 | AB64: =+Y64-AA64 -> 0 | AD64: =+ROUND(D64*G64*1.1-Y64-T64-K64,) -> 0 | AG64: =+AD64-AF64 -> 0 | AX64: =+ROUND($H64*AX$57,) -> 0 | BA64: =+AX64-AZ64 -> 0 | BC64: =T64+Y64+AD64+AX64+K64=D64*G64*1.1 -> TRUE
C65: =+'[6]BT 2HO'!C95 -> 0 | D65: =+'[6]BT 2HO'!D95 -> 0 | F65: 950000 | G65: 1050000 | H65: =+F65*D65*1.1 -> 0 | I65: =+V65+AA65+AF65+AZ65 -> 0 | K65: =+SUM(L65:O65) -> 0 | R65: =+K65-Q65 -> 0 | T65: =+ROUND($H65*T$57,) -> 0 | W65: =+T65-V65 -> 0 | Y65: =+ROUND($H65*Y$57,) -> 0 | AB65: =+Y65-AA65 -> 0 | AD65: =+ROUND(D65*G65*1.1-Y65-T65-K65,) -> 0 | AG65: =+AD65-AF65 -> 0 | AX65: =+ROUND($H65*AX$57,) -> 0 | BA65: =+AX65-AZ65 -> 0 | BC65: =T65+Y65+AD65+AX65+K65=D65*G65*1.1 -> TRUE
C66: =+'[6]BT 2HO'!C100 -> 0 | D66: =+'[6]BT 2HO'!D100 -> 0 | F66: 950000 | G66: 1050000 | H66: =+F66*D66*1.1 -> 0 | I66: =+V66+AA66+AF66+AZ66 -> 0 | K66: =+SUM(L66:O66) -> 0 | R66: =+K66-Q66 -> 0 | T66: =+ROUND($H66*T$57,) -> 0 | W66: =+T66-V66 -> 0 | Y66: =+ROUND($H66*Y$57,) -> 0 | AB66: =+Y66-AA66 -> 0 | AD66: =+ROUND(D66*G66*1.1-Y66-T66-K66,) -> 0 | AG66: =+AD66-AF66 -> 0 | AX66: =+ROUND($H66*AX$57,) -> 0 | BA66: =+AX66-AZ66 -> 0 | BC66: =T66+Y66+AD66+AX66+K66=D66*G66*1.1 -> TRUE
C67: =+'[6]BT 2HO'!C105 -> 0 | D67: =+'[6]BT 2HO'!D105 -> 0 | F67: 950000 | G67: 1050000 | H67: =+F67*D67*1.1 -> 0 | K67: =+SUM(L67:O67) -> 0 | R67: =+K67-Q67 -> 0 | T67: =+ROUND($H67*T$57,) -> 0 | W67: =+T67-V67 -> 0 | Y67: =+ROUND($H67*Y$57,) -> 0 | AB67: =+Y67-AA67 -> 0 | AD67: =+ROUND(D67*G67*1.1-Y67-T67-K67,) -> 0 | AG67: =+AD67-AF67 -> 0 | AX67: =+ROUND($H67*AX$57,) -> 0 | BA67: =+AX67-AZ67 -> 0 | BC67: =T67+Y67+AD67+AX67+K67=D67*G67*1.1 -> TRUE
C68: =+'[6]BT 2HO'!C110 -> 0 | D68: =+'[6]BT 2HO'!D110 -> 0 | F68: 950000 | G68: 1050000 | H68: =+F68*D68*1.1 -> 0 | K68: =+SUM(L68:O68) -> 0 | R68: =+K68-Q68 -> 0 | T68: =+ROUND($H68*T$57,) -> 0 | W68: =+T68-V68 -> 0 | Y68: =+ROUND($H68*Y$57,) -> 0 | AB68: =+Y68-AA68 -> 0 | AD68: =+ROUND(D68*G68*1.1-Y68-T68-K68,) -> 0 | AG68: =+AD68-AF68 -> 0 | AX68: =+ROUND($H68*AX$57,) -> 0 | BA68: =+AX68-AZ68 -> 0 | BC68: =T68+Y68+AD68+AX68+K68=D68*G68*1.1 -> TRUE
C69: =+'[6]BT 2HO'!C115 -> 0 | D69: =+'[6]BT 2HO'!D115 -> 0 | F69: 950000 | G69: 1050000 | H69: =+F69*D69*1.1 -> 0 | K69: =+SUM(L69:O69) -> 0 | R69: =+K69-Q69 -> 0 | T69: =+ROUND($H69*T$57,) -> 0 | W69: =+T69-V69 -> 0 | Y69: =+ROUND($H69*Y$57,) -> 0 | AB69: =+Y69-AA69 -> 0 | AD69: =+ROUND(D69*G69*1.1-Y69-T69-K69,) -> 0 | AG69: =+AD69-AF69 -> 0 | AX69: =+ROUND($H69*AX$57,) -> 0 | BA69: =+AX69-AZ69 -> 0 | BC69: =T69+Y69+AD69+AX69+K69=D69*G69*1.1 -> TRUE
C70: =+'[6]BT 2HO'!C120 -> 0 | D70: =+'[6]BT 2HO'!D120 -> 0 | F70: 950000 | G70: 1050000 | H70: =+F70*D70*1.1 -> 0 | K70: =+SUM(L70:O70) -> 0 | R70: =+K70-Q70 -> 0 | T70: =+ROUND($H70*T$57,) -> 0 | W70: =+T70-V70 -> 0 | Y70: =+ROUND($H70*Y$57,) -> 0 | AB70: =+Y70-AA70 -> 0 | AD70: =+ROUND(D70*G70*1.1-Y70-T70-K70,) -> 0 | AG70: =+AD70-AF70 -> 0 | AX70: =+ROUND($H70*AX$57,) -> 0 | BA70: =+AX70-AZ70 -> 0 | BC70: =T70+Y70+AD70+AX70+K70=D70*G70*1.1 -> TRUE
C71: =+'[6]BT 2HO'!C125 -> 0 | D71: =+'[6]BT 2HO'!D125 -> 0 | F71: 950000 | G71: 1050000 | H71: =+F71*D71*1.1 -> 0 | K71: =+SUM(L71:O71) -> 0 | R71: =+K71-Q71 -> 0 | T71: =+ROUND($H71*T$57,) -> 0 | W71: =+T71-V71 -> 0 | Y71: =+ROUND($H71*Y$57,) -> 0 | AB71: =+Y71-AA71 -> 0 | AD71: =+ROUND(D71*G71*1.1-Y71-T71-K71,) -> 0 | AG71: =+AD71-AF71 -> 0 | AX71: =+ROUND($H71*AX$57,) -> 0 | BA71: =+AX71-AZ71 -> 0 | BC71: =T71+Y71+AD71+AX71+K71=D71*G71*1.1 -> TRUE
C72: =+'[6]BT 2HO'!C130 -> 0 | D72: =+'[6]BT 2HO'!D130 -> 0 | F72: 950000 | G72: 1050000 | H72: =+F72*D72*1.1 -> 0 | K72: =+SUM(L72:O72) -> 0 | R72: =+K72-Q72 -> 0 | T72: =+ROUND($H72*T$57,) -> 0 | W72: =+T72-V72 -> 0 | Y72: =+ROUND($H72*Y$57,) -> 0 | AB72: =+Y72-AA72 -> 0 | AD72: =+ROUND(D72*G72*1.1-Y72-T72-K72,) -> 0 | AG72: =+AD72-AF72 -> 0 | AX72: =+ROUND($H72*AX$57,) -> 0 | BA72: =+AX72-AZ72 -> 0 | BC72: =T72+Y72+AD72+AX72+K72=D72*G72*1.1 -> TRUE
B74: SPV | C74: Project | D74: Capacity (kWp) | F74: CAPEX/MW EPC 계약 | G74: CAPEX/MW COD 적용 | H74: Total | I74: 지급완료 | J74: Drop 지급액 | K74: 계통연계비 | S74: Milestone 1 | X74: Milestone 2 | AC74: Milestone 3 | AW74: Milestone 4
K75: 선로비 Total | L75: 기타시설부담금1 | M75: 기타시설부담금2 | N75: 기술검토비 | O75: 표준시설부담금 | P75: Payment Date | Q75: Paid Amount | R75: 미지급액 | S75: Date | T75: 0.5 | U75: Date | V75: 지급금액 | W75: 차액 | X75: Date | Y75: 0.4 | Z75: Date | AA75: 지급금액 | AB75: 차액 | AC75: Date | AD75: 0.1 | AE75: Date | AF75: 지급금액 | AG75: 차액 | AW75: Date | AX75: 0 | AY75: Date | AZ75: 지급금액 | BA75: 차액
B76: Bolt #7 | D76: =+SUM(D77:D90) -> 1609.38 | F76: 950000 | G76: 1050000 | H76: =+SUM(H77:H90) -> 1.6818021e+09 | I76: =+SUM(I77:I90) -> 662691700 | J76: =+SUM(J77:J90) -> 102643200 | K76: =+SUM(K77:K90) -> 54521680 | L76: =+SUM(L77:L90) -> 5190920 | M76: =+SUM(M77:M90) -> 5885160 | N76: =+SUM(N77:N90) -> 0 | O76: =+SUM(O77:O90) -> 43445600 | Q76: =+SUM(Q77:Q90) -> 54521680 | R76: =+SUM(R77:R90) -> 0 | T76: =+SUM(T77:T90) -> 840901050 | V76: =+SUM(V77:V90) -> 191320800 | W76: =+SUM(W77:W90) -> 649580250 | Y76: =+SUM(Y77:Y90) -> 672720840 | AB76: =+SUM(AB77:AB90) -> 481320840 | AD76: =+SUM(AD77:AD90) -> 290690330 | AG76: =+SUM(AG77:AG90) -> 10719430 | AX76: =+SUM(AX77:AX90) -> 0 | BA76: =+SUM(BA77:BA90) -> 0 | BC76: =T76+Y76+AD76+AX76+K76=D76*G76*1.1 -> TRUE
C77: Eco Inshutech(Drop) | D77: 225.78 | F77: 950000 | G77: 1050000 | H77: =+F77*D77*1.1 -> 2.359401e+08 | I77: =+V77+AA77+AF77+AZ77 -> 158004000 | K77: =+SUM(L77:O77) -> 34643780 | L77: 2824780 | M77: 2999000 | O77: 28820000 | P77: 46001 | Q77: 34643780 | R77: =+K77-Q77 -> 0 | S77: =+'[6]BT 7HO'!N12 -> 45650 | T77: =+ROUND($H77*T$75,) -> 117970050 | U77: =+'[6]BT 7HO'!O12 -> 45650 | V77: =+'[6]BT 7HO'!R12+'[6]BT 7HO'!R13 -> 35112000 | W77: =+T77-V77 -> 82858050 | X77: =+'[6]BT 7HO'!U12 -> 45737 | Y77: =+ROUND($H77*Y$75,) -> 94376040 | Z77: =+'[6]BT 7HO'!V12 -> 45737 | AA77: =+'[6]BT 7HO'!Y12+'[6]BT 7HO'!Y13 -> 35112000 | AB77: =+Y77-AA77 -> 59264040 | AC77: =+'[6]BT 7HO'!AB12 -> 45791 | AD77: =+ROUND(D77*G77*1.1-Y77-T77-K77,) -> 13786030 | AE77: =+'[6]BT 7HO'!AC12 -> 45791 | AF77: =+'[6]BT 7HO'!AF12+'[6]BT 7HO'!AF13 -> 87780000 | AG77: =+AD77-AF77 -> -73993970 | AX77: =+ROUND($H77*AX$75,) -> 0 | BA77: =+AX77-AZ77 -> 0 | BC77: =T77+Y77+AD77+AX77+K77=D77*G77*1.1 -> TRUE
C78: Younggwang Industry | D78: 545.46 | F78: 950000 | G78: 1050000 | H78: =+F78*D78*1.1 -> 5.700057e+08 | I78: =+V78+AA78+AF78+AZ78 -> 120001200 | K78: =+SUM(L78:O78) -> 19877900 | L78: 2366140 | M78: 2886160 | O78: 14625600 | P78: 45975 | Q78: 19877900 | R78: =+K78-Q78 -> 0 | S78: =+'[6]BT 7HO'!N17 -> 45679 | T78: =+ROUND($H78*T$75,) -> 285002850 | U78: =+'[6]BT 7HO'!O17 -> 45679 | V78: =+'[6]BT 7HO'!R17+'[6]BT 7HO'!R18 -> 60000600 | W78: =+T78-V78 -> 225002250 | X78: =+'[6]BT 7HO'!U17 -> 45791 | Y78: =+ROUND($H78*Y$75,) -> 228002280 | Z78: =+'[6]BT 7HO'!V17 -> 45791 | AA78: =+'[6]BT 7HO'!Y17+'[6]BT 7HO'!Y18 -> 60000600 | AB78: =+Y78-AA78 -> 168001680 | AC78: =+'[6]BT 7HO'!AB17 -> 45991 | AD78: =+ROUND(D78*G78*1.1-Y78-T78-K78,) -> 97123270 | AG78: =+AD78-AF78 -> 97123270 | AX78: =+ROUND($H78*AX$75,) -> 0 | BA78: =+AX78-AZ78 -> 0 | BC78: =T78+Y78+AD78+AX78+K78=D78*G78*1.1 -> TRUE
C79: BNB Composite(Drop) | D79: 207.36 | F79: 950000 | G79: 1050000 | H79: =+F79*D79*1.1 -> 2.166912e+08 | I79: =+V79+AA79+AF79+AZ79 -> 102643200 | J79: =+I79 -> 102643200 | K79: =+SUM(L79:O79) -> 0 | R79: =+K79-Q79 -> 0 | S79: =+'[6]BT 7HO'!N22 -> 45808 | T79: =+ROUND($H79*T$75,) -> 108345600 | U79: =+'[6]BT 7HO'!O22 -> 45791 | V79: =+'[6]BT 7HO'!R22+'[6]BT 7HO'!R23 -> 26822400 | W79: =+T79-V79 -> 81523200 | X79: =+'[6]BT 7HO'!U22 -> 45855 | Y79: =+ROUND($H79*Y$75,) -> 86676480 | Z79: =+'[6]BT 7HO'!V22 -> 45867 | AA79: =+'[6]BT 7HO'!Y22+'[6]BT 7HO'!Y23 -> 26822400 | AB79: =+Y79-AA79 -> 59854080 | AC79: =+'[6]BT 7HO'!AB22 -> 45930 | AD79: =+ROUND(D79*G79*1.1-Y79-T79-K79,) -> 44478720 | AE79: =+'[6]BT 7HO'!AC22 -> 45922 | AF79: =+'[6]BT 7HO'!AF22+'[6]BT 7HO'!AF23 -> 48998400 | AG79: =+AD79-AF79 -> -4519680 | AX79: =+ROUND($H79*AX$75,) -> 0 | BA79: =+AX79-AZ79 -> 0 | BC79: =T79+Y79+AD79+AX79+K79=D79*G79*1.1 -> TRUE
C80: MPM Trade | D80: 210.82 | F80: 950000 | G80: 1050000 | H80: =+F80*D80*1.1 -> 2.203069e+08 | I80: =+V80+AA80+AF80+AZ80 -> 104355900 | K80: =+SUM(L80:O80) -> 0 | R80: =+K80-Q80 -> 0 | S80: =+'[6]BT 7HO'!N27 -> 45737 | T80: =+ROUND($H80*T$75,) -> 110153450 | U80: =+'[6]BT 7HO'!O27 -> 45737 | V80: =+'[6]BT 7HO'!R27+'[6]BT 7HO'!R28 -> 23190200 | W80: =+T80-V80 -> 86963250 | X80: =+'[6]BT 7HO'!U27 -> 45820 | Y80: =+ROUND($H80*Y$75,) -> 88122760 | Z80: =+'[6]BT 7HO'!V27 -> 45820 | AA80: =+'[6]BT 7HO'!Y27+'[6]BT 7HO'!Y28 -> 23190200 | AB80: =+Y80-AA80 -> 64932560 | AC80: =+'[6]BT 7HO'!AB27 -> 45900 | AD80: =+ROUND(D80*G80*1.1-Y80-T80-K80,) -> 45220890 | AE80: =+'[6]BT 7HO'!AC27 -> 45883 | AF80: =+'[6]BT 7HO'!AF27+'[6]BT 7HO'!AF28 -> 57975500 | AG80: =+AD80-AF80 -> -12754610 | AX80: =+ROUND($H80*AX$75,) -> 0 | BA80: =+AX80-AZ80 -> 0 | BC80: =T80+Y80+AD80+AX80+K80=D80*G80*1.1 -> TRUE
C81: Ajin P&S(개인사업자) | D81: 151.13 | F81: 950000 | G81: 1050000 | H81: =+F81*D81*1.1 -> 157930850 | I81: =+V81+AA81+AF81+AZ81 -> 74809350 | K81: =+SUM(L81:O81) -> 0 | R81: =+K81-Q81 -> 0 | S81: =+'[6]BT 7HO'!N32 -> 45679 | T81: =+ROUND($H81*T$75,) -> 78965425 | U81: =+'[6]BT 7HO'!O32 -> 45679 | V81: =+'[6]BT 7HO'!R32+'[6]BT 7HO'!R33 -> 16624300 | W81: =+T81-V81 -> 62341125 | X81: =+'[6]BT 7HO'!U32 -> 45791 | Y81: =+ROUND($H81*Y$75,) -> 63172340 | Z81: =+'[6]BT 7HO'!V32 -> 45791 | AA81: =+'[6]BT 7HO'!Y32+'[6]BT 7HO'!Y33 -> 16624300 | AB81: =+Y81-AA81 -> 46548040 | AC81: =+'[6]BT 7HO'!AB32 -> 45820 | AD81: =+ROUND(D81*G81*1.1-Y81-T81-K81,) -> 32417385 | AE81: =+'[6]BT 7HO'!AC32 -> 45820 | AF81: =+'[6]BT 7HO'!AF32+'[6]BT 7HO'!AF33 -> 41560750 | AG81: =+AD81-AF81 -> -9143365 | AX81: =+ROUND($H81*AX$75,) -> 0 | BA81: =+AX81-AZ81 -> 0 | BC81: =T81+Y81+AD81+AX81+K81=D81*G81*1.1 -> TRUE
C82: Myunghyun Tech 1(개인사업자) | D82: 71.68 | F82: 950000 | G82: 1050000 | H82: =+F82*D82*1.1 -> 74905600 | I82: =+V82+AA82+AF82+AZ82 -> 15848800 | K82: =+SUM(L82:O82) -> 0 | R82: =+K82-Q82 -> 0 | S82: =+'[6]BT 7HO'!N37 -> 45705 | T82: =+ROUND($H82*T$75,) -> 37452800 | U82: =+'[6]BT 7HO'!O37 -> 45705 | V82: =+'[6]BT 7HO'!R37+'[6]BT 7HO'!R38 -> 7884800 | W82: =+T82-V82 -> 29568000 | X82: =+'[6]BT 7HO'!U37 -> 45820 | Y82: =+ROUND($H82*Y$75,) -> 29962240 | Z82: =+'[6]BT 7HO'!V37 -> 45820 | AA82: =+'[6]BT 7HO'!Y37+'[6]BT 7HO'!Y38 -> 7964000 | AB82: =+Y82-AA82 -> 21998240 | AC82: =+'[6]BT 7HO'!AB37 -> 46022 | AD82: =+ROUND(D82*G82*1.1-Y82-T82-K82,) -> 15375360 | AG82: =+AD82-AF82 -> 15375360 | AX82: =+ROUND($H82*AX$75,) -> 0 | BA82: =+AX82-AZ82 -> 0 | BC82: =T82+Y82+AD82+AX82+K82=D82*G82*1.1 -> TRUE
C83: Myunghyun Tech 2(개인사업자) | D83: 38.4 | F83: 950000 | G83: 1050000 | H83: =+F83*D83*1.1 -> 40128000 | I83: =+V83+AA83+AF83+AZ83 -> 8448000 | K83: =+SUM(L83:O83) -> 0 | R83: =+K83-Q83 -> 0 | S83: =+'[6]BT 7HO'!N42 -> 45705 | T83: =+ROUND($H83*T$75,) -> 20064000 | U83: =+'[6]BT 7HO'!O42 -> 45705 | V83: =+'[6]BT 7HO'!R42+'[6]BT 7HO'!R43 -> 4224000 | W83: =+T83-V83 -> 15840000 | X83: =+'[6]BT 7HO'!U42 -> 45820 | Y83: =+ROUND($H83*Y$75,) -> 16051200 | Z83: =+'[6]BT 7HO'!V42 -> 45820 | AA83: =+'[6]BT 7HO'!Y42+'[6]BT 7HO'!Y43 -> 4224000 | AB83: =+Y83-AA83 -> 11827200 | AC83: =+'[6]BT 7HO'!AB42 -> 46022 | AD83: =+ROUND(D83*G83*1.1-Y83-T83-K83,) -> 8236800 | AG83: =+AD83-AF83 -> 8236800 | AX83: =+ROUND($H83*AX$75,) -> 0 | BA83: =+AX83-AZ83 -> 0 | BC83: =T83+Y83+AD83+AX83+K83=D83*G83*1.1 -> TRUE
C84: Sehyun Chemical(개인사업자) | D84: 158.75 | F84: 950000 | G84: 1050000 | H84: =+F84*D84*1.1 -> 165893750 | I84: =+V84+AA84+AF84+AZ84 -> 78581250 | K84: =+SUM(L84:O84) -> 0 | R84: =+K84-Q84 -> 0 | S84: =+'[6]BT 7HO'!N47 -> 45705 | T84: =+ROUND($H84*T$75,) -> 82946875 | U84: =+'[6]BT 7HO'!O47 -> 45705 | V84: =+'[6]BT 7HO'!R47+'[6]BT 7HO'!R48 -> 17462500 | W84: =+T84-V84 -> 65484375 | X84: =+'[6]BT 7HO'!U47 -> 45820 | Y84: =+ROUND($H84*Y$75,) -> 66357500 | Z84: =+'[6]BT 7HO'!V47 -> 45820 | AA84: =+'[6]BT 7HO'!Y47+'[6]BT 7HO'!Y48 -> 17462500 | AB84: =+Y84-AA84 -> 48895000 | AC84: =+'[6]BT 7HO'!AB47 -> 45930 | AD84: =+ROUND(D84*G84*1.1-Y84-T84-K84,) -> 34051875 | AE84: 45922 | AF84: =+'[6]BT 7HO'!AF47+'[6]BT 7HO'!AF48 -> 43656250 | AG84: =+AD84-AF84 -> -9604375 | AX84: =+ROUND($H84*AX$75,) -> 0 | BA84: =+AX84-AZ84 -> 0 | BC84: =T84+Y84+AD84+AX84+K84=D84*G84*1.1 -> TRUE
C85: =+'[6]BT 2HO'!C123 -> 0 | D85: 0 | F85: 950000 | G85: 1050000 | H85: =+F85*D85*1.1 -> 0 | K85: =+SUM(L85:O85) -> 0 | R85: =+K85-Q85 -> 0 | T85: =+ROUND($H85*T$75,) -> 0 | W85: =+T85-V85 -> 0 | Y85: =+ROUND($H85*Y$75,) -> 0 | AB85: =+Y85-AA85 -> 0 | AD85: =+ROUND(D85*G85*1.1-Y85-T85-K85,) -> 0 | AG85: =+AD85-AF85 -> 0 | AX85: =+ROUND($H85*AX$75,) -> 0 | BA85: =+AX85-AZ85 -> 0 | BC85: =T85+Y85+AD85+AX85+K85=D85*G85*1.1 -> TRUE
C86: =+'[6]BT 2HO'!C128 -> 0 | D86: 0 | F86: 950000 | G86: 1050000 | H86: =+F86*D86*1.1 -> 0 | K86: =+SUM(L86:O86) -> 0 | R86: =+K86-Q86 -> 0 | T86: =+ROUND($H86*T$75,) -> 0 | W86: =+T86-V86 -> 0 | Y86: =+ROUND($H86*Y$75,) -> 0 | AB86: =+Y86-AA86 -> 0 | AD86: =+ROUND(D86*G86*1.1-Y86-T86-K86,) -> 0 | AG86: =+AD86-AF86 -> 0 | AX86: =+ROUND($H86*AX$75,) -> 0 | BA86: =+AX86-AZ86 -> 0 | BC86: =T86+Y86+AD86+AX86+K86=D86*G86*1.1 -> TRUE
C87: =+'[6]BT 2HO'!C133 -> 0 | D87: 0 | F87: 950000 | G87: 1050000 | H87: =+F87*D87*1.1 -> 0 | K87: =+SUM(L87:O87) -> 0 | R87: =+K87-Q87 -> 0 | T87: =+ROUND($H87*T$75,) -> 0 | W87: =+T87-V87 -> 0 | Y87: =+ROUND($H87*Y$75,) -> 0 | AB87: =+Y87-AA87 -> 0 | AD87: =+ROUND(D87*G87*1.1-Y87-T87-K87,) -> 0 | AG87: =+AD87-AF87 -> 0 | AX87: =+ROUND($H87*AX$75,) -> 0 | BA87: =+AX87-AZ87 -> 0 | BC87: =T87+Y87+AD87+AX87+K87=D87*G87*1.1 -> TRUE
C88: =+'[6]BT 2HO'!C138 -> 0 | D88: 0 | F88: 950000 | G88: 1050000 | H88: =+F88*D88*1.1 -> 0 | K88: =+SUM(L88:O88) -> 0 | R88: =+K88-Q88 -> 0 | T88: =+ROUND($H88*T$75,) -> 0 | W88: =+T88-V88 -> 0 | Y88: =+ROUND($H88*Y$75,) -> 0 | AB88: =+Y88-AA88 -> 0 | AD88: =+ROUND(D88*G88*1.1-Y88-T88-K88,) -> 0 | AG88: =+AD88-AF88 -> 0 | AX88: =+ROUND($H88*AX$75,) -> 0 | BA88: =+AX88-AZ88 -> 0 | BC88: =T88+Y88+AD88+AX88+K88=D88*G88*1.1 -> TRUE
C89: =+'[6]BT 2HO'!C143 -> 0 | D89: 0 | F89: 950000 | G89: 1050000 | H89: =+F89*D89*1.1 -> 0 | K89: =+SUM(L89:O89) -> 0 | R89: =+K89-Q89 -> 0 | T89: =+ROUND($H89*T$75,) -> 0 | W89: =+T89-V89 -> 0 | Y89: =+ROUND($H89*Y$75,) -> 0 | AB89: =+Y89-AA89 -> 0 | AD89: =+ROUND(D89*G89*1.1-Y89-T89-K89,) -> 0 | AG89: =+AD89-AF89 -> 0 | AX89: =+ROUND($H89*AX$75,) -> 0 | BA89: =+AX89-AZ89 -> 0 | BC89: =T89+Y89+AD89+AX89+K89=D89*G89*1.1 -> TRUE
C90: =+'[6]BT 2HO'!C148 -> 0 | D90: 0 | F90: 950000 | G90: 1050000 | H90: =+F90*D90*1.1 -> 0 | K90: =+SUM(L90:O90) -> 0 | R90: =+K90-Q90 -> 0 | T90: =+ROUND($H90*T$75,) -> 0 | W90: =+T90-V90 -> 0 | Y90: =+ROUND($H90*Y$75,) -> 0 | AB90: =+Y90-AA90 -> 0 | AD90: =+ROUND(D90*G90*1.1-Y90-T90-K90,) -> 0 | AG90: =+AD90-AF90 -> 0 | AX90: =+ROUND($H90*AX$75,) -> 0 | BA90: =+AX90-AZ90 -> 0 | BC90: =T90+Y90+AD90+AX90+K90=D90*G90*1.1 -> TRUE

Sheet DEVEX 지급현황
Q3: [단위 : 원]
B4: SPV | C4: Project | D4: Capacity (kWp) | E4: DEVEX/MW COD 적용 | F4: Total | G4: 미지급금 | H4: 지급완료 | I4: Milestone 1 | K4: Milestone 2 | M4: Milestone 3 | O4: Milestone 4 | Q4: Remark
I5: Date | J5: 지급금액 | K5: Date | L5: 지급금액 | M5: Date | N5: 예정금액 | O5: Date | P5: 예정금액 | R5: 용량 소폭 변경에 따른 차액 Milestones 4에 반영
B6: Bolt #1 | D6: =+SUM(D7:D14) -> 7995.2 | F6: =+SUM(F7:F14) -> 2198812000 | G6: =+SUM(G7:G14) -> 726573100 | H6: =+SUM(H7:H14) -> 1472238900 | J6: =+SUM(J7:J14) -> 1209503900 | L6: =+SUM(L7:L14) -> 262735000 | N6: =+SUM(N7:N14) -> 67129700 | P6: =+SUM(P7:P14) -> 659443400 | T6: 차액
C7: =+'SPV별 CAPEX 현황'!C5 -> YJ NANSAN 1 | D7: 999.46 | E7: 550000 | F7: =+D7*E7 -> 549703000 | G7: =+N7+P7 -> 181646300 | H7: =+J7+L7 -> 368056700 | I7: =+'GM Batch1'!M12 -> 45450 | J7: =+'GM Batch1'!Q12 -> 302372950 | K7: =+'GM Batch1'!U12 -> 45456 | L7: =+'GM Batch1'!X12 -> 65683750 | N7: =+'GM Batch1'!AD12 -> 16781600 | P7: =+'GM Batch1'!BM12-66000 -> 164864700 | T7: 66000
C8: =+'SPV별 CAPEX 현황'!C6 -> YJ NANSAN 2 | D8: 999.46 | E8: 550000 | F8: =+D8*E8 -> 549703000 | G8: =+N8+P8 -> 181646300 | H8: =+J8+L8 -> 368056700 | I8: =+'GM Batch1'!N18 -> 45450 | J8: =+'GM Batch1'!Q18 -> 302372950 | K8: =+'GM Batch1'!U18 -> 45456 | L8: =+'GM Batch1'!X18 -> 65683750 | N8: =+'GM Batch1'!AD18 -> 16781600 | P8: =+'GM Batch1'!BM18-66000 -> 164864700 | T8: 66000
C9: =+'SPV별 CAPEX 현황'!C7 -> YJ GASI 1 | D9: 999.46 | E9: 550000 | F9: =+D9*E9 -> 549703000 | G9: =+N9+P9 -> 181640250 | H9: =+J9+L9 -> 368062750 | I9: =+'GM Batch1'!N24 -> 45450 | J9: =+'GM Batch1'!Q24 -> 302379000 | K9: =+'GM Batch1'!U24 -> 45456 | L9: =+'GM Batch1'!X24 -> 65683750 | N9: =+'GM Batch1'!AD24 -> 16783250 | P9: =+'GM Batch1'!BM24-77000 -> 164857000 | T9: 77000
C10: =+'SPV별 CAPEX 현황'!C8 -> YJ GASI 2 | D10: 999.46 | E10: 550000 | F10: =+D10*E10 -> 549703000 | G10: =+N10+P10 -> 181640250 | H10: =+J10+L10 -> 368062750 | I10: =+'GM Batch1'!N30 -> 45450 | J10: =+'GM Batch1'!Q30 -> 302379000 | K10: =+'GM Batch1'!U30 -> 45456 | L10: =+'GM Batch1'!X30 -> 65683750 | N10: =+'GM Batch1'!AD30 -> 16783250 | P10: =+'GM Batch1'!BM30-77000 -> 164857000 | T10: 77000
C11: =+'SPV별 CAPEX 현황'!C9 -> Dream 1 | D11: =+'SPV별 CAPEX 현황'!D9 -> 999.24 | E11: 550000 | H11: =+J11+L11+N11+P11 -> 0
C12: =+'SPV별 CAPEX 현황'!C10 -> Dream 2 | D12: =+'SPV별 CAPEX 현황'!D10 -> 999.24 | E12: 550000 | H12: =+J12+L12+N12+P12 -> 0
C13: =+'SPV별 CAPEX 현황'!C11 -> JEIL TECH 1 | D13: =+'SPV별 CAPEX 현황'!D11 -> 999.44 | E13: 550000 | H13: =+J13+L13+N13+P13 -> 0
C14: =+'SPV별 CAPEX 현황'!C12 -> JEIL TECH 2 | D14: =+'SPV별 CAPEX 현황'!D12 -> 999.44 | E14: 550000 | H14: =+J14+L14+N14+P14 -> 0
Q16: [단위 : 원]
B17: SPV | C17: Project(Batch2) | D17: Capacity (kWp) | E17: DEVEX/MW COD 적용 | F17: Total | G17: 미지급금 | H17: 지급완료 | I17: Milestone 1 | K17: Milestone 2 | M17: Milestone 3 | O17: Milestone 4 | Q17: Remark
I18: Date | J18: 지급금액 | K18: Date | L18: 예정금액 | M18: Date | N18: 예정금액 | O18: Date | P18: 예정금액
B19: Bolt #1 | D19: =+SUM(D20:D25) -> 2398.92 | F19: =+SUM(F20:F25) -> 2039082000 | G19: =+SUM(G20:G25) -> 1298830800 | H19: =+SUM(H20:H25) -> 740251200 | J19: =+SUM(J20:J25) -> 740251200 | L19: =+SUM(L20:L25) -> 311859600 | N19: =+SUM(N20:N25) -> 467789400 | P19: =+SUM(P20:P25) -> 5.191818e+08
C20: =+'GM Batch2-APA'!C11 -> Jangchon 1 (APA) | D20: =+'GM Batch2-APA'!D11 -> 551.04 | E20: 850000 | F20: =+D20*E20 -> 4.68384e+08 | G20: =+L20+N20+P20 -> 2.085816e+08 | H20: =+J20 -> 259802400 | I20: =+'GM Batch2-APA'!N13 -> 45807 | J20: =+'GM Batch2-APA'!Q12+'GM Batch2-APA'!Q13+'GM Batch2-APA'!Q14 -> 259802400 | L20: =+'GM Batch2-APA'!W12+'GM Batch2-APA'!W13 -> 71635200 | N20: =+'GM Batch2-APA'!AD12+'GM Batch2-APA'!AD13 -> 107452800 | P20: 29493600 | Q20: 용량 변경(999.24->551.04) 지급 금액 Milestones 3에 반영 | S20: =+F20=G20+H20 -> TRUE
C21: =+'GM Batch2-APA'!C17 -> Soltop Masan 1 (APA) | D21: =+'GM Batch2-APA'!D17 -> 399.04 | E21: 850000 | F21: =+D21*E21 -> 339184000 | G21: =+L21+N21+P21 -> 235433600 | H21: =+J21 -> 103750400 | I21: =+'GM Batch2-APA'!M18 -> 45807 | J21: =+'GM Batch2-APA'!Q18+'GM Batch2-APA'!Q19+'GM Batch2-APA'!Q20 -> 103750400 | L21: =+'GM Batch2-APA'!W18+'GM Batch2-APA'!W19 -> 51875200 | N21: =+'GM Batch2-APA'!AD18+'GM Batch2-APA'!AD19 -> 77812800 | P21: =+'GM Batch2-APA'!BM18+'GM Batch2-APA'!BM19+'GM Batch2-APA'!BM20 -> 105745600 | S21: =+F21=G21+H21 -> TRUE
C22: =+'GM Batch2-APA'!C23 -> Hanil Mugok 15 (APA) | D22: =+'GM Batch2-APA'!D23 -> 499.96 | E22: 850000 | F22: =+D22*E22 -> 424966000 | G22: =+L22+N22+P22 -> 294976400 | H22: =+J22 -> 129989600 | I22: =+I21 -> 45807 | J22: =+'GM Batch2-APA'!Q24+'GM Batch2-APA'!Q25+'GM Batch2-APA'!Q26 -> 129989600 | L22: =+'GM Batch2-APA'!W24+'GM Batch2-APA'!W25 -> 64994800 | N22: =+'GM Batch2-APA'!AD24+'GM Batch2-APA'!AD25 -> 97492200 | P22: =+'GM Batch2-APA'!BM24+'GM Batch2-APA'!BM25+'GM Batch2-APA'!BM26 -> 132489400 | S22: =+F22=G22+H22 -> TRUE
C23: =+'GM Batch2-APA'!C29 -> Hanil Jigyeong 1 (APA) | D23: =+'GM Batch2-APA'!D29 -> 499.96 | E23: 850000 | F23: =+D23*E23 -> 424966000 | G23: =+L23+N23+P23 -> 294976400 | H23: =+J23 -> 129989600 | I23: =+I22 -> 45807 | J23: =+'GM Batch2-APA'!Q30+'GM Batch2-APA'!Q31+'GM Batch2-APA'!Q32 -> 129989600 | L23: =+'GM Batch2-APA'!W30+'GM Batch2-APA'!W31 -> 64994800 | N23: =+'GM Batch2-APA'!AD30+'GM Batch2-APA'!AD31 -> 97492200 | P23: =+'GM Batch2-APA'!BM30+'GM Batch2-APA'!BM31+'GM Batch2-APA'!BM32 -> 132489400 | S23: =+F23=G23+H23 -> TRUE
C24: =+'GM Batch2-APA'!C35 -> Hanil Jigyeong 2 (APA) | D24: =+'GM Batch2-APA'!D35 -> 149.64 | E24: 850000 | F24: =+D24*E24 -> 1.27194e+08 | G24: =+L24+N24+P24 -> 88287600 | H24: =+J24 -> 38906400 | I24: =+I23 -> 45807 | J24: =+'GM Batch2-APA'!Q36+'GM Batch2-APA'!Q37+'GM Batch2-APA'!Q38 -> 38906400 | L24: =+'GM Batch2-APA'!W36+'GM Batch2-APA'!W37 -> 19453200 | N24: =+'GM Batch2-APA'!AD36+'GM Batch2-APA'!AD37 -> 29179800 | P24: =+'GM Batch2-APA'!BM36+'GM Batch2-APA'!BM37+'GM Batch2-APA'!BM38 -> 39654600 | S24: =+F24=G24+H24 -> TRUE
C25: =+'GM Batch2-APA'!C41 -> Ho Duck4 (APA) | D25: =+'GM Batch2-APA'!D41 -> 299.28 | E25: 850000 | F25: =+D25*E25 -> 2.54388e+08 | G25: =+L25+N25+P25 -> 176575200 | H25: =+J25 -> 77812800 | I25: =+I24 -> 45807 | J25: =+'GM Batch2-APA'!Q42+'GM Batch2-APA'!Q43+'GM Batch2-APA'!Q44 -> 77812800 | L25: =+'GM Batch2-APA'!W42+'GM Batch2-APA'!W43 -> 38906400 | N25: =+'GM Batch2-APA'!AD42+'GM Batch2-APA'!AD43 -> 58359600 | P25: =+'GM Batch2-APA'!BM42+'GM Batch2-APA'!BM43+'GM Batch2-APA'!BM44 -> 79309200 | S25: =+F25=G25+H25 -> TRUE
B26: ※ Batch2의 DEVEX 금액은 8.5억/MW으로 기본적 DEVEX 금액은 3.5억/MW, 토지매입비 3억/MW, Broker Fee 2억/MW입니다. 현재 Milestone 1은 전체 금액 중 40%를 지급하였습니다.
B27: 지급 비율은 40%, 20%, 30%, 10% 지급 계획이며 1차 지급분만 지급 되어 있는 것으로 판단 됩니다. GV 쪽 자료도 40% 지급된 것으로 확인하였습니다.
B28: Broker Fee는 최초 100% 지급으로 되어 있으나 1차 지급분 40% 지급된것으로 표시하였으나 GV 쪽 자료는 Broker Fee는 지급한 내역이 없습니다. 이부분은 확인 부탁드립니다. 수정해 놓겠습니다. _ 확인하였으며 미지급 되었고 Milestone 4에 전부 반영 예정
B29: - GV 직접 매입으로 VAT는 감안하지 않은 상황입니다.
Q30: [단위 : 원]
B31: SPV | C31: Project(Batch2) | D31: Capacity (kWp) | E31: DEVEX/MW COD 적용 | F31: Total | G31: 미지급금 | H31: 지급완료 | I31: Milestone 1(SPA) | K31: Milestone 2 | M31: Milestone 3 | O31: Milestone 4(Broker Fee) | Q31: Remark
I32: Date | J32: 지급금액 | K32: Date | L32: 예정금액 | M32: Date | N32: 예정금액 | O32: Date | P32: 예정금액
B33: Bolt #1 | D33: =+SUM(D34:D37) -> 2443.32 | F33: =+SUM(F34:F37) -> 1390156000 | G33: =+SUM(G34:G37) -> 488664000 | H33: =+SUM(H34:H37) -> 901492000 | J33: =+SUM(J34:J37) -> 901492000 | L33: =+SUM(L34:L37) -> 0 | N33: =+SUM(N34:N37) -> 0 | P33: =+SUM(P34:P37) -> 488664000
C34: =+'GM Batch2-SPA'!C11 -> Galsan (SPA) | D34: 617.76 | F34: =+D34*200000000/1000+223820970 -> 347372970 | G34: =+L34+N34+P34 -> 123552000 | H34: =+J34 -> 223820970 | I34: =+'GM Batch2-SPA'!N12 -> 45863 | J34: =+'GM Batch2-SPA'!K12 -> 223820970 | P34: =+D34*200000000/1000 -> 123552000 | S34: =+P34+J34=F34 -> TRUE
C35: =+'GM Batch2-SPA'!C17 -> Mineuri (SPA) | D35: 564.96 | F35: =+D35*200000000/1000+110418040 -> 223410040 | G35: =+L35+N35+P35 -> 112992000 | H35: =+J35 -> 110418040 | I35: =+I34 -> 45863 | J35: =+'GM Batch2-SPA'!Q18 -> 110418040 | P35: =+D35*200000000/1000 -> 112992000 | S35: =+P35+J35=F35 -> TRUE
C36: =+'GM Batch2-SPA'!C23 -> Seagol(SPA) | D36: 634.92 | F36: =+D36*200000000/1000+108773270 -> 235757270 | G36: =+L36+N36+P36 -> 1.26984e+08 | H36: =+J36 -> 108773270 | I36: =+I35 -> 45863 | J36: =+'GM Batch2-SPA'!Q24 -> 108773270 | P36: =+D36*200000000/1000 -> 1.26984e+08 | S36: =+P36+J36=F36 -> TRUE
C37: =+'GM Batch2-SPA'!C29 -> Jaesan (SPA) | D37: 625.68 | F37: =+D37*200000000/1000+458479720 -> 583615720 | G37: =+L37+N37+P37 -> 1.25136e+08 | H37: =+J37 -> 458479720 | I37: =+I36 -> 45863 | J37: =+'GM Batch2-SPA'!Q30 -> 458479720 | P37: =+D37*200000000/1000 -> 1.25136e+08 | S37: =+P37+J37=F37 -> TRUE
B38: ※ SPA 관련하여 Astronergy에 전액 지급하여 당사 관리하에 있습니다. 미지급 된 사항은 Broker Fee 2억/MW 에 해당하는 금액을 아직 지급하지 않은 상황입니다.
B39: Broker Fee(2억/MW)는 Milestone 4에 반영하였습니다. 반영된 금액은 현재 용량으로 수정하여 기입하였습니다.

Sheet GM Batch1
B9: NO | C9: Name of Project | D9: Capacity (kWp) | E9: Broker | F9: Expenditure Categories | G9: Total Amount | H9: 10% VAT of Total Amount | I9: Total Amount + 10% VAT | J9: Current Payment Status | M9: Milestone 1 | T9: Milestone 2 | AA9: Milestone 3 | AH9: Milestone 4 | AO9: Milestone 5 | AV9: Milestone 6 | BC9: Milestone 7 | BJ9: Milestone 8 | BR9: Check.
J10: % | K10: Paid Amount (KRW) | L10: Total Unpaid Amount | M10: scheduled Date to Paid | N10: Date to Paid | O10: % | P10: scheduled Paid Amount | Q10: Paid Amount | R10: Unpaid Amount | S10: content | T10: scheduled Date to Paid | U10: Date to Paid | V10: % | W10: scheduled Paid Amount | X10: Paid Amount | Y10: Unpaid Amount | Z10: content | AA10: scheduled Date to Paid | AB10: Date to Paid | AC10: % | AD10: scheduled Paid Amount | AE10: Paid Amount | AF10: Unpaid Amount | AG10: content | AH10: scheduled Date to Paid | AI10: Date to Paid | AJ10: % | AK10: scheduled Paid Amount | AL10: Paid Amount | AM10: Unpaid Amount | AN10: content | AO10: scheduled Date to Paid | AP10: Date to Paid | AQ10: % | AR10: scheduled Paid Amount | AS10: Paid Amount | AT10: Unpaid Amount | AU10: content | AV10: scheduled Date to Paid | AW10: Date to Paid | AX10: % | AY10: scheduled Paid Amount | AZ10: Paid Amount | BA10: Unpaid Amount | BB10: content | BC10: scheduled Date to Paid | BD10: Date to Paid | BE10: % | BF10: scheduled Paid Amount | BG10: Paid Amount | BH10: Unpaid Amount | BI10: content | BJ10: scheduled Date to Paid | BK10: Date to Paid | BL10: % | BM10: scheduled Paid Amount | BN10: Paid Amount | BO10: Unpaid Amount | BP10: content
B11: 1 | C11: YJ NANSAN 1 | D11: 999.58 | E11: Solar city | F11: CAPEX | G11: =+'PAYMENT RATIO_RAW'!F$5*'GM Batch1'!$D$11/1000+27500000*D11/1000 -> 1077047450 | H11: =+G11*10% -> 107704745 | I11: =SUM(G11:H11) -> 1184752195 | J11: =+IFERROR(K11/I11,"-") -> 0.19497748 | K11: =+IFERROR(Q11+X11+AE11+AS11+AZ11+BG11+BN11,"-") -> 231000000 | L11: =+I11-K11 -> 953752195 | P11: =+$I11*'PAYMENT RATIO_RAW'!G$5 -> 0 | R11: =+P11-Q11 -> 0 | W11: =+$I11*'PAYMENT RATIO_RAW'!N$5 -> 0 | Y11: =+W11-X11 -> 0 | AA11: 45920 | AB11: 45915 | AC11: =+IFERROR(AD11/$I11,"-") -> 0.19489559 | AD11: =+'PAYMENT RATIO_RAW'!$U$60*$D11*1050000000/1000*1.1 -> 2.3090298e+08 | AE11: 231000000 | AF11: =+AD11-AE11 -> -97020 | AG11: 선급금20% | AH11: =+EDATE(AO11,0) -> 45950 | AI11: 45980 | AJ11: =+IFERROR(AK11/$I11,"-") -> 0 | AK11: =+'PAYMENT RATIO_RAW'!AB$60*$I11 -> 0 | AL11: 231000000 | AM11: =+AK11-AL11 -> -231000000 | AO11: =+EDATE(AV11,0)-10 -> 45950 | AQ11: =+IFERROR(AR11/$I11,"-") -> 0.51276102 | AR11: =+'PAYMENT RATIO_RAW'!AI$60*$D11*1050000000/1000*1.1+27500000*D11/1000*1.1 -> 607494745 | AT11: =+AR11-AS11 -> 607494745 | AV11: =+EDATE(BC11,-1) -> 45960 | AX11: =+IFERROR(AY11/$I11,"-") -> 0 | AY11: =+'PAYMENT RATIO_RAW'!AP$60*$I11 -> 0 | BA11: =+AY11-AZ11 -> 0 | BC11: =+EDATE(BJ11,-1) -> 45991 | BE11: =+IFERROR(BF11/$I11,"-") -> 0.24361949 | BF11: =+'PAYMENT RATIO_RAW'!AW$60*$D11*1050000000/1000*1.1 -> 288628725 | BH11: =+BF11-BG11 -> 288628725 | BJ11: 46022 | BL11: =+IFERROR(BM11/$I11,"-") -> 0.048723898 | BM11: =+'PAYMENT RATIO_RAW'!BD$60*$D11*1050000000/1000*1.1 -> 57725745 | BO11: =+BM11-BN11 -> 57725745 | BR11: =+P11+W11+AD11+AK11+AR11+AY11+BF11+BM11=I11 -> TRUE | BS11: =+Q11+X11+AE11+AS11+AZ11+BG11+BN11=K11 -> TRUE | BU11: =+D11*1050000000/1000*1.1+D11*27500000/1000*1.1 -> 1184752195 | BX11: 27500000
F12: DEVEX | G12: =+'PAYMENT RATIO_RAW'!F$6*'GM Batch1'!$D$11/1000 -> 549769000 | I12: =SUM(G12:H12) -> 549769000 | J12: =+IFERROR(K12/I12,"-") -> 0.66947518 | K12: =+IFERROR(Q12+X12+AE12+AS12+AZ12+BG12+BN12,"-") -> 368056700 | L12: =+I12-K12 -> 181712300 | M12: 45450 | N12: 45450 | O12: =+IFERROR(P12/$I12,"-") -> 0.55 | P12: =+$I12*'PAYMENT RATIO_RAW'!G$6 -> 302372950 | Q12: 302372950 | R12: =+P12-Q12 -> 0 | T12: 45456 | U12: 45456 | V12: =+IFERROR(W12/$I12,"-") -> 0.11947518 | W12: =+$I12*'PAYMENT RATIO_RAW'!N$6-16781600 -> 65683750 | X12: 65683750 | Y12: =+W12-X12 -> 0 | AA12: 45950 | AC12: =+IFERROR(AD12/$I12,"-") -> 0.03052482 | AD12: =+$I12*'PAYMENT RATIO_RAW'!U$6+16781600 -> 16781600 | AF12: =+AD12-AE12 -> 16781600 | AJ12: =+IFERROR(AK12/$I12,"-") -> 0 | AK12: =+$I12*'PAYMENT RATIO_RAW'!AB35 -> 0 | AM12: =+AK12-AL12 -> 0 | AR12: =+$I12*'PAYMENT RATIO_RAW'!AI$6 -> 0 | AT12: =+AR12-AS12 -> 0 | AY12: =+$I12*'PAYMENT RATIO_RAW'!AP$6 -> 0 | BA12: =+AY12-AZ12 -> 0 | BE12: =+IFERROR(BF12/$I12,"-") -> 0 | BF12: =+$I12*'PAYMENT RATIO_RAW'!AW$6 -> 0 | BH12: =+BF12-BG12 -> 0 | BJ12: =+BJ11 -> 46022 | BL12: =+IFERROR(BM12/$I12,"-") -> 0.3 | BM12: =+$I12*'PAYMENT RATIO_RAW'!BD$6 -> 164930700 | BO12: =+BM12-BN12 -> 164930700 | BR12: =+BM12+BF12+AY12+AR12+AD12+W12+P12=I12 -> TRUE | BS12: =+Q12+X12+AE12+AS12+AZ12+BG12+BN12=K12 -> TRUE | BT12: =+BF12+BF14+AY12+AY14+AR12+AR14+AD12+AD14+W12+W14+P12+P14+BM12+BM14=('PAYMENT RATIO_RAW'!$F$6+'PAYMENT RATIO_RAW'!$F$8)*D11/1000 -> TRUE | BU12: =+$D11*1050000000/1000*1.1 -> 1154514900 | BW12: =+$BU12*20%=AD11 -> TRUE | BX12: =+$BU12*50%+BX11*D11/1000*1.1=AR11 -> TRUE | BY12: =+$BU12*25%=BF11 -> TRUE | BZ12: =+$BU12*5%=BM11 -> TRUE
F13: Land Purchase | G13: =+'PAYMENT RATIO_RAW'!F$7*'GM Batch1'!$D$11/1000 -> 0 | H13: =+G13*10% -> 0 | I13: =SUM(G13:H13) -> 0 | J13: =+IFERROR(K13/I13,"-") -> - | K13: =+IFERROR(Q13+X13+AE13+AS13+AZ13+BG13+BN13,"-") -> 0 | L13: =+I13-K13 -> 0 | O13: =+IFERROR(P13/$I13,"-") -> - | P13: =+$I13*'PAYMENT RATIO_RAW'!G$7 -> 0 | R13: =+P13-Q13 -> 0 | V13: =+IFERROR(W13/$I13,"-") -> - | W13: =+$I13*'PAYMENT RATIO_RAW'!N$7 -> 0 | Y13: =+W13-X13 -> 0 | AC13: =+IFERROR(AD13/$I13,"-") -> - | AD13: =+$I13*'PAYMENT RATIO_RAW'!U$7 -> 0 | AF13: =+AD13-AE13 -> 0 | AJ13: =+IFERROR(AK13/$I13,"-") -> - | AK13: =+$I13*'PAYMENT RATIO_RAW'!AB36 -> 0 | AM13: =+AK13-AL13 -> 0 | AR13: =+$I13*'PAYMENT RATIO_RAW'!AI$7 -> 0 | AT13: =+AR13-AS13 -> 0 | AY13: =+$I13*'PAYMENT RATIO_RAW'!AP$7 -> 0 | BA13: =+AY13-AZ13 -> 0 | BE13: =+IFERROR(BF13/$I13,"-") -> - | BF13: =+$I13*'PAYMENT RATIO_RAW'!AW$7 -> 0 | BH13: =+BF13-BG13 -> 0 | BL13: =+IFERROR(BM13/$I13,"-") -> - | BM13: =+$I13*'PAYMENT RATIO_RAW'!BD$7 -> 0 | BO13: =+BM13-BN13 -> 0 | BR13: =+P13+W13+AD13+AR13+AY13+BF13+BM13=I13 -> TRUE | BS13: =+Q13+X13+AE13+AS13+AZ13+BG13+BN13=K13 -> TRUE
F14: Brokerage+Finder fee | G14: =+'PAYMENT RATIO_RAW'!F$8*'GM Batch1'!$D$11/1000 -> 0 | H14: =+G14*10% -> 0 | I14: =SUM(G14:H14) -> 0 | J14: =+IFERROR(K14/I14,"-") -> - | K14: =+IFERROR(Q14+X14+AE14+AS14+AZ14+BG14+BN14,"-") -> 0 | L14: =+I14-K14 -> 0 | O14: =+IFERROR(P14/$I14,"-") -> - | P14: =+$I14*'PAYMENT RATIO_RAW'!G$8 -> 0 | R14: =+P14-Q14 -> 0 | V14: =+IFERROR(W14/$I14,"-") -> - | W14: =+$I14*'PAYMENT RATIO_RAW'!N$8 -> 0 | Y14: =+W14-X14 -> 0 | AC14: =+IFERROR(AD14/$I14,"-") -> - | AD14: =+$I14*'PAYMENT RATIO_RAW'!U$8 -> 0 | AF14: =+AD14-AE14 -> 0 | AJ14: =+IFERROR(AK14/$I14,"-") -> - | AK14: =+$I14*'PAYMENT RATIO_RAW'!AB36 -> 0 | AM14: =+AK14-AL14 -> 0 | AR14: =+$I14*'PAYMENT RATIO_RAW'!AI$8 -> 0 | AT14: =+AR14-AS14 -> 0 | AY14: =+$I14*'PAYMENT RATIO_RAW'!AP$8 -> 0 | BA14: =+AY14-AZ14 -> 0 | BE14: =+IFERROR(BF14/$I14,"-") -> - | BF14: =+$I14*'PAYMENT RATIO_RAW'!AW$8 -> 0 | BH14: =+BF14-BG14 -> 0 | BL14: =+IFERROR(BM14/$I14,"-") -> - | BM14: =+$I14*'PAYMENT RATIO_RAW'!BD$8 -> 0 | BO14: =+BM14-BN14 -> 0 | BR14: =+P14+W14+AD14+AR14+AY14+BF14+BM14=I14 -> TRUE | BS14: =+Q14+X14+AE14+AS14+AZ14+BG14+BN14=K14 -> TRUE
F15: Pre-payment Amount | G15: =+'PAYMENT RATIO_RAW'!F$9*'GM Batch1'!$D$11/1000 -> 0 | H15: =+G15*10% -> 0 | I15: =SUM(G15:H15) -> 0 | J15: =+IFERROR(K15/I15,"-") -> - | K15: =+IFERROR(Q15+X15+AE15+AS15+AZ15+BG15+BN15,"-") -> 0 | L15: =+I15-K15 -> 0 | P15: =+$I15*'PAYMENT RATIO_RAW'!G$9 -> 0 | R15: =+P15-Q15 -> 0 | W15: =+$I15*'PAYMENT RATIO_RAW'!N$9 -> 0 | Y15: =+W15-X15 -> 0 | AD15: =+$I15*'PAYMENT RATIO_RAW'!U$9 -> 0 | AF15: =+AD15-AE15 -> 0 | AR15: =+$I15*'PAYMENT RATIO_RAW'!AI$9 -> 0 | AY15: =+$I15*'PAYMENT RATIO_RAW'!AP$9 -> 0 | BE15: =+IFERROR(BF15/$I15,"-") -> - | BF15: =+$I15*'PAYMENT RATIO_RAW'!AW$9 -> 0 | BH15: =+BF15-BG15 -> 0 | BL15: =+IFERROR(BM15/$I15,"-") -> - | BM15: =+$I15*'PAYMENT RATIO_RAW'!BD$9 -> 0 | BO15: =+BM15-BN15 -> 0 | BR15: =+P15+W15+AD15+AR15+AY15+BF15+BM15=I15 -> TRUE | BS15: =+Q15+X15+AE15+AS15+AZ15+BG15+BN15=K15 -> TRUE
F16: Total | G16: =SUM(G11:G15) -> 1626816450 | H16: =SUM(H11:H15) -> 107704745 | I16: =SUM(I11:I15) -> 1734521195 | J16: =+IFERROR(K16/I16,"-") -> 0.34537295 | K16: =SUM(K11:K15) -> 599056700 | L16: =SUM(L11:L15) -> 1135464495 | O16: =+IFERROR(P16/$I16,"-") -> 0.17432647 | P16: =SUM(P11:P15) -> 302372950 | Q16: =SUM(Q11:Q15) -> 302372950 | R16: =+P16-Q16 -> 0 | V16: =+IFERROR(W16/$I16,"-") -> 0.03786852 | W16: =SUM(W11:W15) -> 65683750 | X16: =SUM(X11:X15) -> 65683750 | Y16: =+W16-X16 -> 0 | AC16: =+IFERROR(AD16/$I16,"-") -> 0.14279709 | AD16: =SUM(AD11:AD15) -> 2.4768458e+08 | AE16: =SUM(AE11:AE15) -> 231000000 | AF16: =+AD16-AE16 -> 16684580 | AJ16: =+IFERROR(AK16/$I16,"-") -> 0 | AK16: =SUM(AK11:AK15) -> 0 | AL16: =SUM(AL11:AL15) -> 231000000 | AM16: =+AK16-AL16 -> -231000000 | AQ16: =+IFERROR(AR16/$I16,"-") -> 0.35023772 | AR16: =SUM(AR11:AR15) -> 607494745 | AS16: =SUM(AS11:AS15) -> 0 | AT16: =+AR16-AS16 -> 607494745 | AX16: =+IFERROR(AY16/$I16,"-") -> 0 | AY16: =SUM(AY11:AY15) -> 0 | AZ16: =SUM(AZ11:AZ15) -> 0 | BA16: =+AY16-AZ16 -> 0 | BE16: =+IFERROR(BF16/$I16,"-") -> 0.16640254 | BF16: =SUM(BF11:BF15) -> 288628725 | BG16: =SUM(BG11:BG15) -> 0 | BH16: =+BF16-BG16 -> 288628725 | BL16: =+IFERROR(BM16/$I16,"-") -> 0.12836767 | BM16: =SUM(BM11:BM15) -> 222656445 | BN16: =SUM(BN11:BN15) -> 0 | BO16: =+BM16-BN16 -> 222656445 | BU16: =+BX11*D11/1000*1.1 -> 30237295
B17: 2 | C17: YJ NANSAN 2 | D17: 999.58 | E17: Solar city | F17: CAPEX | G17: =+'PAYMENT RATIO_RAW'!F$5*$D$17/1000+27500000*D$17/1000 -> 1077047450 | H17: =+G17*10% -> 107704745 | I17: =SUM(G17:H17) -> 1184752195 | J17: =+IFERROR(K17/I17,"-") -> 0.19497748 | K17: =+IFERROR(Q17+X17+AE17+AS17+AZ17+BG17+BN17,"-") -> 231000000 | L17: =+I17-K17 -> 953752195 | P17: =+$I17*'PAYMENT RATIO_RAW'!G$5 -> 0 | R17: =+P17-Q17 -> 0 | W17: =+$I17*'PAYMENT RATIO_RAW'!N$5 -> 0 | Y17: =+W17-X17 -> 0 | AA17: =+$AA$11 -> 45920 | AB17: 45915 | AC17: =+IFERROR(AD17/$I17,"-") -> 0.19489559 | AD17: =+'PAYMENT RATIO_RAW'!$U$60*$D17*1050000000/1000*1.1 -> 2.3090298e+08 | AE17: 231000000 | AF17: =+AD17-AE17 -> -97020 | AG17: 선급금20% | AH17: =+EDATE(AO17,0) -> 45950 | AI17: 45980 | AJ17: =+IFERROR(AK17/$I17,"-") -> 0 | AK17: =+'PAYMENT RATIO_RAW'!AB$60*$I17 -> 0 | AL17: 231000000 | AM17: =+AK17-AL17 -> -231000000 | AO17: =+EDATE(AV17,0)-10 -> 45950 | AQ17: =+IFERROR(AR17/$I17,"-") -> 0.51276102 | AR17: =+'PAYMENT RATIO_RAW'!AI$60*$D17*1050000000/1000*1.1+27500000*$D17/1000*1.1 -> 607494745 | AT17: =+AR17-AS17 -> 607494745 | AV17: =+EDATE(BC17,-1) -> 45960 | AX17: =+IFERROR(AY17/$I17,"-") -> 0 | AY17: =+'PAYMENT RATIO_RAW'!AP$60*$I17 -> 0 | BA17: =+AY17-AZ17 -> 0 | BC17: =+EDATE(BJ17,-1) -> 45991 | BE17: =+IFERROR(BF17/$I17,"-") -> 0.24361949 | BF17: =+'PAYMENT RATIO_RAW'!AW$60*$D17*1050000000/1000*1.1 -> 288628725 | BH17: =+BF17-BG17 -> 288628725 | BJ17: 46022 | BL17: =+IFERROR(BM17/$I17,"-") -> 0.048723898 | BM17: =+'PAYMENT RATIO_RAW'!BD$60*$D17*1050000000/1000*1.1 -> 57725745 | BO17: =+BM17-BN17 -> 57725745 | BR17: =+P17+W17+AD17+AK17+AR17+AY17+BF17+BM17=I17 -> TRUE | BS17: =+Q17+X17+AE17+AS17+AZ17+BG17+BN17=K17 -> TRUE
F18: DEVEX | G18: =+'PAYMENT RATIO_RAW'!F$6*'GM Batch1'!$D$17/1000 -> 549769000 | I18: =SUM(G18:H18) -> 549769000 | J18: =+IFERROR(K18/I18,"-") -> 0.66947518 | K18: =+IFERROR(Q18+X18+AE18+AS18+AZ18+BG18+BN18,"-") -> 368056700 | L18: =+I18-K18 -> 181712300 | M18: 45450 | N18: 45450 | O18: =+IFERROR(P18/$I18,"-") -> 0.55 | P18: =+$I18*'PAYMENT RATIO_RAW'!G$6 -> 302372950 | Q18: 302372950 | R18: =+P18-Q18 -> 0 | T18: 45456 | U18: 45456 | V18: =+IFERROR(W18/$I18,"-") -> 0.11947518 | W18: =+$I18*'PAYMENT RATIO_RAW'!N$6-16781600 -> 65683750 | X18: 65683750 | Y18: =+W18-X18 -> 0 | AA18: 45950 | AC18: =+IFERROR(AD18/$I18,"-") -> 0.03052482 | AD18: =+$I18*'PAYMENT RATIO_RAW'!U$6+16781600 -> 16781600 | AF18: =+AD18-AE18 -> 16781600 | AJ18: =+IFERROR(AK18/$I18,"-") -> 0 | AK18: =+$I18*'PAYMENT RATIO_RAW'!AB40 -> 0 | AM18: =+AK18-AL18 -> 0 | AR18: =+$I18*'PAYMENT RATIO_RAW'!AI$6 -> 0 | AT18: =+AR18-AS18 -> 0 | AY18: =+$I18*'PAYMENT RATIO_RAW'!AP$6 -> 0 | BA18: =+AY18-AZ18 -> 0 | BE18: =+IFERROR(BF18/$I18,"-") -> 0 | BF18: =+$I18*'PAYMENT RATIO_RAW'!AW$6 -> 0 | BH18: =+BF18-BG18 -> 0 | BJ18: =+BJ17 -> 46022 | BL18: =+IFERROR(BM18/$I18,"-") -> 0.3 | BM18: =+$I18*'PAYMENT RATIO_RAW'!BD$6 -> 164930700 | BO18: =+BM18-BN18 -> 164930700 | BR18: =+P18+W18+AD18+AR18+AY18+BF18+BM18=I18 -> TRUE | BS18: =+Q18+X18+AE18+AS18+AZ18+BG18+BN18=K18 -> TRUE | BT18: =+BF18+BF20+AY18+AY20+AR18+AR20+AD18+AD20+W18+W20+P18+P20+BM18+BM20=('PAYMENT RATIO_RAW'!$F$6+'PAYMENT RATIO_RAW'!$F$8)*D17/1000 -> TRUE
F19: Land Purchase | G19: =+'PAYMENT RATIO_RAW'!F$7*'GM Batch1'!$D$17/1000 -> 0 | H19: =+G19*10% -> 0 | I19: =SUM(G19:H19) -> 0 | J19: =+IFERROR(K19/I19,"-") -> - | K19: =+IFERROR(Q19+X19+AE19+AS19+AZ19+BG19+BN19,"-") -> 0 | L19: =+I19-K19 -> 0 | O19: =+IFERROR(P19/$I19,"-") -> - | P19: =+$I19*'PAYMENT RATIO_RAW'!G$7 -> 0 | R19: =+P19-Q19 -> 0 | V19: =+IFERROR(W19/$I19,"-") -> - | W19: =+$I19*'PAYMENT RATIO_RAW'!N$7 -> 0 | Y19: =+W19-X19 -> 0 | AC19: =+IFERROR(AD19/$I19,"-") -> - | AD19: =+$I19*'PAYMENT RATIO_RAW'!U$7 -> 0 | AF19: =+AD19-AE19 -> 0 | AJ19: =+IFERROR(AK19/$I19,"-") -> - | AK19: =+$I19*'PAYMENT RATIO_RAW'!AB40 -> 0 | AM19: =+AK19-AL19 -> 0 | AR19: =+$I19*'PAYMENT RATIO_RAW'!AI$7 -> 0 | AT19: =+AR19-AS19 -> 0 | AY19: =+$I19*'PAYMENT RATIO_RAW'!AP$7 -> 0 | BA19: =+AY19-AZ19 -> 0 | BE19: =+IFERROR(BF19/$I19,"-") -> - | BF19: =+$I19*'PAYMENT RATIO_RAW'!AW$7 -> 0 | BH19: =+BF19-BG19 -> 0 | BL19: =+IFERROR(BM19/$I19,"-") -> - | BM19: =+$I19*'PAYMENT RATIO_RAW'!BD$7 -> 0 | BO19: =+BM19-BN19 -> 0 | BR19: =+P19+W19+AD19+AR19+AY19+BF19+BM19=I19 -> TRUE | BS19: =+Q19+X19+AE19+AS19+AZ19+BG19+BN19=K19 -> TRUE
F20: Brokerage+Finder fee | G20: =+'PAYMENT RATIO_RAW'!F$8*'GM Batch1'!$D$17/1000 -> 0 | H20: =+G20*10% -> 0 | I20: =SUM(G20:H20) -> 0 | J20: =+IFERROR(K20/I20,"-") -> - | K20: =+IFERROR(Q20+X20+AE20+AS20+AZ20+BG20+BN20,"-") -> 0 | L20: =+I20-K20 -> 0 | O20: =+IFERROR(P20/$I20,"-") -> - | P20: =+$I20*'PAYMENT RATIO_RAW'!G$8 -> 0 | R20: =+P20-Q20 -> 0 | V20: =+IFERROR(W20/$I20,"-") -> - | W20: =+$I20*'PAYMENT RATIO_RAW'!N$8 -> 0 | Y20: =+W20-X20 -> 0 | AC20: =+IFERROR(AD20/$I20,"-") -> - | AD20: =+$I20*'PAYMENT RATIO_RAW'!U$8 -> 0 | AF20: =+AD20-AE20 -> 0 | AJ20: =+IFERROR(AK20/$I20,"-") -> - | AK20: =+$I20*'PAYMENT RATIO_RAW'!AB41 -> 0 | AM20: =+AK20-AL20 -> 0 | AR20: =+$I20*'PAYMENT RATIO_RAW'!AI$8 -> 0 | AT20: =+AR20-AS20 -> 0 | AY20: =+$I20*'PAYMENT RATIO_RAW'!AP$8 -> 0 | BA20: =+AY20-AZ20 -> 0 | BE20: =+IFERROR(BF20/$I20,"-") -> - | BF20: =+$I20*'PAYMENT RATIO_RAW'!AW$8 -> 0 | BH20: =+BF20-BG20 -> 0 | BL20: =+IFERROR(BM20/$I20,"-") -> - | BM20: =+$I20*'PAYMENT RATIO_RAW'!BD$8 -> 0 | BO20: =+BM20-BN20 -> 0 | BR20: =+P20+W20+AD20+AR20+AY20+BF20+BM20=I20 -> TRUE | BS20: =+Q20+X20+AE20+AS20+AZ20+BG20+BN20=K20 -> TRUE
F21: Pre-payment Amount | G21: =+'PAYMENT RATIO_RAW'!F$9*'GM Batch1'!$D$17/1000 -> 0 | H21: =+G21*0.1 -> 0 | I21: =SUM(G21:H21) -> 0 | J21: =+IFERROR(K21/I21,"-") -> - | K21: =+IFERROR(Q21+X21+AE21+AS21+AZ21+BG21+BN21,"-") -> 0 | L21: =+I21-K21 -> 0 | P21: =+$I21*'PAYMENT RATIO_RAW'!G$9 -> 0 | R21: =+P21-Q21 -> 0 | W21: =+$I21*'PAYMENT RATIO_RAW'!N$9 -> 0 | Y21: =+W21-X21 -> 0 | AD21: =+$I21*'PAYMENT RATIO_RAW'!U$9 -> 0 | AF21: =+AD21-AE21 -> 0 | AR21: =+$I21*'PAYMENT RATIO_RAW'!AI$9 -> 0 | AY21: =+$I21*'PAYMENT RATIO_RAW'!AP$9 -> 0 | BE21: =+IFERROR(BF21/$I21,"-") -> - | BF21: =+$I21*'PAYMENT RATIO_RAW'!AW$9 -> 0 | BH21: =+BF21-BG21 -> 0 | BL21: =+IFERROR(BM21/$I21,"-") -> - | BM21: =+$I21*'PAYMENT RATIO_RAW'!BD$9 -> 0 | BO21: =+BM21-BN21 -> 0 | BR21: =+P21+W21+AD21+AR21+AY21+BF21+BM21=I21 -> TRUE | BS21: =+Q21+X21+AE21+AS21+AZ21+BG21+BN21=K21 -> TRUE
F22: Total | G22: =SUM(G17:G21) -> 1626816450 | H22: =SUM(H17:H21) -> 107704745 | I22: =SUM(I17:I21) -> 1734521195 | J22: =+IFERROR(K22/I22,"-") -> 0.34537295 | K22: =SUM(K17:K21) -> 599056700 | L22: =SUM(L17:L21) -> 1135464495 | O22: =+IFERROR(P22/$I22,"-") -> 0.17432647 | P22: =SUM(P17:P21) -> 302372950 | Q22: =SUM(Q17:Q21) -> 302372950 | R22: =+P22-Q22 -> 0 | V22: =+IFERROR(W22/$I22,"-") -> 0.03786852 | W22: =SUM(W17:W21) -> 65683750 | X22: =SUM(X17:X21) -> 65683750 | Y22: =+W22-X22 -> 0 | AC22: =+IFERROR(AD22/$I22,"-") -> 0.14279709 | AD22: =SUM(AD17:AD21) -> 2.4768458e+08 | AE22: =SUM(AE17:AE21) -> 231000000 | AF22: =+AD22-AE22 -> 16684580 | AJ22: =+IFERROR(AK22/$I22,"-") -> 0 | AK22: =SUM(AK17:AK21) -> 0 | AL22: =SUM(AL17:AL21) -> 231000000 | AM22: =+AK22-AL22 -> -231000000 | AQ22: =+IFERROR(AR22/$I22,"-") -> 0.35023772 | AR22: =SUM(AR17:AR21) -> 607494745 | AS22: =SUM(AS17:AS21) -> 0 | AT22: =+AR22-AS22 -> 607494745 | AX22: =+IFERROR(AY22/$I22,"-") -> 0 | AY22: =SUM(AY17:AY21) -> 0 | AZ22: =SUM(AZ17:AZ21) -> 0 | BA22: =+AY22-AZ22 -> 0 | BE22: =+IFERROR(BF22/$I22,"-") -> 0.16640254 | BF22: =SUM(BF17:BF21) -> 288628725 | BG22: =SUM(BG17:BG21) -> 0 | BH22: =+BF22-BG22 -> 288628725 | BL22: =+IFERROR(BM22/$I22,"-") -> 0.12836767 | BM22: =SUM(BM17:BM21) -> 222656445 | BN22: =SUM(BN17:BN21) -> 0 | BO22: =+BM22-BN22 -> 222656445
B23: 3 | C23: YJ GASI 1 | D23: 999.6 | E23: Solar city | F23: CAPEX | G23: =+'PAYMENT RATIO_RAW'!F$5*$D$23/1000+27500000*D$23/1000 -> 1077069000 | H23: =+G23*10% -> 107706900 | I23: =SUM(G23:H23) -> 1184775900 | J23: =+IFERROR(K23/I23,"-") -> 0.19497358 | K23: =+IFERROR(Q23+X23+AE23+AS23+AZ23+BG23+BN23,"-") -> 231000000 | L23: =+I23-K23 -> 953775900 | P23: =+$I23*'PAYMENT RATIO_RAW'!G$5 -> 0 | R23: =+P23-Q23 -> 0 | W23: =+$I23*'PAYMENT RATIO_RAW'!N$5 -> 0 | Y23: =+W23-X23 -> 0 | AA23: =+$AA$11 -> 45920 | AB23: 45915 | AC23: =+IFERROR(AD23/$I23,"-") -> 0.19489559 | AD23: =+'PAYMENT RATIO_RAW'!$U$60*$D23*1050000000/1000*1.1 -> 2.309076e+08 | AE23: 231000000 | AF23: =+AD23-AE23 -> -92400 | AG23: 선급금20% | AH23: =+EDATE(AO23,0) -> 45950 | AI23: 45980 | AJ23: =+IFERROR(AK23/$I23,"-") -> 0 | AK23: =+'PAYMENT RATIO_RAW'!AB$60*$I23 -> 0 | AL23: 231000000 | AM23: =+AK23-AL23 -> -231000000 | AO23: =+EDATE(AV23,0)-10 -> 45950 | AQ23: =+IFERROR(AR23/$I23,"-") -> 0.51276102 | AR23: =+'PAYMENT RATIO_RAW'!AI$60*$D23*1050000000/1000*1.1+27500000*$D23/1000*1.1 -> 607506900 | AT23: =+AR23-AS23 -> 607506900 | AV23: =+EDATE(BC23,-1) -> 45960 | AX23: =+IFERROR(AY23/$I23,"-") -> 0 | AY23: =+'PAYMENT RATIO_RAW'!AP$60*$I23 -> 0 | BA23: =+AY23-AZ23 -> 0 | BC23: =+EDATE(BJ23,-1) -> 45991 | BE23: =+IFERROR(BF23/$I23,"-") -> 0.24361949 | BF23: =+'PAYMENT RATIO_RAW'!AW$60*$D23*1050000000/1000*1.1 -> 288634500 | BH23: =+BF23-BG23 -> 288634500 | BJ23: 46022 | BL23: =+IFERROR(BM23/$I23,"-") -> 0.048723898 | BM23: =+'PAYMENT RATIO_RAW'!BD$60*$D23*1050000000/1000*1.1 -> 57726900 | BO23: =+BM23-BN23 -> 57726900 | BR23: =+P23+W23+AD23+AK23+AR23+AY23+BF23+BM23=I23 -> TRUE | BS23: =+Q23+X23+AE23+AS23+AZ23+BG23+BN23=K23 -> TRUE
F24: DEVEX | G24: =+'PAYMENT RATIO_RAW'!F$6*'GM Batch1'!$D$23/1000 -> 549780000 | I24: =SUM(G24:H24) -> 549780000 | J24: =+IFERROR(K24/I24,"-") -> 0.66947279 | K24: =+IFERROR(Q24+X24+AE24+AS24+AZ24+BG24+BN24,"-") -> 368062750 | L24: =+I24-K24 -> 181717250 | M24: 45450 | N24: 45450 | O24: =+IFERROR(P24/$I24,"-") -> 0.55 | P24: =+$I24*'PAYMENT RATIO_RAW'!G$6 -> 302379000 | Q24: 302379000 | R24: =+P24-Q24 -> 0 | T24: 45456 | U24: 45456 | V24: =+IFERROR(W24/$I24,"-") -> 0.11947279 | W24: =+$I24*'PAYMENT RATIO_RAW'!N$6-16783250 -> 65683750 | X24: 65683750 | Y24: =+W24-X24 -> 0 | AA24: 45950 | AC24: =+IFERROR(AD24/$I24,"-") -> 0.030527211 | AD24: =+$I24*'PAYMENT RATIO_RAW'!U$6+16783250 -> 16783250 | AF24: =+AD24-AE24 -> 16783250 | AJ24: =+IFERROR(AK24/$I24,"-") -> 0 | AK24: =+$I24*'PAYMENT RATIO_RAW'!AB44 -> 0 | AM24: =+AK24-AL24 -> 0 | AR24: =+$I24*'PAYMENT RATIO_RAW'!AI$6 -> 0 | AT24: =+AR24-AS24 -> 0 | AY24: =+$I24*'PAYMENT RATIO_RAW'!AP$6 -> 0 | BA24: =+AY24-AZ24 -> 0 | BE24: =+IFERROR(BF24/$I24,"-") -> 0 | BF24: =+$I24*'PAYMENT RATIO_RAW'!AW$6 -> 0 | BH24: =+BF24-BG24 -> 0 | BJ24: =+BJ23 -> 46022 | BL24: =+IFERROR(BM24/$I24,"-") -> 0.3 | BM24: =+$I24*'PAYMENT RATIO_RAW'!BD$6 -> 164934000 | BO24: =+BM24-BN24 -> 164934000 | BR24: =+P24+W24+AD24+AR24+AY24+BF24+BM24=I24 -> TRUE | BS24: =+Q24+X24+AE24+AS24+AZ24+BG24+BN24=K24 -> TRUE | BT24: =+BF24+BF26+AY24+AY26+AR24+AR26+AD24+AD26+W24+W26+P24+P26+BM24+BM26=('PAYMENT RATIO_RAW'!$F$6+'PAYMENT RATIO_RAW'!$F$8)*D23/1000 -> TRUE
F25: Land Purchase | G25: =+'PAYMENT RATIO_RAW'!F$7*'GM Batch1'!$D$23/1000 -> 0 | I25: =SUM(G25:H25) -> 0 | J25: =+IFERROR(K25/I25,"-") -> - | K25: =+IFERROR(Q25+X25+AE25+AS25+AZ25+BG25+BN25,"-") -> 0 | L25: =+I25-K25 -> 0 | O25: =+IFERROR(P25/$I25,"-") -> - | P25: =+$I25*'PAYMENT RATIO_RAW'!G$7 -> 0 | R25: =+P25-Q25 -> 0 | V25: =+IFERROR(W25/$I25,"-") -> - | W25: =+$I25*'PAYMENT RATIO_RAW'!N$7 -> 0 | Y25: =+W25-X25 -> 0 | AC25: =+IFERROR(AD25/$I25,"-") -> - | AD25: =+$I25*'PAYMENT RATIO_RAW'!U$7 -> 0 | AF25: =+AD25-AE25 -> 0 | AJ25: =+IFERROR(AK25/$I25,"-") -> - | AK25: =+$I25*'PAYMENT RATIO_RAW'!AB45 -> 0 | AM25: =+AK25-AL25 -> 0 | AR25: =+$I25*'PAYMENT RATIO_RAW'!AI$7 -> 0 | AT25: =+AR25-AS25 -> 0 | AY25: =+$I25*'PAYMENT RATIO_RAW'!AP$7 -> 0 | BA25: =+AY25-AZ25 -> 0 | BE25: =+IFERROR(BF25/$I25,"-") -> - | BF25: =+$I25*'PAYMENT RATIO_RAW'!AW$7 -> 0 | BH25: =+BF25-BG25 -> 0 | BL25: =+IFERROR(BM25/$I25,"-") -> - | BM25: =+$I25*'PAYMENT RATIO_RAW'!BD$7 -> 0 | BO25: =+BM25-BN25 -> 0 | BR25: =+P25+W25+AD25+AR25+AY25+BF25+BM25=I25 -> TRUE | BS25: =+Q25+X25+AE25+AS25+AZ25+BG25+BN25=K25 -> TRUE
F26: Brokerage+Finder fee | G26: =+'PAYMENT RATIO_RAW'!F$8*'GM Batch1'!$D$23/1000 -> 0 | H26: =+G26*10% -> 0 | I26: =SUM(G26:H26) -> 0 | J26: =+IFERROR(K26/I26,"-") -> - | K26: =+IFERROR(Q26+X26+AE26+AS26+AZ26+BG26+BN26,"-") -> 0 | L26: =+I26-K26 -> 0 | O26: =+IFERROR(P26/$I26,"-") -> - | P26: =+$I26*'PAYMENT RATIO_RAW'!G$8 -> 0 | R26: =+P26-Q26 -> 0 | V26: =+IFERROR(W26/$I26,"-") -> - | W26: =+$I26*'PAYMENT RATIO_RAW'!N$8 -> 0 | Y26: =+W26-X26 -> 0 | AC26: =+IFERROR(AD26/$I26,"-") -> - | AD26: =+$I26*'PAYMENT RATIO_RAW'!U$8 -> 0 | AF26: =+AD26-AE26 -> 0 | AJ26: =+IFERROR(AK26/$I26,"-") -> - | AK26: =+$I26*'PAYMENT RATIO_RAW'!AB46 -> 0 | AM26: =+AK26-AL26 -> 0 | AR26: =+$I26*'PAYMENT RATIO_RAW'!AI$8 -> 0 | AT26: =+AR26-AS26 -> 0 | AY26: =+$I26*'PAYMENT RATIO_RAW'!AP$8 -> 0 | BA26: =+AY26-AZ26 -> 0 | BE26: =+IFERROR(BF26/$I26,"-") -> - | BF26: =+$I26*'PAYMENT RATIO_RAW'!AW$8 -> 0 | BH26: =+BF26-BG26 -> 0 | BL26: =+IFERROR(BM26/$I26,"-") -> - | BM26: =+$I26*'PAYMENT RATIO_RAW'!BD$8 -> 0 | BO26: =+BM26-BN26 -> 0 | BR26: =+P26+W26+AD26+AR26+AY26+BF26+BM26=I26 -> TRUE | BS26: =+Q26+X26+AE26+AS26+AZ26+BG26+BN26=K26 -> TRUE
F27: Pre-payment Amount | G27: =+'PAYMENT RATIO_RAW'!F$9*'GM Batch1'!$D$23/1000 -> 0 | H27: =+G27*0.1 -> 0 | I27: =SUM(G27:H27) -> 0 | J27: =+IFERROR(K27/I27,"-") -> - | K27: =+IFERROR(Q27+X27+AE27+AS27+AZ27+BG27+BN27,"-") -> 0 | L27: =+I27-K27 -> 0 | P27: =+$I27*'PAYMENT RATIO_RAW'!G$9 -> 0 | R27: =+P27-Q27 -> 0 | W27: =+$I27*'PAYMENT RATIO_RAW'!N$9 -> 0 | Y27: =+W27-X27 -> 0 | AD27: =+$I27*'PAYMENT RATIO_RAW'!U$9 -> 0 | AF27: =+AD27-AE27 -> 0 | AR27: =+$I27*'PAYMENT RATIO_RAW'!AI$9 -> 0 | AY27: =+$I27*'PAYMENT RATIO_RAW'!AP$9 -> 0 | BE27: =+IFERROR(BF27/$I27,"-") -> - | BF27: =+$I27*'PAYMENT RATIO_RAW'!AW$9 -> 0 | BH27: =+BF27-BG27 -> 0 | BL27: =+IFERROR(BM27/$I27,"-") -> - | BM27: =+$I27*'PAYMENT RATIO_RAW'!BD$9 -> 0 | BO27: =+BM27-BN27 -> 0 | BR27: =+P27+W27+AD27+AR27+AY27+BF27+BM27=I27 -> TRUE | BS27: =+Q27+X27+AE27+AS27+AZ27+BG27+BN27=K27 -> TRUE
F28: Total | G28: =SUM(G23:G27) -> 1626849000 | H28: =SUM(H23:H27) -> 107706900 | I28: =SUM(I23:I27) -> 1734555900 | J28: =+IFERROR(K28/I28,"-") -> 0.34536953 | K28: =SUM(K23:K27) -> 599062750 | L28: =SUM(L23:L27) -> 1135493150 | O28: =+IFERROR(P28/$I28,"-") -> 0.17432647 | P28: =SUM(P23:P27) -> 302379000 | Q28: =SUM(Q23:Q27) -> 302379000 | R28: =+P28-Q28 -> 0 | V28: =+IFERROR(W28/$I28,"-") -> 0.037867762 | W28: =SUM(W23:W27) -> 65683750 | X28: =SUM(X23:X27) -> 65683750 | Y28: =+W28-X28 -> 0 | AC28: =+IFERROR(AD28/$I28,"-") -> 0.14279785 | AD28: =SUM(AD23:AD27) -> 2.4769085e+08 | AE28: =SUM(AE23:AE27) -> 231000000 | AF28: =+AD28-AE28 -> 16690850 | AJ28: =+IFERROR(AK28/$I28,"-") -> 0 | AK28: =SUM(AK23:AK27) -> 0 | AL28: =SUM(AL23:AL27) -> 231000000 | AM28: =+AK28-AL28 -> -231000000 | AQ28: =+IFERROR(AR28/$I28,"-") -> 0.35023772 | AR28: =SUM(AR23:AR27) -> 607506900 | AS28: =SUM(AS23:AS27) -> 0 | AT28: =+AR28-AS28 -> 607506900 | AX28: =+IFERROR(AY28/$I28,"-") -> 0 | AY28: =SUM(AY23:AY27) -> 0 | AZ28: =SUM(AZ23:AZ27) -> 0 | BA28: =+AY28-AZ28 -> 0 | BE28: =+IFERROR(BF28/$I28,"-") -> 0.16640254 | BF28: =SUM(BF23:BF27) -> 288634500 | BG28: =SUM(BG23:BG27) -> 0 | BH28: =+BF28-BG28 -> 288634500 | BL28: =+IFERROR(BM28/$I28,"-") -> 0.12836767 | BM28: =SUM(BM23:BM27) -> 222660900 | BN28: =SUM(BN23:BN27) -> 0 | BO28: =+BM28-BN28 -> 222660900
B29: 4 | C29: YJ GASI 2 | D29: 999.6 | E29: Solar city | F29: CAPEX | G29: =+'PAYMENT RATIO_RAW'!F$5*$D$29/1000+27500000*D$29/1000 -> 1077069000 | H29: =+G29*10% -> 107706900 | I29: =SUM(G29:H29) -> 1184775900 | J29: =+IFERROR(K29/I29,"-") -> 0.19497358 | K29: =+IFERROR(Q29+X29+AE29+AS29+AZ29+BG29+BN29,"-") -> 231000000 | L29: =+I29-K29 -> 953775900 | P29: =+$I29*'PAYMENT RATIO_RAW'!G$5 -> 0 | R29: =+P29-Q29 -> 0 | W29: =+$I29*'PAYMENT RATIO_RAW'!N$5 -> 0 | Y29: =+W29-X29 -> 0 | AA29: =+$AA$11 -> 45920 | AB29: 45915 | AC29: =+IFERROR(AD29/$I29,"-") -> 0.19489559 | AD29: =+'PAYMENT RATIO_RAW'!$U$60*$D29*1050000000/1000*1.1 -> 2.309076e+08 | AE29: 231000000 | AF29: =+AD29-AE29 -> -92400 | AG29: 선급금20% | AH29: =+EDATE(AO29,0) -> 45950 | AI29: 45980 | AJ29: =+IFERROR(AK29/$I29,"-") -> 0 | AK29: =+'PAYMENT RATIO_RAW'!AB$60*$I29 -> 0 | AL29: 231000000 | AM29: =+AK29-AL29 -> -231000000 | AO29: =+EDATE(AV29,0)-10 -> 45950 | AQ29: =+IFERROR(AR29/$I29,"-") -> 0.51276102 | AR29: =+'PAYMENT RATIO_RAW'!AI$60*$D29*1050000000/1000*1.1+27500000*$D29/1000*1.1 -> 607506900 | AT29: =+AR29-AS29 -> 607506900 | AV29: =+EDATE(BC29,-1) -> 45960 | AX29: =+IFERROR(AY29/$I29,"-") -> 0 | AY29: =+'PAYMENT RATIO_RAW'!AP$60*$I29 -> 0 | BA29: =+AY29-AZ29 -> 0 | BC29: =+EDATE(BJ29,-1) -> 45991 | BE29: =+IFERROR(BF29/$I29,"-") -> 0.24361949 | BF29: =+'PAYMENT RATIO_RAW'!AW$60*$D29*1050000000/1000*1.1 -> 288634500 | BH29: =+BF29-BG29 -> 288634500 | BJ29: 46022 | BL29: =+IFERROR(BM29/$I29,"-") -> 0.048723898 | BM29: =+'PAYMENT RATIO_RAW'!BD$60*$D29*1050000000/1000*1.1 -> 57726900 | BO29: =+BM29-BN29 -> 57726900 | BR29: =+P29+W29+AD29+AK29+AR29+AY29+BF29+BM29=I29 -> TRUE | BS29: =+Q29+X29+AE29+AS29+AZ29+BG29+BN29=K29 -> TRUE
F30: DEVEX | G30: =+'PAYMENT RATIO_RAW'!F$6*'GM Batch1'!$D$29/1000 -> 549780000 | I30: =SUM(G30:H30) -> 549780000 | J30: =+IFERROR(K30/I30,"-") -> 0.66947279 | K30: =+IFERROR(Q30+X30+AE30+AS30+AZ30+BG30+BN30,"-") -> 368062750 | L30: =+I30-K30 -> 181717250 | M30: 45450 | N30: 45450 | O30: =+IFERROR(P30/$I30,"-") -> 0.55 | P30: =+$I30*'PAYMENT RATIO_RAW'!G$6 -> 302379000 | Q30: 302379000 | R30: =+P30-Q30 -> 0 | T30: 45456 | U30: 45456 | V30: =+IFERROR(W30/$I30,"-") -> 0.11947279 | W30: =+$I30*'PAYMENT RATIO_RAW'!N$6-16783250 -> 65683750 | X30: 65683750 | Y30: =+W30-X30 -> 0 | AA30: 45950 | AC30: =+IFERROR(AD30/$I30,"-") -> 0.030527211 | AD30: =+$I30*'PAYMENT RATIO_RAW'!U$6+16783250 -> 16783250 | AF30: =+AD30-AE30 -> 16783250 | AJ30: =+IFERROR(AK30/$I30,"-") -> 0 | AK30: =+$I30*'PAYMENT RATIO_RAW'!AB50 -> 0 | AM30: =+AK30-AL30 -> 0 | AR30: =+$I30*'PAYMENT RATIO_RAW'!AI$6 -> 0 | AT30: =+AR30-AS30 -> 0 | AY30: =+$I30*'PAYMENT RATIO_RAW'!AP$6 -> 0 | BA30: =+AY30-AZ30 -> 0 | BE30: =+IFERROR(BF30/$I30,"-") -> 0 | BF30: =+$I30*'PAYMENT RATIO_RAW'!AW$6 -> 0 | BH30: =+BF30-BG30 -> 0 | BJ30: =+BJ29 -> 46022 | BL30: =+IFERROR(BM30/$I30,"-") -> 0.3 | BM30: =+$I30*'PAYMENT RATIO_RAW'!BD$6 -> 164934000 | BO30: =+BM30-BN30 -> 164934000 | BR30: =+P30+W30+AD30+AR30+AY30+BF30+BM30=I30 -> TRUE | BS30: =+Q30+X30+AE30+AS30+AZ30+BG30+BN30=K30 -> TRUE | BT30: =+BF30+BF32+AY30+AY32+AR30+AR32+AD30+AD32+W30+W32+P30+P32+BM30+BM32=('PAYMENT RATIO_RAW'!$F$6+'PAYMENT RATIO_RAW'!$F$8)*D29/1000 -> TRUE
F31: Land Purchase | G31: =+'PAYMENT RATIO_RAW'!F$7*'GM Batch1'!$D$29/1000 -> 0 | I31: =SUM(G31:H31) -> 0 | J31: =+IFERROR(K31/I31,"-") -> - | K31: =+IFERROR(Q31+X31+AE31+AS31+AZ31+BG31+BN31,"-") -> 0 | L31: =+I31-K31 -> 0 | O31: =+IFERROR(P31/$I31,"-") -> - | P31: =+$I31*'PAYMENT RATIO_RAW'!G$7 -> 0 | R31: =+P31-Q31 -> 0 | V31: =+IFERROR(W31/$I31,"-") -> - | W31: =+$I31*'PAYMENT RATIO_RAW'!N$7 -> 0 | Y31: =+W31-X31 -> 0 | AC31: =+IFERROR(AD31/$I31,"-") -> - | AD31: =+$I31*'PAYMENT RATIO_RAW'!U$7 -> 0 | AF31: =+AD31-AE31 -> 0 | AJ31: =+IFERROR(AK31/$I31,"-") -> - | AK31: =+$I31*'PAYMENT RATIO_RAW'!AB51 -> 0 | AM31: =+AK31-AL31 -> 0 | AR31: =+$I31*'PAYMENT RATIO_RAW'!AI$7 -> 0 | AT31: =+AR31-AS31 -> 0 | AY31: =+$I31*'PAYMENT RATIO_RAW'!AP$7 -> 0 | BA31: =+AY31-AZ31 -> 0 | BE31: =+IFERROR(BF31/$I31,"-") -> - | BF31: =+$I31*'PAYMENT RATIO_RAW'!AW$7 -> 0 | BH31: =+BF31-BG31 -> 0 | BL31: =+IFERROR(BM31/$I31,"-") -> - | BM31: =+$I31*'PAYMENT RATIO_RAW'!BD$7 -> 0 | BO31: =+BM31-BN31 -> 0 | BR31: =+P31+W31+AD31+AR31+AY31+BF31+BM31=I31 -> TRUE | BS31: =+Q31+X31+AE31+AS31+AZ31+BG31+BN31=K31 -> TRUE
F32: Brokerage+Finder fee | G32: =+'PAYMENT RATIO_RAW'!F$8*'GM Batch1'!$D$29/1000 -> 0 | H32: =+G32*10% -> 0 | I32: =SUM(G32:H32) -> 0 | J32: =+IFERROR(K32/I32,"-") -> - | K32: =+IFERROR(Q32+X32+AE32+AS32+AZ32+BG32+BN32,"-") -> 0 | L32: =+I32-K32 -> 0 | O32: =+IFERROR(P32/$I32,"-") -> - | P32: =+$I32*'PAYMENT RATIO_RAW'!G$8 -> 0 | R32: =+P32-Q32 -> 0 | V32: =+IFERROR(W32/$I32,"-") -> - | W32: =+$I32*'PAYMENT RATIO_RAW'!N$8 -> 0 | Y32: =+W32-X32 -> 0 | AC32: =+IFERROR(AD32/$I32,"-") -> - | AD32: =+$I32*'PAYMENT RATIO_RAW'!U$8 -> 0 | AF32: =+AD32-AE32 -> 0 | AJ32: =+IFERROR(AK32/$I32,"-") -> - | AM32: =+AK32-AL32 -> 0 | AR32: =+$I32*'PAYMENT RATIO_RAW'!AI$8 -> 0 | AT32: =+AR32-AS32 -> 0 | AY32: =+$I32*'PAYMENT RATIO_RAW'!AP$8 -> 0 | BA32: =+AY32-AZ32 -> 0 | BE32: =+IFERROR(BF32/$I32,"-") -> - | BF32: =+$I32*'PAYMENT RATIO_RAW'!AW$8 -> 0 | BH32: =+BF32-BG32 -> 0 | BL32: =+IFERROR(BM32/$I32,"-") -> - | BM32: =+$I32*'PAYMENT RATIO_RAW'!BD$8 -> 0 | BO32: =+BM32-BN32 -> 0 | BR32: =+P32+W32+AD32+AR32+AY32+BF32+BM32=I32 -> TRUE | BS32: =+Q32+X32+AE32+AS32+AZ32+BG32+BN32=K32 -> TRUE
F33: Pre-payment Amount | G33: =+'PAYMENT RATIO_RAW'!F$9*'GM Batch1'!$D$29/1000 -> 0 | H33: =+G33*0.1 -> 0 | I33: =SUM(G33:H33) -> 0 | J33: =+IFERROR(K33/I33,"-") -> - | K33: =+IFERROR(Q33+X33+AE33+AS33+AZ33+BG33+BN33,"-") -> 0 | L33: =+I33-K33 -> 0 | P33: =+$I33*'PAYMENT RATIO_RAW'!G$9 -> 0 | R33: =+P33-Q33 -> 0 | W33: =+$I33*'PAYMENT RATIO_RAW'!N$9 -> 0 | Y33: =+W33-X33 -> 0 | AD33: =+$I33*'PAYMENT RATIO_RAW'!U$9 -> 0 | AF33: =+AD33-AE33 -> 0 | AR33: =+$I33*'PAYMENT RATIO_RAW'!AI$9 -> 0 | AY33: =+$I33*'PAYMENT RATIO_RAW'!AP$9 -> 0 | BE33: =+IFERROR(BF33/$I33,"-") -> - | BF33: =+$I33*'PAYMENT RATIO_RAW'!AW$9 -> 0 | BH33: =+BF33-BG33 -> 0 | BL33: =+IFERROR(BM33/$I33,"-") -> - | BM33: =+$I33*'PAYMENT RATIO_RAW'!BD$9 -> 0 | BO33: =+BM33-BN33 -> 0 | BR33: =+P33+W33+AD33+AR33+AY33+BF33+BM33=I33 -> TRUE | BS33: =+Q33+X33+AE33+AS33+AZ33+BG33+BN33=K33 -> TRUE
F34: Total | G34: =SUM(G29:G33) -> 1626849000 | H34: =SUM(H29:H33) -> 107706900 | I34: =SUM(I29:I33) -> 1734555900 | J34: =+IFERROR(K34/I34,"-") -> 0.34536953 | K34: =SUM(K29:K33) -> 599062750 | L34: =SUM(L29:L33) -> 1135493150 | O34: =+IFERROR(P34/$I34,"-") -> 0.17432647 | P34: =SUM(P29:P33) -> 302379000 | Q34: =SUM(Q29:Q33) -> 302379000 | R34: =+P34-Q34 -> 0 | V34: =+IFERROR(W34/$I34,"-") -> 0.037867762 | W34: =SUM(W29:W33) -> 65683750 | X34: =SUM(X29:X33) -> 65683750 | Y34: =+W34-X34 -> 0 | AC34: =+IFERROR(AD34/$I34,"-") -> 0.14279785 | AD34: =SUM(AD29:AD33) -> 2.4769085e+08 | AE34: =SUM(AE29:AE33) -> 231000000 | AF34: =+AD34-AE34 -> 16690850 | AJ34: =+IFERROR(AK34/$I34,"-") -> 0 | AK34: =SUM(AK29:AK33) -> 0 | AL34: =SUM(AL29:AL33) -> 231000000 | AM34: =+AK34-AL34 -> -231000000 | AQ34: =+IFERROR(AR34/$I34,"-") -> 0.35023772 | AR34: =SUM(AR29:AR33) -> 607506900 | AS34: =SUM(AS29:AS33) -> 0 | AT34: =+AR34-AS34 -> 607506900 | AX34: =+IFERROR(AY34/$I34,"-") -> 0 | AY34: =SUM(AY29:AY33) -> 0 | AZ34: =SUM(AZ29:AZ33) -> 0 | BA34: =+AY34-AZ34 -> 0 | BE34: =+IFERROR(BF34/$I34,"-") -> 0.16640254 | BF34: =SUM(BF29:BF33) -> 288634500 | BG34: =SUM(BG29:BG33) -> 0 | BH34: =+BF34-BG34 -> 288634500 | BL34: =+IFERROR(BM34/$I34,"-") -> 0.12836767 | BM34: =SUM(BM29:BM33) -> 222660900 | BN34: =SUM(BN29:BN33) -> 0 | BO34: =+BM34-BN34 -> 222660900
B35: 5 | C35: Dream 1 | D35: 999.24 | E35: Solar city | F35: CAPEX | G35: =+'PAYMENT RATIO_RAW'!F$5*$D$35/1000+27500000*D$35/1000 -> 1076681100 | H35: =+G35*10% -> 107668110 | I35: =SUM(G35:H35) -> 1184349210 | J35: =+IFERROR(K35/I35,"-") -> 0 | K35: =+IFERROR(Q35+X35+AE35+AS35+AZ35+BG35+BN35,"-") -> 0 | L35: =+I35-K35 -> 1184349210 | P35: =+$I35*'PAYMENT RATIO_RAW'!G$5 -> 0 | R35: =+P35-Q35 -> 0 | W35: =+$I35*'PAYMENT RATIO_RAW'!N$5 -> 0 | Y35: =+W35-X35 -> 0 | AA35: =+EDATE(AH35,-2) -> 46052 | AC35: =+IFERROR(AD35/$I35,"-") -> 0.19489559 | AD35: =+'PAYMENT RATIO_RAW'!$U$60*$D35*1050000000/1000*1.1 -> 2.3082444e+08 | AF35: =+AD35-AE35 -> 2.3082444e+08 | AH35: =+EDATE(AO35,-1) -> 46111 | AJ35: =+IFERROR(AK35/$I35,"-") -> 0 | AK35: =+'PAYMENT RATIO_RAW'!$AB65*I35 -> 0 | AM35: =+AK35-AL35 -> 0 | AO35: =+EDATE(AV35,-1) -> 46142 | AQ35: =+IFERROR(AR35/$I35,"-") -> 0.51276102 | AR35: =+'PAYMENT RATIO_RAW'!AI$60*$D35*1050000000/1000*1.1+27500000*$D35/1000*1.1 -> 607288110 | AT35: =+AR35-AS35 -> 607288110 | AV35: =+EDATE(BC35,-1) -> 46172 | AX35: =+IFERROR(AY35/$I35,"-") -> 0 | AY35: =+'PAYMENT RATIO_RAW'!AP65*$I35 -> 0 | BA35: =+AY35-AZ35 -> 0 | BC35: =+EDATE(BJ35,-1) -> 46203 | BE35: =+IFERROR(BF35/$I35,"-") -> 0.24361949 | BF35: =+'PAYMENT RATIO_RAW'!AW$60*$D35*1050000000/1000*1.1 -> 288530550 | BH35: =+BF35-BG35 -> 288530550 | BJ35: 46233 | BL35: =+IFERROR(BM35/$I35,"-") -> 0.048723898 | BM35: =+'PAYMENT RATIO_RAW'!BD$60*$D35*1050000000/1000*1.1 -> 57706110 | BO35: =+BM35-BN35 -> 57706110 | BR35: =+P35+W35+AD35+AK35+AR35+AY35+BF35+BM35=I35 -> TRUE | BS35: =+Q35+X35+AE35+AS35+AZ35+BG35+BN35=K35 -> TRUE
F36: DEVEX | G36: =+'PAYMENT RATIO_RAW'!F$6*'GM Batch1'!$D$35/1000 -> 549582000 | I36: =SUM(G36:H36) -> 549582000 | J36: =+IFERROR(K36/I36,"-") -> 0.62115408 | K36: =+IFERROR(Q36+X36+AE36+AS36+AZ36+BG36+BN36,"-") -> 341375100 | L36: =+I36-K36 -> 208206900 | M36: 45450 | N36: 45450 | O36: =+IFERROR(P36/$I36,"-") -> 0.55 | P36: =+$I36*'PAYMENT RATIO_RAW'!G$6 -> 302270100 | Q36: 302270100 | R36: =+P36-Q36 -> 0 | T36: 45456 | U36: 45456 | V36: =+IFERROR(W36/$I36,"-") -> 0.071154077 | W36: =+$I36*'PAYMENT RATIO_RAW'!N$6-43332300 -> 39105000 | X36: 39105000 | Y36: =+W36-X36 -> 0 | AA36: 46022 | AC36: =+IFERROR(AD36/$I36,"-") -> 0.078845923 | AD36: =+$I36*'PAYMENT RATIO_RAW'!U$6+43332300 -> 43332300 | AF36: =+AD36-AE36 -> 43332300 | AJ36: =+IFERROR(AK36/$I36,"-") -> 0 | AK36: =+'PAYMENT RATIO_RAW'!$AB66*I36 -> 0 | AM36: =+AK36-AL36 -> 0 | AR36: =+$I36*'PAYMENT RATIO_RAW'!AI$6 -> 0 | AT36: =+AR36-AS36 -> 0 | AY36: =+$I36*'PAYMENT RATIO_RAW'!AP$6 -> 0 | BA36: =+AY36-AZ36 -> 0 | BE36: =+IFERROR(BF36/$I36,"-") -> 0 | BF36: =+$I36*'PAYMENT RATIO_RAW'!AW$6 -> 0 | BH36: =+BF36-BG36 -> 0 | BJ36: =+BJ35 -> 46233 | BL36: =+IFERROR(BM36/$I36,"-") -> 0.3 | BM36: =+$I36*'PAYMENT RATIO_RAW'!BD$6 -> 164874600 | BO36: =+BM36-BN36 -> 164874600 | BR36: =+P36+W36+AD36+AR36+AY36+BF36+BM36=I36 -> TRUE | BS36: =+Q36+X36+AE36+AS36+AZ36+BG36+BN36=K36 -> TRUE | BT36: =+BF36+BF38+AY36+AY38+AR36+AR38+AD36+AD38+W36+W38+P36+P38+BM36+BM38=('PAYMENT RATIO_RAW'!$F$6+'PAYMENT RATIO_RAW'!$F$8)*D35/1000 -> TRUE
F37: Land Purchase | G37: =+'PAYMENT RATIO_RAW'!F$7*'GM Batch1'!$D$35/1000 -> 0 | I37: =SUM(G37:H37) -> 0 | J37: =+IFERROR(K37/I37,"-") -> - | K37: =+IFERROR(Q37+X37+AE37+AS37+AZ37+BG37+BN37,"-") -> 0 | L37: =+I37-K37 -> 0 | O37: =+IFERROR(P37/$I37,"-") -> - | P37: =+$I37*'PAYMENT RATIO_RAW'!G$7 -> 0 | R37: =+P37-Q37 -> 0 | V37: =+IFERROR(W37/$I37,"-") -> - | W37: =+$I37*'PAYMENT RATIO_RAW'!N$7 -> 0 | Y37: =+W37-X37 -> 0 | AC37: =+IFERROR(AD37/$I37,"-") -> - | AD37: =+$I37*'PAYMENT RATIO_RAW'!U$7 -> 0 | AF37: =+AD37-AE37 -> 0 | AJ37: =+IFERROR(AK37/$I37,"-") -> - | AK37: =+'PAYMENT RATIO_RAW'!$AB67*I37 -> 0 | AM37: =+AK37-AL37 -> 0 | AR37: =+$I37*'PAYMENT RATIO_RAW'!AI$7 -> 0 | AT37: =+AR37-AS37 -> 0 | AY37: =+$I37*'PAYMENT RATIO_RAW'!AP$7 -> 0 | BA37: =+AY37-AZ37 -> 0 | BE37: =+IFERROR(BF37/$I37,"-") -> - | BF37: =+$I37*'PAYMENT RATIO_RAW'!AW$7 -> 0 | BH37: =+BF37-BG37 -> 0 | BL37: =+IFERROR(BM37/$I37,"-") -> - | BM37: =+$I37*'PAYMENT RATIO_RAW'!BD$7 -> 0 | BO37: =+BM37-BN37 -> 0 | BR37: =+P37+W37+AD37+AR37+AY37+BF37+BM37=I37 -> TRUE | BS37: =+Q37+X37+AE37+AS37+AZ37+BG37+BN37=K37 -> TRUE
F38: Brokerage+Finder fee | G38: =+'PAYMENT RATIO_RAW'!F$8*'GM Batch1'!$D$35/1000 -> 0 | H38: =+G38*10% -> 0 | I38: =SUM(G38:H38) -> 0 | J38: =+IFERROR(K38/I38,"-") -> - | K38: =+IFERROR(Q38+X38+AE38+AS38+AZ38+BG38+BN38,"-") -> 0 | L38: =+I38-K38 -> 0 | O38: =+IFERROR(P38/$I38,"-") -> - | P38: =+$I38*'PAYMENT RATIO_RAW'!G$8 -> 0 | R38: =+P38-Q38 -> 0 | V38: =+IFERROR(W38/$I38,"-") -> - | W38: =+$I38*'PAYMENT RATIO_RAW'!N$8 -> 0 | Y38: =+W38-X38 -> 0 | AC38: =+IFERROR(AD38/$I38,"-") -> - | AD38: =+$I38*'PAYMENT RATIO_RAW'!U$8 -> 0 | AF38: =+AD38-AE38 -> 0 | AJ38: =+IFERROR(AK38/$I38,"-") -> - | AK38: =+'PAYMENT RATIO_RAW'!$AB68*I38 -> 0 | AM38: =+AK38-AL38 -> 0 | AR38: =+$I38*'PAYMENT RATIO_RAW'!AI$8 -> 0 | AT38: =+AR38-AS38 -> 0 | AY38: =+$I38*'PAYMENT RATIO_RAW'!AP$8 -> 0 | BA38: =+AY38-AZ38 -> 0 | BE38: =+IFERROR(BF38/$I38,"-") -> - | BF38: =+$I38*'PAYMENT RATIO_RAW'!AW$8 -> 0 | BH38: =+BF38-BG38 -> 0 | BL38: =+IFERROR(BM38/$I38,"-") -> - | BM38: =+$I38*'PAYMENT RATIO_RAW'!BD$8 -> 0 | BO38: =+BM38-BN38 -> 0 | BR38: =+P38+W38+AD38+AR38+AY38+BF38+BM38=I38 -> TRUE | BS38: =+Q38+X38+AE38+AS38+AZ38+BG38+BN38=K38 -> TRUE
F39: Pre-payment Amount | G39: =+'PAYMENT RATIO_RAW'!F$9*'GM Batch1'!$D$35/1000 -> 0 | H39: =+G39*0.1 -> 0 | I39: =SUM(G39:H39) -> 0 | J39: =+IFERROR(K39/I39,"-") -> - | K39: =+IFERROR(Q39+X39+AE39+AS39+AZ39+BG39+BN39,"-") -> 0 | L39: =+I39-K39 -> 0 | P39: =+$I39*'PAYMENT RATIO_RAW'!G$9 -> 0 | R39: =+P39-Q39 -> 0 | W39: =+$I39*'PAYMENT RATIO_RAW'!N$9 -> 0 | Y39: =+W39-X39 -> 0 | AD39: =+$I39*'PAYMENT RATIO_RAW'!U$9 -> 0 | AF39: =+AD39-AE39 -> 0 | AK39: =+'PAYMENT RATIO_RAW'!$AB69*I39 -> 0 | AR39: =+$I39*'PAYMENT RATIO_RAW'!AI$9 -> 0 | AY39: =+$I39*'PAYMENT RATIO_RAW'!AP$9 -> 0 | BE39: =+IFERROR(BF39/$I39,"-") -> - | BF39: =+$I39*'PAYMENT RATIO_RAW'!AW$9 -> 0 | BH39: =+BF39-BG39 -> 0 | BL39: =+IFERROR(BM39/$I39,"-") -> - | BM39: =+$I39*'PAYMENT RATIO_RAW'!BD$9 -> 0 | BO39: =+BM39-BN39 -> 0 | BR39: =+P39+W39+AD39+AR39+AY39+BF39+BM39=I39 -> TRUE | BS39: =+Q39+X39+AE39+AS39+AZ39+BG39+BN39=K39 -> TRUE
F40: Total | G40: =SUM(G35:G39) -> 1626263100 | H40: =SUM(H35:H39) -> 107668110 | I40: =SUM(I35:I39) -> 1733931210 | J40: =+IFERROR(K40/I40,"-") -> 0.19687926 | K40: =SUM(K35:K39) -> 341375100 | L40: =SUM(L35:L39) -> 1392556110 | O40: =+IFERROR(P40/$I40,"-") -> 0.17432647 | P40: =SUM(P35:P39) -> 302270100 | Q40: =SUM(Q35:Q39) -> 302270100 | R40: =+P40-Q40 -> 0 | V40: =+IFERROR(W40/$I40,"-") -> 0.022552798 | W40: =SUM(W35:W39) -> 39105000 | X40: =SUM(X35:X39) -> 39105000 | Y40: =+W40-X40 -> 0 | AC40: =+IFERROR(AD40/$I40,"-") -> 0.15811281 | AD40: =SUM(AD35:AD39) -> 274156740 | AE40: =SUM(AE35:AE39) -> 0 | AF40: =+AD40-AE40 -> 274156740 | AJ40: =+IFERROR(AK40/$I40,"-") -> 0 | AK40: =SUM(AK35:AK39) -> 0 | AL40: =SUM(AL35:AL39) -> 0 | AM40: =+AK40-AL40 -> 0 | AQ40: =+IFERROR(AR40/$I40,"-") -> 0.35023772 | AR40: =SUM(AR35:AR39) -> 607288110 | AS40: =SUM(AS35:AS39) -> 0 | AT40: =+AR40-AS40 -> 607288110 | AX40: =+IFERROR(AY40/$I40,"-") -> 0 | AY40: =SUM(AY35:AY39) -> 0 | AZ40: =SUM(AZ35:AZ39) -> 0 | BA40: =+AY40-AZ40 -> 0 | BE40: =+IFERROR(BF40/$I40,"-") -> 0.16640254 | BF40: =SUM(BF35:BF39) -> 288530550 | BG40: =SUM(BG35:BG39) -> 0 | BH40: =+BF40-BG40 -> 288530550 | BL40: =+IFERROR(BM40/$I40,"-") -> 0.12836767 | BM40: =SUM(BM35:BM39) -> 222580710 | BN40: =SUM(BN35:BN39) -> 0 | BO40: =+BM40-BN40 -> 222580710
B41: 6 | C41: Dream 2 | D41: 999.24 | E41: Solar city | F41: CAPEX | G41: =+'PAYMENT RATIO_RAW'!F$5*$D$41/1000+27500000*D$41/1000 -> 1076681100 | H41: =+G41*10% -> 107668110 | I41: =SUM(G41:H41) -> 1184349210 | J41: =+IFERROR(K41/I41,"-") -> 0 | K41: =+IFERROR(Q41+X41+AE41+AS41+AZ41+BG41+BN41,"-") -> 0 | L41: =+I41-K41 -> 1184349210 | P41: =+$I41*'PAYMENT RATIO_RAW'!G$5 -> 0 | R41: =+P41-Q41 -> 0 | W41: =+$I41*'PAYMENT RATIO_RAW'!N$5 -> 0 | Y41: =+W41-X41 -> 0 | AA41: =+EDATE(AH41,-2) -> 46052 | AC41: =+IFERROR(AD41/$I41,"-") -> 0.19489559 | AD41: =+'PAYMENT RATIO_RAW'!$U$60*$D41*1050000000/1000*1.1 -> 2.3082444e+08 | AF41: =+AD41-AE41 -> 2.3082444e+08 | AH41: =+EDATE(AO41,-1) -> 46111 | AJ41: =+IFERROR(AK41/$I41,"-") -> 0 | AK41: =+'PAYMENT RATIO_RAW'!$AB65*I41 -> 0 | AM41: =+AK41-AL41 -> 0 | AO41: =+EDATE(AV41,-1) -> 46142 | AQ41: =+IFERROR(AR41/$I41,"-") -> 0.51276102 | AR41: =+'PAYMENT RATIO_RAW'!AI$60*$D41*1050000000/1000*1.1+27500000*$D41/1000*1.1 -> 607288110 | AT41: =+AR41-AS41 -> 607288110 | AV41: =+EDATE(BC41,-1) -> 46172 | AX41: =+IFERROR(AY41/$I41,"-") -> 0 | AY41: =+'PAYMENT RATIO_RAW'!AP65*$I41 -> 0 | BA41: =+AY41-AZ41 -> 0 | BC41: =+EDATE(BJ41,-1) -> 46203 | BE41: =+IFERROR(BF41/$I41,"-") -> 0.24361949 | BF41: =+'PAYMENT RATIO_RAW'!AW$60*$D41*1050000000/1000*1.1 -> 288530550 | BH41: =+BF41-BG41 -> 288530550 | BJ41: 46233 | BL41: =+IFERROR(BM41/$I41,"-") -> 0.048723898 | BM41: =+'PAYMENT RATIO_RAW'!BD$60*$D41*1050000000/1000*1.1 -> 57706110 | BO41: =+BM41-BN41 -> 57706110 | BR41: =+P41+W41+AD41+AK41+AR41+AY41+BF41+BM41=I41 -> TRUE | BS41: =+Q41+X41+AE41+AS41+AZ41+BG41+BN41=K41 -> TRUE
F42: DEVEX | G42: =+'PAYMENT RATIO_RAW'!F$6*'GM Batch1'!$D$41/1000 -> 549582000 | I42: =SUM(G42:H42) -> 549582000 | J42: =+IFERROR(K42/I42,"-") -> 0.62115408 | K42: =+IFERROR(Q42+X42+AE42+AS42+AZ42+BG42+BN42,"-") -> 341375100 | L42: =+I42-K42 -> 208206900 | M42: 45450 | N42: 45450 | O42: =+IFERROR(P42/$I42,"-") -> 0.55 | P42: =+$I42*'PAYMENT RATIO_RAW'!G$6 -> 302270100 | Q42: 302270100 | R42: =+P42-Q42 -> 0 | T42: 45456 | U42: 45456 | V42: =+IFERROR(W42/$I42,"-") -> 0.071154077 | W42: =+$I42*'PAYMENT RATIO_RAW'!N$6-43332300 -> 39105000 | X42: 39105000 | Y42: =+W42-X42 -> 0 | AA42: 46022 | AC42: =+IFERROR(AD42/$I42,"-") -> 0.078845923 | AD42: =+$I42*'PAYMENT RATIO_RAW'!U$6+43332300 -> 43332300 | AF42: =+AD42-AE42 -> 43332300 | AJ42: =+IFERROR(AK42/$I42,"-") -> 0 | AK42: =+'PAYMENT RATIO_RAW'!$AB66*I42 -> 0 | AM42: =+AK42-AL42 -> 0 | AR42: =+$I42*'PAYMENT RATIO_RAW'!AI$6 -> 0 | AT42: =+AR42-AS42 -> 0 | AY42: =+$I42*'PAYMENT RATIO_RAW'!AP$6 -> 0 | BA42: =+AY42-AZ42 -> 0 | BE42: =+IFERROR(BF42/$I42,"-") -> 0 | BF42: =+$I42*'PAYMENT RATIO_RAW'!AW$6 -> 0 | BH42: =+BF42-BG42 -> 0 | BJ42: =+BJ41 -> 46233 | BL42: =+IFERROR(BM42/$I42,"-") -> 0.3 | BM42: =+$I42*'PAYMENT RATIO_RAW'!BD$6 -> 164874600 | BO42: =+BM42-BN42 -> 164874600 | BR42: =+P42+W42+AD42+AR42+AY42+BF42+BM42=I42 -> TRUE | BS42: =+Q42+X42+AE42+AS42+AZ42+BG42+BN42=K42 -> TRUE | BT42: =+BF42+BF44+AY42+AY44+AR42+AR44+AD42+AD44+W42+W44+P42+P44+BM42+BM44=('PAYMENT RATIO_RAW'!$F$6+'PAYMENT RATIO_RAW'!$F$8)*D41/1000 -> TRUE
